Workbook

Sheet PAPER_VIEW
A1: PAPER INTELLIGENCE — SINGLE PAPER SCORECARD
A2: Paper row # in ALL_METRICS → | C2: =COUNTA(ALL_METRICS!A:A) -> 63 | D2: ← auto-tracks latest paper | override with any row number (2 = first paper) to pin a specific paper
A3: {=INDEX(ALL_METRICS!B:B,C2)} -> MDA-001-story-introduction.md | G3: {="Paper ID: "&INDEX(ALL_METRICS!A:A,C2)} -> Paper ID: P-d03a0e6c62da | J3: {="Words: "&INDEX(ALL_METRICS!J:J,C2)} -> Words: 958 | L3: {="Run: "&INDEX(ALL_METRICS!D:D,C2)} -> Run: 20260604_224847
A4: COMPOSITE SCORES — derived from raw metrics | 0–100 scale
A5: ✍ Writing | B5: 🎓 Acad. Rigor | C5: ⚛ Theophysics | D5: 🌿 Moral | E5: ❤ Emotion | F5: 💡 Idea Density | G5: ★ OVERALL
A6: {=ROUND( MIN(INDEX(ALL_METRICS!L:L,C2),0.6)/0.6*40 + MAX(0,(0.4-INDEX(ALL_METRICS!X:X,C2))/0.4)*20 + IF(INDEX(ALL_METRICS!AT:AT,C2)="A — Evidence-Rich",30,IF(LEFT(INDEX(ALL_METRICS!AT:AT,C2),1)="B",20,IF(LEFT(INDEX(ALL_METRICS!AT:AT,C2),1)="C",10,5))) + IF(AND(INDEX(ALL_METRICS!AM:AM,C2)>=6,INDEX(ALL_METRICS!AM:AM,C2)<=12),15,IF(INDEX(ALL_METRICS!AM:AM,C2)<6,10,5)),1)} -> 61.7 | B6: {=ROUND( MIN(INDEX(ALL_METRICS!EB:EB,C2),20)/20*50 + MIN(INDEX(ALL_METRICS!DC:DC,C2),5)/5*25 + MIN(INDEX(ALL_METRICS!DE:DE,C2),2)/2*15 + (1-MIN(ABS(INDEX(ALL_METRICS!DJ:DJ,C2)-0.5),0.5)/0.5)*10,1)} -> 31 | C6: =ROUND( MIN(INDEX(ALL_METRICS!EE:EE,C2),10)/10*40 + MIN(MAX(INDEX(ALL_METRICS!EI:EI,C2),0),3)/3*30 + MIN(INDEX(ALL_METRICS!EN:EN,C2),10)/10*30,1) -> 42.9 | D6: {=ROUND( INDEX(ALL_METRICS!FN:FN,C2)*30 + INDEX(ALL_METRICS!FO:FO,C2)*30 + INDEX(ALL_METRICS!FY:FY,C2)*25 + MAX(0,(1-INDEX(ALL_METRICS!FZ:FZ,C2)/0.5))*15,1)} -> 50.6 | E6: {=ROUND( MIN(INDEX(ALL_METRICS!LI:LI,C2),1)*50 + MAX(0,(1-INDEX(ALL_METRICS!LJ:LJ,C2)*5))*30 + MIN(MAX(INDEX(ALL_METRICS!LK:LK,C2),0),1)*20,1)} -> 57.8 | F6: {=ROUND(MIN(MAX(INDEX(ALL_METRICS!LX:LX,C2)-0.2,0)/0.45*100,100),1)} -> 63.6 | G6: =ROUND(AVERAGE(A6:F6),1) -> 51.3
A7: =IFERROR(AVERAGE(ALL_METRICS!L2:L62)*66.7&" ser.avg","—") -> 28.0100636065574 ser.avg | B7: =IFERROR(AVERAGE(ALL_METRICS!EB2:EB62)*2.5&" ser.avg","—") -> 27.3004098360656 ser.avg | C7: =IFERROR(AVERAGE(ALL_METRICS!EE2:EE62)*4&" ser.avg","—") -> 21.0806557377049 ser.avg | D7: =IFERROR(AVERAGE(ALL_METRICS!FN2:FN62)*30&" ser.avg","—") -> 16.4261803278689 ser.avg | E7: =IFERROR(AVERAGE(ALL_METRICS!LI2:LI62)*50&" ser.avg","—") -> 0 ser.avg | F7: =IFERROR(AVERAGE(ALL_METRICS!LX2:LX62)*222.2&" ser.avg","—") -> 119.669270491803 ser.avg | G7: ="ser. avg: "&ROUND(AVERAGE(A7:F7),1) -> #DIV/0!
A13: Metric | C13: This Paper | E13: Series Avg (n=61) | G13: Rank in Series
A14: ✍ WRITING QUALITY
A15: Word Count | C15: {=INDEX(ALL_METRICS!J:J,C2)} -> 958 | E15: =IFERROR(AVERAGE(ALL_METRICS!J2:J62),"") -> 1867.2787 | G15: {=IFERROR(RANK(INDEX(ALL_METRICS!J:J,C2),ALL_METRICS!J2:J62,0)&" / 62","")}
A16: Type-Token Ratio (lexical diversity) | C16: {=INDEX(ALL_METRICS!L:L,C2)} -> 0.3998 | E16: =IFERROR(AVERAGE(ALL_METRICS!L2:L62),"") -> 0.41994098 | G16: {=IFERROR(RANK(INDEX(ALL_METRICS!L:L,C2),ALL_METRICS!L2:L62,0)&" / 62","")}
A17: Avg Words per Sentence | C17: {=INDEX(ALL_METRICS!P:P,C2)} -> 14.7 | E17: =IFERROR(AVERAGE(ALL_METRICS!P2:P62),"") -> 18.160656 | G17: {=IFERROR(RANK(INDEX(ALL_METRICS!P:P,C2),ALL_METRICS!P2:P62,0)&" / 62","")}
A18: Passive Voice % | C18: {=INDEX(ALL_METRICS!X:X,C2)} -> 1 | E18: =IFERROR(AVERAGE(ALL_METRICS!X2:X62),"") -> 4.4213115 | G18: {=IFERROR(RANK(INDEX(ALL_METRICS!X:X,C2),ALL_METRICS!X2:X62,0)&" / 62","")}
A19: Argument Grade | C19: {=INDEX(ALL_METRICS!AT:AT,C2)} -> A — Evidence-Rich
A20: Flow Label | C20: {=INDEX(ALL_METRICS!AW:AW,C2)} -> MODERATE
A21: Flesch-Kincaid Grade | C21: {=INDEX(ALL_METRICS!AM:AM,C2)} -> MODERATE | E21: =IFERROR(AVERAGE(ALL_METRICS!AM2:AM62),"") | G21: {=IFERROR(RANK(INDEX(ALL_METRICS!AM:AM,C2),ALL_METRICS!AM2:AM62,0)&" / 62","")}
A22: Reading Time (min) | C22: {=INDEX(ALL_METRICS!AQ:AQ,C2)} -> 2.09 | E22: =IFERROR(AVERAGE(ALL_METRICS!AQ2:AQ62),"") -> 8.6095082 | G22: {=IFERROR(RANK(INDEX(ALL_METRICS!AQ:AQ,C2),ALL_METRICS!AQ2:AQ62,0)&" / 62","")}
A24: 🎓 ACADEMIC RIGOR (L2)
A25: Academic Grade | C25: {=INDEX(ALL_METRICS!ED:ED,C2)} -> F (Needs Citations)
A26: Academic Rubric Score /100 | C26: {=INDEX(ALL_METRICS!EB:EB,C2)} -> 8.38 | E26: =IFERROR(AVERAGE(ALL_METRICS!EB2:EB62),"") -> 10.920164 | G26: {=IFERROR(RANK(INDEX(ALL_METRICS!EB:EB,C2),ALL_METRICS!EB2:EB62,0)&" / 62","")}
A27: Citation Count | C27: {=INDEX(ALL_METRICS!CD:CD,C2)} -> 0 | E27: =IFERROR(AVERAGE(ALL_METRICS!CD2:CD62),"") -> 2.6229508 | G27: {=IFERROR(RANK(INDEX(ALL_METRICS!CD:CD,C2),ALL_METRICS!CD2:CD62,0)&" / 62","")} -> 11 / 62
A28: Evidence-to-Claim Ratio | C28: {=INDEX(ALL_METRICS!DC:DC,C2)} -> 2 | E28: =IFERROR(AVERAGE(ALL_METRICS!DC2:DC62),"") -> 11.848033 | G28: {=IFERROR(RANK(INDEX(ALL_METRICS!DC:DC,C2),ALL_METRICS!DC2:DC62,0)&" / 62","")}
A29: Falsifiability Density /1k words | C29: {=INDEX(ALL_METRICS!DE:DE,C2)} -> 0 | E29: =IFERROR(AVERAGE(ALL_METRICS!DE2:DE62),"") -> 0.64491803 | G29: {=IFERROR(RANK(INDEX(ALL_METRICS!DE:DE,C2),ALL_METRICS!DE2:DE62,0)&" / 62","")} -> 24 / 62
A30: Hedge-to-Absolute Ratio | C30: {=INDEX(ALL_METRICS!DJ:DJ,C2)} -> 0 | E30: =IFERROR(AVERAGE(ALL_METRICS!DJ2:DJ62),"") -> 0.55622951 | G30: {=IFERROR(RANK(INDEX(ALL_METRICS!DJ:DJ,C2),ALL_METRICS!DJ2:DJ62,0)&" / 62","")} -> 47 / 62
A31: Counterargument Count | C31: {=INDEX(ALL_METRICS!DK:DK,C2)} -> 0 | E31: =IFERROR(AVERAGE(ALL_METRICS!DK2:DK62),"") -> 0.31147541 | G31: {=IFERROR(RANK(INDEX(ALL_METRICS!DK:DK,C2),ALL_METRICS!DK2:DK62,0)&" / 62","")} -> 13 / 62
A32: Novelty Marker Count | C32: {=INDEX(ALL_METRICS!DN:DN,C2)} -> 0 | E32: =IFERROR(AVERAGE(ALL_METRICS!DN2:DN62),"") -> 0.32786885 | G32: {=IFERROR(RANK(INDEX(ALL_METRICS!DN:DN,C2),ALL_METRICS!DN2:DN62,0)&" / 62","")} -> 16 / 62
A34: ⚛ THEOPHYSICS (L3)
A35: χ (Chi) Coherence Score | C35: {=INDEX(ALL_METRICS!EE:EE,C2)} -> 3.46 | E35: =IFERROR(AVERAGE(ALL_METRICS!EE2:EE62),"") -> 5.2701639 | G35: {=IFERROR(RANK(INDEX(ALL_METRICS!EE:EE,C2),ALL_METRICS!EE2:EE62,0)&" / 62","")}
A36: χ Status | C36: {=INDEX(ALL_METRICS!EF:EF,C2)} -> WEAK
A37: Wisdom Score | C37: {=INDEX(ALL_METRICS!EG:EG,C2)} -> 1.43 | E37: =IFERROR(AVERAGE(ALL_METRICS!EG2:EG62),"") -> 0.4057377 | G37: {=IFERROR(RANK(INDEX(ALL_METRICS!EG:EG,C2),ALL_METRICS!EG2:EG62,0)&" / 62","")}
A38: Knowledge Score | C38: {=INDEX(ALL_METRICS!EH:EH,C2)} -> 0.61 | E38: =IFERROR(AVERAGE(ALL_METRICS!EH2:EH62),"") -> 1.9636066 | G38: {=IFERROR(RANK(INDEX(ALL_METRICS!EH:EH,C2),ALL_METRICS!EH2:EH62,0)&" / 62","")}
A39: Wisdom:Knowledge Ratio | C39: {=INDEX(ALL_METRICS!EI:EI,C2)} -> 2.333 | E39: =IFERROR(AVERAGE(ALL_METRICS!EI2:EI62),"") -> 0.26068852 | G39: {=IFERROR(RANK(INDEX(ALL_METRICS!EI:EI,C2),ALL_METRICS!EI2:EI62,0)&" / 62","")}
A40: Dominant Fruit of the Spirit | C40: {=INDEX(ALL_METRICS!EL:EL,C2)} -> goodness
A41: ME Avg Score (Master Equation) | C41: {=INDEX(ALL_METRICS!EN:EN,C2)} -> 1.9 | E41: =IFERROR(AVERAGE(ALL_METRICS!EN2:EN62),"") -> 1.7960656 | G41: {=IFERROR(RANK(INDEX(ALL_METRICS!EN:EN,C2),ALL_METRICS!EN2:EN62,0)&" / 62","")}
A42: Scripture References | C42: {=INDEX(ALL_METRICS!EQ:EQ,C2)} -> 0 | E42: =IFERROR(AVERAGE(ALL_METRICS!EQ2:EQ62),"") -> 1.0491803 | G42: {=IFERROR(RANK(INDEX(ALL_METRICS!EQ:EQ,C2),ALL_METRICS!EQ2:EQ62,0)&" / 62","")} -> 30 / 62
A43: Cross-Domain Bridges | C43: {=INDEX(ALL_METRICS!EP:EP,C2)} -> 0 | E43: =IFERROR(AVERAGE(ALL_METRICS!EP2:EP62),"") -> 0.32786885 | G43: {=IFERROR(RANK(INDEX(ALL_METRICS!EP:EP,C2),ALL_METRICS!EP2:EP62,0)&" / 62","")} -> 13 / 62
A45: 🌿 MORAL & SPIRITUAL POSTURE (L6)
A46: Truth Score | C46: {=INDEX(ALL_METRICS!FN:FN,C2)} -> 0.5343 | E46: =IFERROR(AVERAGE(ALL_METRICS!FN2:FN62),"") -> 0.54753934 | G46: {=IFERROR(RANK(INDEX(ALL_METRICS!FN:FN,C2),ALL_METRICS!FN2:FN62,0)&" / 62","")}
A47: Coherence Score | C47: {=INDEX(ALL_METRICS!FO:FO,C2)} -> 0.3618 | E47: =IFERROR(AVERAGE(ALL_METRICS!FO2:FO62),"") -> 0.775 | G47: {=IFERROR(RANK(INDEX(ALL_METRICS!FO:FO,C2),ALL_METRICS!FO2:FO62,0)&" / 62","")}
A48: Fruit Integrity Score | C48: {=INDEX(ALL_METRICS!FY:FY,C2)} -> 0.4694 | E48: =IFERROR(AVERAGE(ALL_METRICS!FY2:FY62),"") -> 0.28967705 | G48: {=IFERROR(RANK(INDEX(ALL_METRICS!FY:FY,C2),ALL_METRICS!FY2:FY62,0)&" / 62","")}
A49: Anti-Fruit Pressure | C49: {=INDEX(ALL_METRICS!FZ:FZ,C2)} -> 0.1005 | E49: =IFERROR(AVERAGE(ALL_METRICS!FZ2:FZ62),"") -> 0.0083786885 | G49: {=IFERROR(RANK(INDEX(ALL_METRICS!FZ:FZ,C2),ALL_METRICS!FZ2:FZ62,0)&" / 62","")}
A50: Character Posture | C50: {=INDEX(ALL_METRICS!JD:JD,C2)} -> agitated or reactionary; charitable; disciplined; morally unstable; technically strong, spiritually ordered
A51: Warmth Score | C51: {=INDEX(ALL_METRICS!FV:FV,C2)} -> 0.1484 | E51: =IFERROR(AVERAGE(ALL_METRICS!FV2:FV62),"") -> 0.16077049 | G51: {=IFERROR(RANK(INDEX(ALL_METRICS!FV:FV,C2),ALL_METRICS!FV2:FV62,0)&" / 62","")}
A52: Discipline Score | C52: {=INDEX(ALL_METRICS!FW:FW,C2)} -> 0.2262 | E52: =IFERROR(AVERAGE(ALL_METRICS!FW2:FW62),"") -> 0.028963934 | G52: {=IFERROR(RANK(INDEX(ALL_METRICS!FW:FW,C2),ALL_METRICS!FW2:FW62,0)&" / 62","")}
A53: Anchored Claims | C53: {=INDEX(ALL_METRICS!GF:GF,C2)} -> 15 | E53: =IFERROR(AVERAGE(ALL_METRICS!GF2:GF62),"") -> 22.311475 | G53: {=IFERROR(RANK(INDEX(ALL_METRICS!GF:GF,C2),ALL_METRICS!GF2:GF62,0)&" / 62","")} -> 40 / 62
A54: Overstated Claims | C54: {=INDEX(ALL_METRICS!GI:GI,C2)} -> 0 | E54: =IFERROR(AVERAGE(ALL_METRICS!GI2:GI62),"") -> 0.1147541 | G54: {=IFERROR(RANK(INDEX(ALL_METRICS!GI:GI,C2),ALL_METRICS!GI2:GI62,0)&" / 62","")} -> 7 / 62
A56: ❤ EMOTION PROFILE (L8)
A57: Fruit Emotion Composite | C57: {=INDEX(ALL_METRICS!LI:LI,C2)} -> 0.4018 | E57: =IFERROR(AVERAGE(ALL_METRICS!LI2:LI62),"") -> 0 | G57: {=IFERROR(RANK(INDEX(ALL_METRICS!LI:LI,C2),ALL_METRICS!LI2:LI62,0)&" / 62","")}
A58: Anti-Emotion Composite | C58: {=INDEX(ALL_METRICS!LJ:LJ,C2)} -> 0.0021 | E58: =IFERROR(AVERAGE(ALL_METRICS!LJ2:LJ62),"") -> 0 | G58: {=IFERROR(RANK(INDEX(ALL_METRICS!LJ:LJ,C2),ALL_METRICS!LJ2:LJ62,0)&" / 62","")}
A59: Net Emotional Score | C59: {=INDEX(ALL_METRICS!LK:LK,C2)} -> 0.3997 | E59: =IFERROR(AVERAGE(ALL_METRICS!LK2:LK62),"") -> 0 | G59: {=IFERROR(RANK(INDEX(ALL_METRICS!LK:LK,C2),ALL_METRICS!LK2:LK62,0)&" / 62","")}
A60: Dominant Emotion | C60: {=INDEX(ALL_METRICS!LL:LL,C2)} -> confusion
A61: NRC Trust | C61: {=INDEX(ALL_METRICS!JT:JT,C2)} -> 0.0542 | E61: =IFERROR(AVERAGE(ALL_METRICS!JT2:JT62),"") -> 0 | G61: {=IFERROR(RANK(INDEX(ALL_METRICS!JT:JT,C2),ALL_METRICS!JT2:JT62,0)&" / 62","")}
A62: NRC Positive | C62: {=INDEX(ALL_METRICS!JX:JX,C2)} -> 0 | E62: =IFERROR(AVERAGE(ALL_METRICS!JX2:JX62),"") | G62: {=IFERROR(RANK(INDEX(ALL_METRICS!JX:JX,C2),ALL_METRICS!JX2:JX62,0)&" / 62","")}
A63: NRC Negative | C63: {=INDEX(ALL_METRICS!JY:JY,C2)} -> 0.4001 | E63: =IFERROR(AVERAGE(ALL_METRICS!JY2:JY62),"") -> 0 | G63: {=IFERROR(RANK(INDEX(ALL_METRICS!JY:JY,C2),ALL_METRICS!JY2:JY62,0)&" / 62","")}
A65: 💡 IDEA DENSITY (L10)
A66: Mean Idea Density | C66: {=INDEX(ALL_METRICS!LX:LX,C2)} -> 0.4864 | E66: =IFERROR(AVERAGE(ALL_METRICS!LX2:LX62),"") -> 0.53856557 | G66: {=IFERROR(RANK(INDEX(ALL_METRICS!LX:LX,C2),ALL_METRICS!LX2:LX62,0)&" / 62","")}
A67: Idea Density Level | C67: {=INDEX(ALL_METRICS!ME:ME,C2)} -> HIGH (academic)
A68: Total Propositions | C68: {=INDEX(ALL_METRICS!LB:LB,C2)} -> 0 | E68: =IFERROR(AVERAGE(ALL_METRICS!LB2:LB62),"") -> 0 | G68: {=IFERROR(RANK(INDEX(ALL_METRICS!LB:LB,C2),ALL_METRICS!LB2:LB62,0)&" / 62","")} -> 1 / 62
A69: Paragraphs Analyzed | C69: {=INDEX(ALL_METRICS!LC:LC,C2)} -> 0.0002 | E69: =IFERROR(AVERAGE(ALL_METRICS!LC2:LC62),"") -> 0 | G69: {=IFERROR(RANK(INDEX(ALL_METRICS!LC:LC,C2),ALL_METRICS!LC2:LC62,0)&" / 62","")}
A71: SOURCE: ALL_METRICS | DASHBOARD tab for multi-paper view | CHANGELOG for column tracking

Sheet CHANGELOG
A1: timestamp | B1: original_column_name | C1: original_sheet | D1: original_col_index | E1: new_sheet | F1: new_col_or_cell | G1: change_type | H1: notes
A3: --- CHANGE TYPE LEGEND ---
A4: MOVED_TO_DASHBOARD | B4: Column surfaced on DASHBOARD sheet as a key metric
A5: HIDDEN | B5: Column hidden in ALL_METRICS (data still there)
A6: GROUPED | B6: Columns grouped under a collapsible section header
A7: RENAMED_DISPLAY | B7: Display label changed; original column name unchanged in row 2
A8: REORDERED | B8: Column moved to a new position within ALL_METRICS
A9: --- CHANGE LOG (newest first) ---
A10: 46177 | B10: file | C10: ALL_METRICS | D10: B | E10: DASHBOARD | F10: A | G10: MOVED_TO_DASHBOARD | H10: Article name (filename). Full path still in ALL_METRICS col B
A11: 46177 | B11: paper_id | C11: ALL_METRICS | D11: A | E11: DASHBOARD | F11: B | G11: MOVED_TO_DASHBOARD | H11: Paper identifier
A12: 46177 | B12: PA_s_word_count | C12: ALL_METRICS | D12: J | E12: DASHBOARD | F12: C | G12: MOVED_TO_DASHBOARD | H12: Total word count
A13: 46177 | B13: PA_s_ttr | C13: ALL_METRICS | D13: L | E13: DASHBOARD | F13: D | G13: MOVED_TO_DASHBOARD | H13: Type-Token Ratio — lexical diversity (0-1)
A14: 46177 | B14: PA_s_avg_words_per_sentence | C14: ALL_METRICS | D14: P | E14: DASHBOARD | F14: E | G14: MOVED_TO_DASHBOARD | H14: Avg words/sentence — sentence complexity
A15: 46177 | B15: PA_g_passive_pct | C15: ALL_METRICS | D15: X | E15: DASHBOARD | F15: F | G15: MOVED_TO_DASHBOARD | H15: Passive voice % — academic register signal
A16: 46177 | B16: PA_a_argument_grade | C16: ALL_METRICS | D16: AT | E16: DASHBOARD | F16: G | G16: MOVED_TO_DASHBOARD | H16: Argument quality grade (letter)
A17: 46177 | B17: PA_f_flow_label | C17: ALL_METRICS | D17: AW | E17: DASHBOARD | F17: H | G17: MOVED_TO_DASHBOARD | H17: Prose flow label
A18: 46177 | B18: L2_academic_grade | C18: ALL_METRICS | D18: ED | E18: DASHBOARD | F18: I | G18: MOVED_TO_DASHBOARD | H18: Academic rigor letter grade
A19: 46177 | B19: L2_citation_count | C19: ALL_METRICS | D19: CD | E19: DASHBOARD | F19: J | G19: MOVED_TO_DASHBOARD | H19: Total citation count
A20: 46177 | B20: L2_evidence_to_claim_ratio | C20: ALL_METRICS | D20: DC | E20: DASHBOARD | F20: K | G20: MOVED_TO_DASHBOARD | H20: Evidence:claim ratio — grounding quality
A21: 46177 | B21: L2_falsifiability_density_per1k | C21: ALL_METRICS | D21: DE | E21: DASHBOARD | F21: L | G21: MOVED_TO_DASHBOARD | H21: Falsifiability markers per 1000 words
... A41: 46177 | B41: ALL_METRICS (2) → ALL_METRICS row 63 | C41: ALL_METRICS (2) | D41: A2 | E41: ALL_METRICS | F41: A63 | G41: APPEND_ROW | H41: New paper P-d03a0e6c62da (MDA-001-story-introduction.md) merged. 336/343 cols matched. 100 new columns in schema 2026.04.07-B not yet in ALL_METRICS — added to gaps for next schema sync.
A42: 46177 | B42: Schema drift detected | C42: ALL_METRICS (2) | E42: ALL_METRICS | G42: SCHEMA_NOTE | H42: New schema has 100 cols not in original ALL_METRICS (e.g. PA_sm_topic_drift_*, L1_readability_*, L3_anti_fruits_*, L8_emo_* GoEmotions expanded). Python should add these cols when it next runs a full batch.

Sheet SCORES
A1: COMPOSITE SCORES — All Papers
A2: Article | B2: Writing | C2: Acad. Rigor | D2: Theophysics | E2: Moral | F2: Emotion | G2: Idea Density | H2: OVERALL | I2: Acad. Grade
A3: =ALL_METRICS!B2 -> MDA-000-series-map.md | B3: =ROUND(MIN(ALL_METRICS!L2,0.6)/0.6*40+MAX(0,(0.4-ALL_METRICS!X2)/0.4)*20+IF(ALL_METRICS!AT2="A — Evidence-Rich",30,IF(LEFT(ALL_METRICS!AT2,1)="B",20,IF(LEFT(ALL_METRICS!AT2,1)="C",10,5)))+IF(AND(ALL_METRICS!AM2>=6,ALL_METRICS!AM2<=12),15,IF(ALL_METRICS!AM2<6,10,5)),1) -> 89.3 | C3: =ROUND(MIN(ALL_METRICS!EB2,20)/20*50+MIN(ALL_METRICS!DC2,5)/5*25+MIN(ALL_METRICS!DE2,2)/2*15+(1-MIN(ABS(ALL_METRICS!DJ2-0.5),0.5)/0.5)*10,1) -> 47.9 | D3: =ROUND(MIN(ALL_METRICS!EE2,10)/10*40+MIN(MAX(ALL_METRICS!EI2,0),3)/3*30+MIN(ALL_METRICS!EN2,10)/10*30,1) -> 48.1 | E3: =ROUND(ALL_METRICS!FN2*30+ALL_METRICS!FO2*30+ALL_METRICS!FY2*25+MAX(0,(1-ALL_METRICS!FZ2/0.5))*15,1) -> 66.7 | F3: =ROUND(MIN(ALL_METRICS!LI2,1)*50+MAX(0,(1-ALL_METRICS!LJ2*5))*30+MIN(MAX(ALL_METRICS!LK2,0),1)*20,1) -> 30 | G3: =ROUND(MIN(MAX(ALL_METRICS!LX2-0.2,0)/0.45*100,100),1) -> 72.7 | H3: =ROUND(AVERAGE(B3:G3),1) -> 59.1 | I3: =ALL_METRICS!ED2 -> D (Light)
A4: =ALL_METRICS!B3 -> MDA-001-story-introduction.md | B4: =ROUND(MIN(ALL_METRICS!L3,0.6)/0.6*40+MAX(0,(0.4-ALL_METRICS!X3)/0.4)*20+IF(ALL_METRICS!AT3="A — Evidence-Rich",30,IF(LEFT(ALL_METRICS!AT3,1)="B",20,IF(LEFT(ALL_METRICS!AT3,1)="C",10,5)))+IF(AND(ALL_METRICS!AM3>=6,ALL_METRICS!AM3<=12),15,IF(ALL_METRICS!AM3<6,10,5)),1) -> 65.1 | C4: =ROUND(MIN(ALL_METRICS!EB3,20)/20*50+MIN(ALL_METRICS!DC3,5)/5*25+MIN(ALL_METRICS!DE3,2)/2*15+(1-MIN(ABS(ALL_METRICS!DJ3-0.5),0.5)/0.5)*10,1) -> 37.3 | D4: =ROUND(MIN(ALL_METRICS!EE3,10)/10*40+MIN(MAX(ALL_METRICS!EI3,0),3)/3*30+MIN(ALL_METRICS!EN3,10)/10*30,1) -> 30.9 | E4: =ROUND(ALL_METRICS!FN3*30+ALL_METRICS!FO3*30+ALL_METRICS!FY3*25+MAX(0,(1-ALL_METRICS!FZ3/0.5))*15,1) -> 66 | F4: =ROUND(MIN(ALL_METRICS!LI3,1)*50+MAX(0,(1-ALL_METRICS!LJ3*5))*30+MIN(MAX(ALL_METRICS!LK3,0),1)*20,1) -> 30 | G4: =ROUND(MIN(MAX(ALL_METRICS!LX3-0.2,0)/0.45*100,100),1) -> 60.5 | H4: =ROUND(AVERAGE(B4:G4),1) -> 48.3 | I4: =ALL_METRICS!ED3 -> F (Needs Citations)
A5: =ALL_METRICS!B4 -> MDA-002-samuel-1900.md | B5: =ROUND(MIN(ALL_METRICS!L4,0.6)/0.6*40+MAX(0,(0.4-ALL_METRICS!X4)/0.4)*20+IF(ALL_METRICS!AT4="A — Evidence-Rich",30,IF(LEFT(ALL_METRICS!AT4,1)="B",20,IF(LEFT(ALL_METRICS!AT4,1)="C",10,5)))+IF(AND(ALL_METRICS!AM4>=6,ALL_METRICS!AM4<=12),15,IF(ALL_METRICS!AM4<6,10,5)),1) -> 70 | C5: =ROUND(MIN(ALL_METRICS!EB4,20)/20*50+MIN(ALL_METRICS!DC4,5)/5*25+MIN(ALL_METRICS!DE4,2)/2*15+(1-MIN(ABS(ALL_METRICS!DJ4-0.5),0.5)/0.5)*10,1) -> 31 | D5: =ROUND(MIN(ALL_METRICS!EE4,10)/10*40+MIN(MAX(ALL_METRICS!EI4,0),3)/3*30+MIN(ALL_METRICS!EN4,10)/10*30,1) -> 15.5 | E5: =ROUND(ALL_METRICS!FN4*30+ALL_METRICS!FO4*30+ALL_METRICS!FY4*25+MAX(0,(1-ALL_METRICS!FZ4/0.5))*15,1) -> 62.5 | F5: =ROUND(MIN(ALL_METRICS!LI4,1)*50+MAX(0,(1-ALL_METRICS!LJ4*5))*30+MIN(MAX(ALL_METRICS!LK4,0),1)*20,1) -> 30 | G5: =ROUND(MIN(MAX(ALL_METRICS!LX4-0.2,0)/0.45*100,100),1) -> 52.8 | H5: =ROUND(AVERAGE(B5:G5),1) -> 43.6 | I5: =ALL_METRICS!ED4 -> F (Needs Citations)
A6: =ALL_METRICS!B5 -> MDA-003-measuring-moral-health.md | B6: =ROUND(MIN(ALL_METRICS!L5,0.6)/0.6*40+MAX(0,(0.4-ALL_METRICS!X5)/0.4)*20+IF(ALL_METRICS!AT5="A — Evidence-Rich",30,IF(LEFT(ALL_METRICS!AT5,1)="B",20,IF(LEFT(ALL_METRICS!AT5,1)="C",10,5)))+IF(AND(ALL_METRICS!AM5>=6,ALL_METRICS!AM5<=12),15,IF(ALL_METRICS!AM5<6,10,5)),1) -> 64.3 | C6: =ROUND(MIN(ALL_METRICS!EB5,20)/20*50+MIN(ALL_METRICS!DC5,5)/5*25+MIN(ALL_METRICS!DE5,2)/2*15+(1-MIN(ABS(ALL_METRICS!DJ5-0.5),0.5)/0.5)*10,1) -> 49.3 | D6: =ROUND(MIN(ALL_METRICS!EE5,10)/10*40+MIN(MAX(ALL_METRICS!EI5,0),3)/3*30+MIN(ALL_METRICS!EN5,10)/10*30,1) -> 43.6 | E6: =ROUND(ALL_METRICS!FN5*30+ALL_METRICS!FO5*30+ALL_METRICS!FY5*25+MAX(0,(1-ALL_METRICS!FZ5/0.5))*15,1) -> 60.5 | F6: =ROUND(MIN(ALL_METRICS!LI5,1)*50+MAX(0,(1-ALL_METRICS!LJ5*5))*30+MIN(MAX(ALL_METRICS!LK5,0),1)*20,1) -> 30 | G6: =ROUND(MIN(MAX(ALL_METRICS!LX5-0.2,0)/0.45*100,100),1) -> 76.5 | H6: =ROUND(AVERAGE(B6:G6),1) -> 54 | I6: =ALL_METRICS!ED5 -> F (Needs Citations)
A7: =ALL_METRICS!B6 -> MDA-005-empirical-evidence.md | B7: =ROUND(MIN(ALL_METRICS!L6,0.6)/0.6*40+MAX(0,(0.4-ALL_METRICS!X6)/0.4)*20+IF(ALL_METRICS!AT6="A — Evidence-Rich",30,IF(LEFT(ALL_METRICS!AT6,1)="B",20,IF(LEFT(ALL_METRICS!AT6,1)="C",10,5)))+IF(AND(ALL_METRICS!AM6>=6,ALL_METRICS!AM6<=12),15,IF(ALL_METRICS!AM6<6,10,5)),1) -> 59.8 | C7: =ROUND(MIN(ALL_METRICS!EB6,20)/20*50+MIN(ALL_METRICS!DC6,5)/5*25+MIN(ALL_METRICS!DE6,2)/2*15+(1-MIN(ABS(ALL_METRICS!DJ6-0.5),0.5)/0.5)*10,1) -> 75.4 | D7: =ROUND(MIN(ALL_METRICS!EE6,10)/10*40+MIN(MAX(ALL_METRICS!EI6,0),3)/3*30+MIN(ALL_METRICS!EN6,10)/10*30,1) -> 19.6 | E7: =ROUND(ALL_METRICS!FN6*30+ALL_METRICS!FO6*30+ALL_METRICS!FY6*25+MAX(0,(1-ALL_METRICS!FZ6/0.5))*15,1) -> 64.2 | F7: =ROUND(MIN(ALL_METRICS!LI6,1)*50+MAX(0,(1-ALL_METRICS!LJ6*5))*30+MIN(MAX(ALL_METRICS!LK6,0),1)*20,1) -> 30 | G7: =ROUND(MIN(MAX(ALL_METRICS!LX6-0.2,0)/0.45*100,100),1) -> 78.4 | H7: =ROUND(AVERAGE(B7:G7),1) -> 54.6 | I7: =ALL_METRICS!ED6 -> D (Light)
A8: =ALL_METRICS!B7 -> MDA-006-research-method.md | B8: =ROUND(MIN(ALL_METRICS!L7,0.6)/0.6*40+MAX(0,(0.4-ALL_METRICS!X7)/0.4)*20+IF(ALL_METRICS!AT7="A — Evidence-Rich",30,IF(LEFT(ALL_METRICS!AT7,1)="B",20,IF(LEFT(ALL_METRICS!AT7,1)="C",10,5)))+IF(AND(ALL_METRICS!AM7>=6,ALL_METRICS!AM7<=12),15,IF(ALL_METRICS!AM7<6,10,5)),1) -> 60.6 | C8: =ROUND(MIN(ALL_METRICS!EB7,20)/20*50+MIN(ALL_METRICS!DC7,5)/5*25+MIN(ALL_METRICS!DE7,2)/2*15+(1-MIN(ABS(ALL_METRICS!DJ7-0.5),0.5)/0.5)*10,1) -> 60.2 | D8: =ROUND(MIN(ALL_METRICS!EE7,10)/10*40+MIN(MAX(ALL_METRICS!EI7,0),3)/3*30+MIN(ALL_METRICS!EN7,10)/10*30,1) -> 14.3 | E8: =ROUND(ALL_METRICS!FN7*30+ALL_METRICS!FO7*30+ALL_METRICS!FY7*25+MAX(0,(1-ALL_METRICS!FZ7/0.5))*15,1) -> 61.6 | F8: =ROUND(MIN(ALL_METRICS!LI7,1)*50+MAX(0,(1-ALL_METRICS!LJ7*5))*30+MIN(MAX(ALL_METRICS!LK7,0),1)*20,1) -> 30 | G8: =ROUND(MIN(MAX(ALL_METRICS!LX7-0.2,0)/0.45*100,100),1) -> 65.4 | H8: =ROUND(AVERAGE(B8:G8),1) -> 48.7 | I8: =ALL_METRICS!ED7 -> D (Light)
A9: =ALL_METRICS!B8 -> MDA-007-nine-domains.md | B9: =ROUND(MIN(ALL_METRICS!L8,0.6)/0.6*40+MAX(0,(0.4-ALL_METRICS!X8)/0.4)*20+IF(ALL_METRICS!AT8="A — Evidence-Rich",30,IF(LEFT(ALL_METRICS!AT8,1)="B",20,IF(LEFT(ALL_METRICS!AT8,1)="C",10,5)))+IF(AND(ALL_METRICS!AM8>=6,ALL_METRICS!AM8<=12),15,IF(ALL_METRICS!AM8<6,10,5)),1) -> 65.1 | C9: =ROUND(MIN(ALL_METRICS!EB8,20)/20*50+MIN(ALL_METRICS!DC8,5)/5*25+MIN(ALL_METRICS!DE8,2)/2*15+(1-MIN(ABS(ALL_METRICS!DJ8-0.5),0.5)/0.5)*10,1) -> 44.2 | D9: =ROUND(MIN(ALL_METRICS!EE8,10)/10*40+MIN(MAX(ALL_METRICS!EI8,0),3)/3*30+MIN(ALL_METRICS!EN8,10)/10*30,1) -> 36.4 | E9: =ROUND(ALL_METRICS!FN8*30+ALL_METRICS!FO8*30+ALL_METRICS!FY8*25+MAX(0,(1-ALL_METRICS!FZ8/0.5))*15,1) -> 60.2 | F9: =ROUND(MIN(ALL_METRICS!LI8,1)*50+MAX(0,(1-ALL_METRICS!LJ8*5))*30+MIN(MAX(ALL_METRICS!LK8,0),1)*20,1) -> 30 | G9: =ROUND(MIN(MAX(ALL_METRICS!LX8-0.2,0)/0.45*100,100),1) -> 89.5 | H9: =ROUND(AVERAGE(B9:G9),1) -> 54.2 | I9: =ALL_METRICS!ED8 -> F (Needs Citations)
A10: =ALL_METRICS!B9 -> MDA-008-henry-1926.md | B10: =ROUND(MIN(ALL_METRICS!L9,0.6)/0.6*40+MAX(0,(0.4-ALL_METRICS!X9)/0.4)*20+IF(ALL_METRICS!AT9="A — Evidence-Rich",30,IF(LEFT(ALL_METRICS!AT9,1)="B",20,IF(LEFT(ALL_METRICS!AT9,1)="C",10,5)))+IF(AND(ALL_METRICS!AM9>=6,ALL_METRICS!AM9<=12),15,IF(ALL_METRICS!AM9<6,10,5)),1) -> 55.1 | C10: =ROUND(MIN(ALL_METRICS!EB9,20)/20*50+MIN(ALL_METRICS!DC9,5)/5*25+MIN(ALL_METRICS!DE9,2)/2*15+(1-MIN(ABS(ALL_METRICS!DJ9-0.5),0.5)/0.5)*10,1) -> 45.1 | D10: =ROUND(MIN(ALL_METRICS!EE9,10)/10*40+MIN(MAX(ALL_METRICS!EI9,0),3)/3*30+MIN(ALL_METRICS!EN9,10)/10*30,1) -> 18.4 | E10: =ROUND(ALL_METRICS!FN9*30+ALL_METRICS!FO9*30+ALL_METRICS!FY9*25+MAX(0,(1-ALL_METRICS!FZ9/0.5))*15,1) -> 61.1 | F10: =ROUND(MIN(ALL_METRICS!LI9,1)*50+MAX(0,(1-ALL_METRICS!LJ9*5))*30+MIN(MAX(ALL_METRICS!LK9,0),1)*20,1) -> 30 | G10: =ROUND(MIN(MAX(ALL_METRICS!LX9-0.2,0)/0.45*100,100),1) -> 49.2 | H10: =ROUND(AVERAGE(B10:G10),1) -> 43.2 | I10: =ALL_METRICS!ED9 -> F (Needs Citations)
A11: =ALL_METRICS!B10 -> MDA-009-the-1900-baseline.md | B11: =ROUND(MIN(ALL_METRICS!L10,0.6)/0.6*40+MAX(0,(0.4-ALL_METRICS!X10)/0.4)*20+IF(ALL_METRICS!AT10="A — Evidence-Rich",30,IF(LEFT(ALL_METRICS!AT10,1)="B",20,IF(LEFT(ALL_METRICS!AT10,1)="C",10,5)))+IF(AND(ALL_METRICS!AM10>=6,ALL_METRICS!AM10<=12),15,IF(ALL_METRICS!AM10<6,10,5)),1) -> 64.6 | C11: =ROUND(MIN(ALL_METRICS!EB10,20)/20*50+MIN(ALL_METRICS!DC10,5)/5*25+MIN(ALL_METRICS!DE10,2)/2*15+(1-MIN(ABS(ALL_METRICS!DJ10-0.5),0.5)/0.5)*10,1) -> 53.1 | D11: =ROUND(MIN(ALL_METRICS!EE10,10)/10*40+MIN(MAX(ALL_METRICS!EI10,0),3)/3*30+MIN(ALL_METRICS!EN10,10)/10*30,1) -> 23.7 | E11: =ROUND(ALL_METRICS!FN10*30+ALL_METRICS!FO10*30+ALL_METRICS!FY10*25+MAX(0,(1-ALL_METRICS!FZ10/0.5))*15,1) -> 58.6 | F11: =ROUND(MIN(ALL_METRICS!LI10,1)*50+MAX(0,(1-ALL_METRICS!LJ10*5))*30+MIN(MAX(ALL_METRICS!LK10,0),1)*20,1) -> 30 | G11: =ROUND(MIN(MAX(ALL_METRICS!LX10-0.2,0)/0.45*100,100),1) -> 79.7 | H11: =ROUND(AVERAGE(B11:G11),1) -> 51.6 | I11: =ALL_METRICS!ED10 -> F (Needs Citations)
A12: =ALL_METRICS!B11 -> MDA-010-pre-modern-baseline.md | B12: =ROUND(MIN(ALL_METRICS!L11,0.6)/0.6*40+MAX(0,(0.4-ALL_METRICS!X11)/0.4)*20+IF(ALL_METRICS!AT11="A — Evidence-Rich",30,IF(LEFT(ALL_METRICS!AT11,1)="B",20,IF(LEFT(ALL_METRICS!AT11,1)="C",10,5)))+IF(AND(ALL_METRICS!AM11>=6,ALL_METRICS!AM11<=12),15,IF(ALL_METRICS!AM11<6,10,5)),1) -> 60 | C12: =ROUND(MIN(ALL_METRICS!EB11,20)/20*50+MIN(ALL_METRICS!DC11,5)/5*25+MIN(ALL_METRICS!DE11,2)/2*15+(1-MIN(ABS(ALL_METRICS!DJ11-0.5),0.5)/0.5)*10,1) -> 52.3 | D12: =ROUND(MIN(ALL_METRICS!EE11,10)/10*40+MIN(MAX(ALL_METRICS!EI11,0),3)/3*30+MIN(ALL_METRICS!EN11,10)/10*30,1) -> 18.1 | E12: =ROUND(ALL_METRICS!FN11*30+ALL_METRICS!FO11*30+ALL_METRICS!FY11*25+MAX(0,(1-ALL_METRICS!FZ11/0.5))*15,1) -> 62.2 | F12: =ROUND(MIN(ALL_METRICS!LI11,1)*50+MAX(0,(1-ALL_METRICS!LJ11*5))*30+MIN(MAX(ALL_METRICS!LK11,0),1)*20,1) -> 30 | G12: =ROUND(MIN(MAX(ALL_METRICS!LX11-0.2,0)/0.45*100,100),1) -> 84.5 | H12: =ROUND(AVERAGE(B12:G12),1) -> 51.2 | I12: =ALL_METRICS!ED11 -> D (Light)
A13: =ALL_METRICS!B12 -> MDA-011-collective-security-1930.md | B13: =ROUND(MIN(ALL_METRICS!L12,0.6)/0.6*40+MAX(0,(0.4-ALL_METRICS!X12)/0.4)*20+IF(ALL_METRICS!AT12="A — Evidence-Rich",30,IF(LEFT(ALL_METRICS!AT12,1)="B",20,IF(LEFT(ALL_METRICS!AT12,1)="C",10,5)))+IF(AND(ALL_METRICS!AM12>=6,ALL_METRICS!AM12<=12),15,IF(ALL_METRICS!AM12<6,10,5)),1) -> 62.8 | C13: =ROUND(MIN(ALL_METRICS!EB12,20)/20*50+MIN(ALL_METRICS!DC12,5)/5*25+MIN(ALL_METRICS!DE12,2)/2*15+(1-MIN(ABS(ALL_METRICS!DJ12-0.5),0.5)/0.5)*10,1) -> 60.4 | D13: =ROUND(MIN(ALL_METRICS!EE12,10)/10*40+MIN(MAX(ALL_METRICS!EI12,0),3)/3*30+MIN(ALL_METRICS!EN12,10)/10*30,1) -> 11.6 | E13: =ROUND(ALL_METRICS!FN12*30+ALL_METRICS!FO12*30+ALL_METRICS!FY12*25+MAX(0,(1-ALL_METRICS!FZ12/0.5))*15,1) -> 63.8 | F13: =ROUND(MIN(ALL_METRICS!LI12,1)*50+MAX(0,(1-ALL_METRICS!LJ12*5))*30+MIN(MAX(ALL_METRICS!LK12,0),1)*20,1) -> 30 | G13: =ROUND(MIN(MAX(ALL_METRICS!LX12-0.2,0)/0.45*100,100),1) -> 70.1 | H13: =ROUND(AVERAGE(B13:G13),1) -> 49.8 | I13: =ALL_METRICS!ED12 -> C (Moderate)
A14: =ALL_METRICS!B13 -> MDA-012-william-1950.md | B14: =ROUND(MIN(ALL_METRICS!L13,0.6)/0.6*40+MAX(0,(0.4-ALL_METRICS!X13)/0.4)*20+IF(ALL_METRICS!AT13="A — Evidence-Rich",30,IF(LEFT(ALL_METRICS!AT13,1)="B",20,IF(LEFT(ALL_METRICS!AT13,1)="C",10,5)))+IF(AND(ALL_METRICS!AM13>=6,ALL_METRICS!AM13<=12),15,IF(ALL_METRICS!AM13<6,10,5)),1) -> 56 | C14: =ROUND(MIN(ALL_METRICS!EB13,20)/20*50+MIN(ALL_METRICS!DC13,5)/5*25+MIN(ALL_METRICS!DE13,2)/2*15+(1-MIN(ABS(ALL_METRICS!DJ13-0.5),0.5)/0.5)*10,1) -> 57.4 | D14: =ROUND(MIN(ALL_METRICS!EE13,10)/10*40+MIN(MAX(ALL_METRICS!EI13,0),3)/3*30+MIN(ALL_METRICS!EN13,10)/10*30,1) -> 11.3 | E14: =ROUND(ALL_METRICS!FN13*30+ALL_METRICS!FO13*30+ALL_METRICS!FY13*25+MAX(0,(1-ALL_METRICS!FZ13/0.5))*15,1) -> 62.3 | F14: =ROUND(MIN(ALL_METRICS!LI13,1)*50+MAX(0,(1-ALL_METRICS!LJ13*5))*30+MIN(MAX(ALL_METRICS!LK13,0),1)*20,1) -> 30 | G14: =ROUND(MIN(MAX(ALL_METRICS!LX13-0.2,0)/0.45*100,100),1) -> 54.6 | H14: =ROUND(AVERAGE(B14:G14),1) -> 45.3 | I14: =ALL_METRICS!ED13 -> F (Needs Citations)
... A64: =ALL_METRICS!B63 -> MDA-001-story-introduction.md | B64: =ROUND(MIN(ALL_METRICS!L63,0.6)/0.6*40+MAX(0,(0.4-ALL_METRICS!X63)/0.4)*20+IF(ALL_METRICS!AT63="A — Evidence-Rich",30,IF(LEFT(ALL_METRICS!AT63,1)="B",20,IF(LEFT(ALL_METRICS!AT63,1)="C",10,5)))+IF(AND(ALL_METRICS!AM63>=6,ALL_METRICS!AM63<=12),15,IF(ALL_METRICS!AM63<6,10,5)),1) -> 61.7 | C64: =ROUND(MIN(ALL_METRICS!EB63,20)/20*50+MIN(ALL_METRICS!DC63,5)/5*25+MIN(ALL_METRICS!DE63,2)/2*15+(1-MIN(ABS(ALL_METRICS!DJ63-0.5),0.5)/0.5)*10,1) -> 31 | D64: =ROUND(MIN(ALL_METRICS!EE63,10)/10*40+MIN(MAX(ALL_METRICS!EI63,0),3)/3*30+MIN(ALL_METRICS!EN63,10)/10*30,1) -> 42.9 | E64: =ROUND(ALL_METRICS!FN63*30+ALL_METRICS!FO63*30+ALL_METRICS!FY63*25+MAX(0,(1-ALL_METRICS!FZ63/0.5))*15,1) -> 50.6 | F64: =ROUND(MIN(ALL_METRICS!LI63,1)*50+MAX(0,(1-ALL_METRICS!LJ63*5))*30+MIN(MAX(ALL_METRICS!LK63,0),1)*20,1) -> 57.8 | G64: =ROUND(MIN(MAX(ALL_METRICS!LX63-0.2,0)/0.45*100,100),1) -> 63.6 | H64: =ROUND(AVERAGE(B64:G64),1) -> 51.3 | I64: =ALL_METRICS!ED63 -> F (Needs Citations)
A65: SERIES AVERAGE | B65: =ROUND(AVERAGE(B3:B64),1) -> 63.1 | C65: =ROUND(AVERAGE(C3:C64),1) -> 55 | D65: =ROUND(AVERAGE(D3:D64),1) -> 29.3 | E65: =ROUND(AVERAGE(E3:E64),1) -> 61.5 | F65: =ROUND(AVERAGE(F3:F64),1) -> 30.4 | G65: =ROUND(AVERAGE(G3:G64),1) -> 74.9 | H65: =ROUND(AVERAGE(H3:H64),1) -> 52.4

Sheet DASHBOARD
A1: Paper Intelligence — Academic Dashboard
A2: Series: MDA | Run: 20260530_220100 | Schema: 2026.04.07-B | 61 papers analyzed
A3: IDENTITY | D3: WRITING QUALITY | I3: ACADEMIC RIGOR | O3: THEOPHYSICS (L3) | U3: MORAL / SPIRITUAL (L6) | Y3: EMOTION (L8) | AC3: IDEA DENSITY (L10)
A4: Article | B4: Paper ID | C4: Word Count | D4: Type-Token Ratio | E4: Avg Words/Sentence | F4: Passive Voice % | G4: Argument Grade | H4: Flow Label | I4: Academic Grade | J4: Citation Count | K4: Evidence:Claim Ratio | L4: Falsifiability Density | M4: Hedge:Absolute Ratio | N4: Rubric Score /100 | O4: χ Score | P4: χ Status | Q4: Wisdom Score | R4: Knowledge Score | S4: W:K Ratio | T4: Dominant Fruit | U4: Truth Score | V4: Coherence Score | W4: Fruit Integrity | X4: Character Posture | Y4: Fruit Emo Composite | Z4: Anti-Emo Composite | AA4: Net Emotional | AB4: Dominant Emotion | AC4: Idea Density (mean) | AD4: Density Level
A5: ⬆ SOURCE MAPPING (Python reads this row) | B5: ALL_METRICS::paper_id | C5: ALL_METRICS::PA_s_word_count | D5: ALL_METRICS::PA_s_ttr | E5: ALL_METRICS::PA_s_avg_words_per_sentence | F5: ALL_METRICS::PA_g_passive_pct | G5: ALL_METRICS::PA_a_argument_grade | H5: ALL_METRICS::PA_f_flow_label | I5: ALL_METRICS::L2_academic_grade | J5: ALL_METRICS::L2_citation_count | K5: ALL_METRICS::L2_evidence_to_claim_ratio | L5: ALL_METRICS::L2_falsifiability_density_per1k | M5: ALL_METRICS::L2_hedge_to_absolute_ratio | N5: ALL_METRICS::L2_academic_rubric_total | O5: ALL_METRICS::L3_chi_score | P5: ALL_METRICS::L3_chi_status | Q5: ALL_METRICS::L3_wisdom_score | R5: ALL_METRICS::L3_knowledge_score | S5: ALL_METRICS::L3_wk_ratio | T5: ALL_METRICS::L3_dominant_fruit | U5: ALL_METRICS::L6_truth_score | V5: ALL_METRICS::L6_coherence_score | W5: ALL_METRICS::L6_fruit_integrity_score | X5: ALL_METRICS::L6_character_posture | Y5: ALL_METRICS::L8_fruit_emo_composite | Z5: ALL_METRICS::L8_anti_emo_composite | AA5: ALL_METRICS::L8_fruit_emo_net | AB5: ALL_METRICS::L8_emo_dominant | AC5: ALL_METRICS::L10_idea_density_mean | AD5: ALL_METRICS::L10_idea_density_level
A6: =ALL_METRICS!B6 -> MDA-005-empirical-evidence.md | B6: =ALL_METRICS!A6 -> P-5115499be213 | C6: =ALL_METRICS!J6 -> 1251 | D6: =ALL_METRICS!L6 -> 0.3717 | E6: =ALL_METRICS!P6 -> 20.9 | F6: =ALL_METRICS!X6 -> 8.8 | G6: =ALL_METRICS!AT6 -> A — Evidence-Rich | H6: =ALL_METRICS!AW6 -> MODERATE | I6: =ALL_METRICS!ED6 -> D (Light) | J6: =ALL_METRICS!CD6 -> 0 | K6: =ALL_METRICS!DC6 -> 43 | L6: =ALL_METRICS!DE6 -> 3.99 | M6: =ALL_METRICS!DJ6 -> 0 | N6: =ALL_METRICS!EB6 -> 14.14 | O6: =ALL_METRICS!EE6 -> 3.87 | P6: =ALL_METRICS!EF6 -> WEAK | Q6: =ALL_METRICS!EG6 -> 0 | R6: =ALL_METRICS!EH6 -> 4.07 | S6: =ALL_METRICS!EI6 -> 0 | T6: =ALL_METRICS!EL6 -> peace | U6: =ALL_METRICS!FN6 -> 0.6109 | V6: =ALL_METRICS!FO6 -> 0.775 | W6: =ALL_METRICS!FY6 -> 0.3033 | X6: =ALL_METRICS!JD6 -> disciplined; technically strong, spiritually ordered | Y6: =ALL_METRICS!LI6 -> 0 | Z6: =ALL_METRICS!LJ6 -> 0 | AA6: =ALL_METRICS!LK6 -> 0 | AB6: =ALL_METRICS!LL6 -> 0 | AC6: =ALL_METRICS!LX6 -> 0.5528 | AD6: =ALL_METRICS!ME6 -> VERY HIGH (dense academic)
A7: =ALL_METRICS!B7 -> MDA-006-research-method.md | B7: =ALL_METRICS!A7 -> P-d67cbfce1ec4 | C7: =ALL_METRICS!J7 -> 1167 | D7: =ALL_METRICS!L7 -> 0.3839 | E7: =ALL_METRICS!P7 -> 14.4 | F7: =ALL_METRICS!X7 -> 7.2 | G7: =ALL_METRICS!AT7 -> A — Evidence-Rich | H7: =ALL_METRICS!AW7 -> HIGH | I7: =ALL_METRICS!ED7 -> D (Light) | J7: =ALL_METRICS!CD7 -> 0 | K7: =ALL_METRICS!DC7 -> 15 | L7: =ALL_METRICS!DE7 -> 0.86 | M7: =ALL_METRICS!DJ7 -> 0.17 | N7: =ALL_METRICS!EB7 -> 10.14 | O7: =ALL_METRICS!EE7 -> 2.35 | P7: =ALL_METRICS!EF7 -> WEAK | Q7: =ALL_METRICS!EG7 -> 0.26 | R7: =ALL_METRICS!EH7 -> 2.14 | S7: =ALL_METRICS!EI7 -> 0.12 | T7: =ALL_METRICS!EL7 -> self_control | U7: =ALL_METRICS!FN7 -> 0.5495 | V7: =ALL_METRICS!FO7 -> 0.775 | W7: =ALL_METRICS!FY7 -> 0.2739 | X7: =ALL_METRICS!JD7 -> mixed spiritual posture | Y7: =ALL_METRICS!LI7 -> 0 | Z7: =ALL_METRICS!LJ7 -> 0 | AA7: =ALL_METRICS!LK7 -> 0 | AB7: =ALL_METRICS!LL7 -> 0 | AC7: =ALL_METRICS!LX7 -> 0.4942 | AD7: =ALL_METRICS!ME7 -> HIGH (academic)
A8: =ALL_METRICS!B8 -> MDA-007-nine-domains.md | B8: =ALL_METRICS!A8 -> P-c38c656b2b9b | C8: =ALL_METRICS!J8 -> 1077 | D8: =ALL_METRICS!L8 -> 0.4522 | E8: =ALL_METRICS!P8 -> 16.8 | F8: =ALL_METRICS!X8 -> 5.4 | G8: =ALL_METRICS!AT8 -> A — Evidence-Rich | H8: =ALL_METRICS!AW8 -> MODERATE | I8: =ALL_METRICS!ED8 -> F (Needs Citations) | J8: =ALL_METRICS!CD8 -> 0 | K8: =ALL_METRICS!DC8 -> 3 | L8: =ALL_METRICS!DE8 -> 0.93 | M8: =ALL_METRICS!DJ8 -> 0 | N8: =ALL_METRICS!EB8 -> 8.88 | O8: =ALL_METRICS!EE8 -> 6.82 | P8: =ALL_METRICS!EF8 -> STRONG | Q8: =ALL_METRICS!EG8 -> 0.19 | R8: =ALL_METRICS!EH8 -> 1.86 | S8: =ALL_METRICS!EI8 -> 0.1 | T8: =ALL_METRICS!EL8 -> self_control | U8: =ALL_METRICS!FN8 -> 0.5422 | V8: =ALL_METRICS!FO8 -> 0.775 | W8: =ALL_METRICS!FY8 -> 0.2787 | X8: =ALL_METRICS!JD8 -> agitated or reactionary; disciplined | Y8: =ALL_METRICS!LI8 -> 0 | Z8: =ALL_METRICS!LJ8 -> 0 | AA8: =ALL_METRICS!LK8 -> 0 | AB8: =ALL_METRICS!LL8 -> 0 | AC8: =ALL_METRICS!LX8 -> 0.6029 | AD8: =ALL_METRICS!ME8 -> VERY HIGH (dense academic)
A9: =ALL_METRICS!B9 -> MDA-008-henry-1926.md | B9: =ALL_METRICS!A9 -> P-5eaaaea5ccd2 | C9: =ALL_METRICS!J9 -> 3803 | D9: =ALL_METRICS!L9 -> 0.3016 | E9: =ALL_METRICS!P9 -> 12 | F9: =ALL_METRICS!X9 -> 3.1 | G9: =ALL_METRICS!AT9 -> A — Evidence-Rich | H9: =ALL_METRICS!AW9 -> MODERATE | I9: =ALL_METRICS!ED9 -> F (Needs Citations) | J9: =ALL_METRICS!CD9 -> 0 | K9: =ALL_METRICS!DC9 -> 3 | L9: =ALL_METRICS!DE9 -> 0 | M9: =ALL_METRICS!DJ9 -> 0.67 | N9: =ALL_METRICS!EB9 -> 9.38 | O9: =ALL_METRICS!EE9 -> 1.66 | P9: =ALL_METRICS!EF9 -> WEAK | Q9: =ALL_METRICS!EG9 -> 0.26 | R9: =ALL_METRICS!EH9 -> 0.32 | S9: =ALL_METRICS!EI9 -> 0.833 | T9: =ALL_METRICS!EL9 -> goodness | U9: =ALL_METRICS!FN9 -> 0.5195 | V9: =ALL_METRICS!FO9 -> 0.775 | W9: =ALL_METRICS!FY9 -> 0.3066 | X9: =ALL_METRICS!JD9 -> technically strong, spiritually ordered | Y9: =ALL_METRICS!LI9 -> 0 | Z9: =ALL_METRICS!LJ9 -> 0 | AA9: =ALL_METRICS!LK9 -> 0 | AB9: =ALL_METRICS!LL9 -> 0 | AC9: =ALL_METRICS!LX9 -> 0.4213 | AD9: =ALL_METRICS!ME9 -> MODERATE (accessible)
A10: =ALL_METRICS!B10 -> MDA-009-the-1900-baseline.md | B10: =ALL_METRICS!A10 -> P-6174b3e6eed2 | C10: =ALL_METRICS!J10 -> 1327 | D10: =ALL_METRICS!L10 -> 0.4439 | E10: =ALL_METRICS!P10 -> 12.5 | F10: =ALL_METRICS!X10 -> 5.2 | G10: =ALL_METRICS!AT10 -> A — Evidence-Rich | H10: =ALL_METRICS!AW10 -> MODERATE | I10: =ALL_METRICS!ED10 -> F (Needs Citations) | J10: =ALL_METRICS!CD10 -> 0 | K10: =ALL_METRICS!DC10 -> 5 | L10: =ALL_METRICS!DE10 -> 0 | M10: =ALL_METRICS!DJ10 -> 0.33 | N10: =ALL_METRICS!EB10 -> 8.6 | O10: =ALL_METRICS!EE10 -> 4.22 | P10: =ALL_METRICS!EF10 -> MODERATE | Q10: =ALL_METRICS!EG10 -> 0.15 | R10: =ALL_METRICS!EH10 -> 1.43 | S10: =ALL_METRICS!EI10 -> 0.105 | T10: =ALL_METRICS!EL10 -> self_control | U10: =ALL_METRICS!FN10 -> 0.4662 | V10: =ALL_METRICS!FO10 -> 0.775 | W10: =ALL_METRICS!FY10 -> 0.2945 | X10: =ALL_METRICS!JD10 -> disciplined | Y10: =ALL_METRICS!LI10 -> 0 | Z10: =ALL_METRICS!LJ10 -> 0 | AA10: =ALL_METRICS!LK10 -> 0 | AB10: =ALL_METRICS!LL10 -> 0 | AC10: =ALL_METRICS!LX10 -> 0.5587 | AD10: =ALL_METRICS!ME10 -> VERY HIGH (dense academic)
A11: =ALL_METRICS!B11 -> MDA-010-pre-modern-baseline.md | B11: =ALL_METRICS!A11 -> P-b16210a6fece | C11: =ALL_METRICS!J11 -> 3453 | D11: =ALL_METRICS!L11 -> 0.3747 | E11: =ALL_METRICS!P11 -> 22.1 | F11: =ALL_METRICS!X11 -> 8.8 | G11: =ALL_METRICS!AT11 -> A — Evidence-Rich | H11: =ALL_METRICS!AW11 -> HIGH | I11: =ALL_METRICS!ED11 -> D (Light) | J11: =ALL_METRICS!CD11 -> 0 | K11: =ALL_METRICS!DC11 -> 5 | L11: =ALL_METRICS!DE11 -> 0 | M11: =ALL_METRICS!DJ11 -> 1 | N11: =ALL_METRICS!EB11 -> 10.93 | O11: =ALL_METRICS!EE11 -> 3.45 | P11: =ALL_METRICS!EF11 -> WEAK | Q11: =ALL_METRICS!EG11 -> 0.09 | R11: =ALL_METRICS!EH11 -> 0.75 | S11: =ALL_METRICS!EI11 -> 0.115 | T11: =ALL_METRICS!EL11 -> peace | U11: =ALL_METRICS!FN11 -> 0.5773 | V11: =ALL_METRICS!FO11 -> 0.775 | W11: =ALL_METRICS!FY11 -> 0.2734 | X11: =ALL_METRICS!JD11 -> mixed spiritual posture | Y11: =ALL_METRICS!LI11 -> 0 | Z11: =ALL_METRICS!LJ11 -> 0 | AA11: =ALL_METRICS!LK11 -> 0 | AB11: =ALL_METRICS!LL11 -> 0 | AC11: =ALL_METRICS!LX11 -> 0.5803 | AD11: =ALL_METRICS!ME11 -> VERY HIGH (dense academic)
A12: =ALL_METRICS!B12 -> MDA-011-collective-security-1930.md | B12: =ALL_METRICS!A12 -> P-5714a123d5b0 | C12: =ALL_METRICS!J12 -> 1732 | D12: =ALL_METRICS!L12 -> 0.4174 | E12: =ALL_METRICS!P12 -> 26.6 | F12: =ALL_METRICS!X12 -> 2.8 | G12: =ALL_METRICS!AT12 -> A — Evidence-Rich | H12: =ALL_METRICS!AW12 -> HIGH | I12: =ALL_METRICS!ED12 -> C (Moderate) | J12: =ALL_METRICS!CD12 -> 20 | K12: =ALL_METRICS!DC12 -> 32 | L12: =ALL_METRICS!DE12 -> 0 | M12: =ALL_METRICS!DJ12 -> 3 | N12: =ALL_METRICS!EB12 -> 14.14 | O12: =ALL_METRICS!EE12 -> 1.7 | P12: =ALL_METRICS!EF12 -> WEAK | Q12: =ALL_METRICS!EG12 -> 0.29 | R12: =ALL_METRICS!EH12 -> 1.21 | S12: =ALL_METRICS!EI12 -> 0.238 | T12: =ALL_METRICS!EL12 -> goodness | U12: =ALL_METRICS!FN12 -> 0.6002 | V12: =ALL_METRICS!FO12 -> 0.775 | W12: =ALL_METRICS!FY12 -> 0.3012 | X12: =ALL_METRICS!JD12 -> disciplined; technically strong, spiritually ordered | Y12: =ALL_METRICS!LI12 -> 0 | Z12: =ALL_METRICS!LJ12 -> 0 | AA12: =ALL_METRICS!LK12 -> 0 | AB12: =ALL_METRICS!LL12 -> 0 | AC12: =ALL_METRICS!LX12 -> 0.5153 | AD12: =ALL_METRICS!ME12 -> HIGH (academic)
A13: =ALL_METRICS!B13 -> MDA-012-william-1950.md | B13: =ALL_METRICS!A13 -> P-45de3640a23d | C13: =ALL_METRICS!J13 -> 3812 | D13: =ALL_METRICS!L13 -> 0.3148 | E13: =ALL_METRICS!P13 -> 11.8 | F13: =ALL_METRICS!X13 -> 3.3 | G13: =ALL_METRICS!AT13 -> A — Evidence-Rich | H13: =ALL_METRICS!AW13 -> MODERATE | I13: =ALL_METRICS!ED13 -> F (Needs Citations) | J13: =ALL_METRICS!CD13 -> 0 | K13: =ALL_METRICS!DC13 -> 5 | L13: =ALL_METRICS!DE13 -> 0 | M13: =ALL_METRICS!DJ13 -> 0.38 | N13: =ALL_METRICS!EB13 -> 9.93 | O13: =ALL_METRICS!EE13 -> 0.93 | P13: =ALL_METRICS!EF13 -> WEAK | Q13: =ALL_METRICS!EG13 -> 0.16 | R13: =ALL_METRICS!EH13 -> 0.34 | S13: =ALL_METRICS!EI13 -> 0.462 | T13: =ALL_METRICS!EL13 -> goodness | U13: =ALL_METRICS!FN13 -> 0.5329 | V13: =ALL_METRICS!FO13 -> 0.775 | W13: =ALL_METRICS!FY13 -> 0.326 | X13: =ALL_METRICS!JD13 -> technically strong, spiritually ordered | Y13: =ALL_METRICS!LI13 -> 0 | Z13: =ALL_METRICS!LJ13 -> 0 | AA13: =ALL_METRICS!LK13 -> 0 | AB13: =ALL_METRICS!LL13 -> 0 | AC13: =ALL_METRICS!LX13 -> 0.4459 | AD13: =ALL_METRICS!ME13 -> MODERATE (accessible)
A14: =ALL_METRICS!B14 -> MDA-013-peak-coherence-1940.md | B14: =ALL_METRICS!A14 -> P-b1721534cce8 | C14: =ALL_METRICS!J14 -> 2144 | D14: =ALL_METRICS!L14 -> 0.4151 | E14: =ALL_METRICS!P14 -> 16.6 | F14: =ALL_METRICS!X14 -> 5.5 | G14: =ALL_METRICS!AT14 -> A — Evidence-Rich | H14: =ALL_METRICS!AW14 -> MODERATE | I14: =ALL_METRICS!ED14 -> D (Light) | J14: =ALL_METRICS!CD14 -> 0 | K14: =ALL_METRICS!DC14 -> 14 | L14: =ALL_METRICS!DE14 -> 0 | M14: =ALL_METRICS!DJ14 -> 0.8 | N14: =ALL_METRICS!EB14 -> 9.81 | O14: =ALL_METRICS!EE14 -> 4.59 | P14: =ALL_METRICS!EF14 -> MODERATE | Q14: =ALL_METRICS!EG14 -> 0.23 | R14: =ALL_METRICS!EH14 -> 1.59 | S14: =ALL_METRICS!EI14 -> 0.147 | T14: =ALL_METRICS!EL14 -> peace | U14: =ALL_METRICS!FN14 -> 0.5579 | V14: =ALL_METRICS!FO14 -> 0.775 | W14: =ALL_METRICS!FY14 -> 0.2635 | X14: =ALL_METRICS!JD14 -> mixed spiritual posture | Y14: =ALL_METRICS!LI14 -> 0 | Z14: =ALL_METRICS!LJ14 -> 0 | AA14: =ALL_METRICS!LK14 -> 0 | AB14: =ALL_METRICS!LL14 -> 0 | AC14: =ALL_METRICS!LX14 -> 0.506 | AD14: =ALL_METRICS!ME14 -> HIGH (academic)
A15: =ALL_METRICS!B15 -> MDA-014-fissure-1950.md | B15: =ALL_METRICS!A15 -> P-10c538ca5abc | C15: =ALL_METRICS!J15 -> 1887 | D15: =ALL_METRICS!L15 -> 0.3731 | E15: =ALL_METRICS!P15 -> 18.5 | F15: =ALL_METRICS!X15 -> 4.9 | G15: =ALL_METRICS!AT15 -> A — Evidence-Rich | H15: =ALL_METRICS!AW15 -> MODERATE | I15: =ALL_METRICS!ED15 -> D (Light) | J15: =ALL_METRICS!CD15 -> 0 | K15: =ALL_METRICS!DC15 -> 10 | L15: =ALL_METRICS!DE15 -> 0 | M15: =ALL_METRICS!DJ15 -> 0.29 | N15: =ALL_METRICS!EB15 -> 8.43 | O15: =ALL_METRICS!EE15 -> 2.91 | P15: =ALL_METRICS!EF15 -> WEAK | Q15: =ALL_METRICS!EG15 -> 0 | R15: =ALL_METRICS!EH15 -> 1.48 | S15: =ALL_METRICS!EI15 -> 0 | T15: =ALL_METRICS!EL15 -> peace | U15: =ALL_METRICS!FN15 -> 0.5739 | V15: =ALL_METRICS!FO15 -> 0.775 | W15: =ALL_METRICS!FY15 -> 0.2887 | X15: =ALL_METRICS!JD15 -> mixed spiritual posture | Y15: =ALL_METRICS!LI15 -> 0 | Z15: =ALL_METRICS!LJ15 -> 0 | AA15: =ALL_METRICS!LK15 -> 0 | AB15: =ALL_METRICS!LL15 -> 0 | AC15: =ALL_METRICS!LX15 -> 0.467 | AD15: =ALL_METRICS!ME15 -> HIGH (academic)
A16: =ALL_METRICS!B16 -> MDA-015-long-decline.md | B16: =ALL_METRICS!A16 -> P-ac8790ade693 | C16: =ALL_METRICS!J16 -> 983 | D16: =ALL_METRICS!L16 -> 0.532 | E16: =ALL_METRICS!P16 -> 13.3 | F16: =ALL_METRICS!X16 -> 2.4 | G16: =ALL_METRICS!AT16 -> A — Evidence-Rich | H16: =ALL_METRICS!AW16 -> MODERATE | I16: =ALL_METRICS!ED16 -> F (Needs Citations) | J16: =ALL_METRICS!CD16 -> 0 | K16: =ALL_METRICS!DC16 -> 5 | L16: =ALL_METRICS!DE16 -> 0 | M16: =ALL_METRICS!DJ16 -> 4 | N16: =ALL_METRICS!EB16 -> 7.88 | O16: =ALL_METRICS!EE16 -> 8.03 | P16: =ALL_METRICS!EF16 -> HIGH | Q16: =ALL_METRICS!EG16 -> 0.1 | R16: =ALL_METRICS!EH16 -> 1.83 | S16: =ALL_METRICS!EI16 -> 0.056 | T16: =ALL_METRICS!EL16 -> love | U16: =ALL_METRICS!FN16 -> 0.4831 | V16: =ALL_METRICS!FO16 -> 0.775 | W16: =ALL_METRICS!FY16 -> 0.2799 | X16: =ALL_METRICS!JD16 -> mixed spiritual posture | Y16: =ALL_METRICS!LI16 -> 0 | Z16: =ALL_METRICS!LJ16 -> 0 | AA16: =ALL_METRICS!LK16 -> 0 | AB16: =ALL_METRICS!LL16 -> 0 | AC16: =ALL_METRICS!LX16 -> 0.6104 | AD16: =ALL_METRICS!ME16 -> VERY HIGH (dense academic)
A17: =ALL_METRICS!B17 -> MDA-016-thomas-1974.md | B17: =ALL_METRICS!A17 -> P-dd73709327e1 | C17: =ALL_METRICS!J17 -> 3532 | D17: =ALL_METRICS!L17 -> 0.2993 | E17: =ALL_METRICS!P17 -> 11.3 | F17: =ALL_METRICS!X17 -> 3.3 | G17: =ALL_METRICS!AT17 -> A — Evidence-Rich | H17: =ALL_METRICS!AW17 -> MODERATE | I17: =ALL_METRICS!ED17 -> F (Needs Citations) | J17: =ALL_METRICS!CD17 -> 0 | K17: =ALL_METRICS!DC17 -> 4 | L17: =ALL_METRICS!DE17 -> 0 | M17: =ALL_METRICS!DJ17 -> 0.16 | N17: =ALL_METRICS!EB17 -> 10.14 | O17: =ALL_METRICS!EE17 -> 0.86 | P17: =ALL_METRICS!EF17 -> WEAK | Q17: =ALL_METRICS!EG17 -> 0.14 | R17: =ALL_METRICS!EH17 -> 0.37 | S17: =ALL_METRICS!EI17 -> 0.385 | T17: =ALL_METRICS!EL17 -> goodness | U17: =ALL_METRICS!FN17 -> 0.4966 | V17: =ALL_METRICS!FO17 -> 0.775 | W17: =ALL_METRICS!FY17 -> 0.3594 | X17: =ALL_METRICS!JD17 -> spiritually ordered; technically strong, spiritually ordered | Y17: =ALL_METRICS!LI17 -> 0 | Z17: =ALL_METRICS!LJ17 -> 0 | AA17: =ALL_METRICS!LK17 -> 0 | AB17: =ALL_METRICS!LL17 -> 0 | AC17: =ALL_METRICS!LX17 -> 0.4642 | AD17: =ALL_METRICS!ME17 -> HIGH (academic)
... A66: =ALL_METRICS!B66 -> 0 | B66: =ALL_METRICS!A66 -> 0 | C66: =ALL_METRICS!J66 -> 0 | D66: =ALL_METRICS!L66 -> 0 | E66: =ALL_METRICS!P66 -> 0 | F66: =ALL_METRICS!X66 -> 0 | G66: =ALL_METRICS!AT66 -> 0 | H66: =ALL_METRICS!AW66 -> 0 | I66: =ALL_METRICS!ED66 -> 0 | J66: =ALL_METRICS!CD66 -> 0 | K66: =ALL_METRICS!DC66 -> 0 | L66: =ALL_METRICS!DE66 -> 0 | M66: =ALL_METRICS!DJ66 -> 0 | N66: =ALL_METRICS!EB66 -> 0 | O66: =ALL_METRICS!EE66 -> 0 | P66: =ALL_METRICS!EF66 -> 0 | Q66: =ALL_METRICS!EG66 -> 0 | R66: =ALL_METRICS!EH66 -> 0 | S66: =ALL_METRICS!EI66 -> 0 | T66: =ALL_METRICS!EL66 -> 0 | U66: =ALL_METRICS!FN66 -> 0 | V66: =ALL_METRICS!FO66 -> 0 | W66: =ALL_METRICS!FY66 -> 0 | X66: =ALL_METRICS!JD66 -> 0 | Y66: =ALL_METRICS!LI66 -> 0 | Z66: =ALL_METRICS!LJ66 -> 0 | AA66: =ALL_METRICS!LK66 -> 0 | AB66: =ALL_METRICS!LL66 -> 0 | AC66: =ALL_METRICS!LX66 -> 0 | AD66: =ALL_METRICS!ME66 -> 0

Sheet ALL_METRICS
A1: paper_id | B1: file | C1: series_id | D1: run_id | E1: schema_version | F1: source_path | G1: analyzed_at | H1: snapshot_path | I1: layer_status | J1: PA_s_word_count | K1: PA_s_unique_word_count | L1: PA_s_ttr | M1: PA_s_sentence_count | N1: PA_s_paragraph_count | O1: PA_s_header_count | P1: PA_s_avg_words_per_sentence | Q1: PA_s_avg_sentences_per_paragraph | R1: PA_g_noun_pct | S1: PA_g_verb_pct | T1: PA_g_adj_pct | U1: PA_g_adv_pct | V1: PA_g_prep_pct | W1: PA_g_passive_voice_count | X1: PA_g_passive_pct | Y1: PA_g_modal_verb_count | Z1: PA_g_assertive_verb_count | AA1: PA_g_modal_vs_assertive_ratio | AB1: PA_g_weight_signal | AC1: PA_g_fluff_flag | AD1: PA_sm_semantic_note | AE1: PA_d_compression_ratio | AF1: PA_d_density_label | AG1: PA_d_stopword_ratio | AH1: PA_d_trigram_redundancy | AI1: PA_d_signal_noise_ratio | AJ1: PA_r_readability_note | AK1: PA_r_avg_dependency_depth | AL1: PA_r_max_dependency_depth | AM1: PA_r_cognitive_load | AN1: PA_a_claim_count | AO1: PA_a_claim_density_per1k | AP1: PA_a_evidence_count | AQ1: PA_a_evidence_density_per1k | AR1: PA_a_evidence_to_claim_ratio | AS1: PA_a_falsifiability_markers | AT1: PA_a_argument_grade | AU1: PA_f_transition_density_pct | AV1: PA_f_transition_count | AW1: PA_f_flow_label | AX1: PA_lk_total_links | AY1: PA_lk_link_density_per1k | AZ1: PA_lk_link_citation | BA1: PA_lk_link_concept | BB1: PA_lk_link_dependency | BC1: PA_lk_link_evidence | BD1: PA_lk_link_navigation | BE1: PA_lk_internal_links | BF1: PA_lk_external_links | BG1: PA_lk_internal_external_ratio | BH1: PA_lk_cross_domain_bridges | BI1: PA_lk_link_quality_score | BJ1: PA_lk_underlink_flag | BK1: PA_lk_overlink_flag | BL1: PA_lk_concept_nodes | BM1: PA_lk_concept_edges | BN1: PA_lk_avg_degree | BO1: PA_lk_clustering_coeff | BP1: PA_lk_most_central_paragraph | BQ1: PA_lk_centralization | BR1: PA_lk_isolated_nodes | BS1: L1_word_count | BT1: L1_unique_word_count | BU1: L1_vocab_richness | BV1: L1_paragraph_count | BW1: L1_header_count | BX1: L1_avg_paragraph_words | BY1: L1_keybert_keywords | BZ1: L1_yake_keywords | CA1: L1_top_bigrams | CB1: L1_top_trigrams | CC1: L2_title_detected | CD1: L2_citation_count | CE1: L2_author_year_citation_count | CF1: L2_numeric_citation_count | CG1: L2_citation_density_per1k | CH1: L2_external_theory_count | CI1: L2_external_theories | CJ1: L2_academic_signal_count | CK1: L2_academic_signal_density | CL1: L2_structure_score | CM1: L2_heading_count | CN1: L2_reference_entry_count | CO1: L2_has_abstract | CP1: L2_has_introduction | CQ1: L2_has_methodology | CR1: L2_has_results | CS1: L2_has_discussion | CT1: L2_has_conclusion | CU1: L2_has_references_section | CV1: L2_footnote_count | CW1: L2_url_references | CX1: L2_doi_references | CY1: L2_claim_marker_count | CZ1: L2_claim_density_per1k | DA1: L2_evidence_marker_count | DB1: L2_evidence_density_per1k | DC1: L2_evidence_to_claim_ratio | DD1: L2_falsifiability_marker_count | DE1: L2_falsifiability_density_per1k | DF1: L2_hedge_count | DG1: L2_hedge_density_per1k | DH1: L2_absolute_claim_count | DI1: L2_absolute_density_per1k | DJ1: L2_hedge_to_absolute_ratio | DK1: L2_counterargument_count | DL1: L2_limitation_count | DM1: L2_novelty_marker_count | DN1: L2_definition_marker_count | DO1: L2_quantitative_marker_count | DP1: L2_equation_count | DQ1: L2_equation_density_per1k | DR1: L2_claim_candidate_1 | DS1: L2_claim_candidate_2 | DT1: L2_claim_candidate_3 | DU1: L2_evidence_candidate_1 | DV1: L2_evidence_candidate_2 | DW1: L2_rubric_structure_points | DX1: L2_rubric_grounding_points | DY1: L2_rubric_claim_points | DZ1: L2_rubric_quantitative_points | EA1: L2_rubric_falsifiability_points | EB1: L2_academic_rubric_total | EC1: L2_academic_rubric_grade | ED1: L2_academic_grade | EE1: L3_chi_score | EF1: L3_chi_status | EG1: L3_wisdom_score | EH1: L3_knowledge_score | EI1: L3_wk_ratio | EJ1: L3_wk_status | EK1: L3_fruits_composite | EL1: L3_dominant_fruit | EM1: L3_fruits_detail | EN1: L3_me_avg_score | EO1: L3_me_dominant_variable | EP1: L3_cross_domain_bridges | EQ1: L3_scripture_refs | ER1: L3_ckg_raw | ES1: L3_ckg_tier | ET1: L3_me_G_gravity_belonging | EU1: L3_me_M_mass_meaning | EV1: L3_me_E_entropy_engagement | EW1: L3_me_S_spacetime_structure | EX1: L3_me_T_time_eternity | EY1: L3_me_K_knowledge_logos | EZ1: L3_me_R_relationship | FA1: L3_me_Q_quantum_observer | FB1: L3_me_F_faith_coupling | FC1: L3_me_C_christ_coherence | FD1: L4_7q_verdict | FE1: L5_entity_count | FF1: L5_entity_people | FG1: L5_entity_orgs | FH1: L5_entity_concepts | FI1: L5_entity_types_found | FJ1: L5_key_sentence_1 | FK1: L5_key_sentence_2 | FL1: L5_key_sentence_3 | FM1: L5_topic_count | FN1: L6_truth_score | FO1: L6_coherence_score | FP1: L6_combined_score | FQ1: L6_evidence_density | FR1: L6_falsifiability_density | FS1: L6_hedge_density | FT1: L6_contradiction_flags | FU1: L6_absolute_pressure | FV1: L6_rhetorical_force | FW1: L6_warmth_score | FX1: L6_discipline_score | FY1: L6_fruit_integrity_score | FZ1: L6_anti_fruit_pressure | GA1: L6_sentence_count | GB1: L6_paragraph_count | GC1: L6_section_count | GD1: L6_claim_count | GE1: L6_anchored_claims | GF1: L6_under_supported_claims | GG1: L6_overstated_claims | GH1: L6_speculative_claims | GI1: L6_contradictory_claims | GJ1: L6_falsifiable_claims | GK1: L6_fruit_love | GL1: L6_fruit_joy | GM1: L6_fruit_peace | GN1: L6_fruit_patience | GO1: L6_fruit_kindness | GP1: L6_fruit_goodness | GQ1: L6_fruit_faithfulness | GR1: L6_fruit_gentleness | GS1: L6_fruit_self_control | GT1: L6_anti_love | GU1: L6_anti_joy | GV1: L6_anti_peace | GW1: L6_anti_patience | GX1: L6_anti_kindness | GY1: L6_anti_goodness | GZ1: L6_anti_faithfulness | HA1: L6_anti_gentleness | HB1: L6_anti_self_control | HC1: L6_attr_spiritual_coherence_kind | HD1: L6_attr_spiritual_coherence_pos_hits | HE1: L6_attr_spiritual_coherence_neg_hits | HF1: L6_attr_spiritual_coherence_strength | HG1: L6_attr_spiritual_coherence_counter_pressure | HH1: L6_attr_spiritual_coherence_net_score | HI1: L6_attr_humility_index_kind | HJ1: L6_attr_humility_index_pos_hits | HK1: L6_attr_humility_index_neg_hits | HL1: L6_attr_humility_index_strength | HM1: L6_attr_humility_index_counter_pressure | HN1: L6_attr_humility_index_net_score | HO1: L6_attr_spiritual_discernment_kind | HP1: L6_attr_spiritual_discernment_pos_hits | HQ1: L6_attr_spiritual_discernment_neg_hits | HR1: L6_attr_spiritual_discernment_strength | HS1: L6_attr_spiritual_discernment_counter_pressure | HT1: L6_attr_spiritual_discernment_net_score | HU1: L6_attr_moral_courage_kind | HV1: L6_attr_moral_courage_pos_hits | HW1: L6_attr_moral_courage_neg_hits | HX1: L6_attr_moral_courage_strength | HY1: L6_attr_moral_courage_counter_pressure | HZ1: L6_attr_moral_courage_net_score | IA1: L6_attr_deception_mastery_kind | IB1: L6_attr_deception_mastery_pos_hits | IC1: L6_attr_deception_mastery_neg_hits | ID1: L6_attr_deception_mastery_strength | IE1: L6_attr_deception_mastery_counter_pressure | IF1: L6_attr_deception_mastery_net_score | IG1: L6_attr_charismatic_manipulation_kind | IH1: L6_attr_charismatic_manipulation_pos_hits | II1: L6_attr_charismatic_manipulation_neg_hits | IJ1: L6_attr_charismatic_manipulation_strength | IK1: L6_attr_charismatic_manipulation_counter_pressure | IL1: L6_attr_charismatic_manipulation_net_score | IM1: L6_attr_authority_usurpation_kind | IN1: L6_attr_authority_usurpation_pos_hits | IO1: L6_attr_authority_usurpation_neg_hits | IP1: L6_attr_authority_usurpation_strength | IQ1: L6_attr_authority_usurpation_counter_pressure | IR1: L6_attr_authority_usurpation_net_score | IS1: L6_attr_global_solution_complex_kind | IT1: L6_attr_global_solution_complex_pos_hits | IU1: L6_attr_global_solution_complex_neg_hits | IV1: L6_attr_global_solution_complex_strength | IW1: L6_attr_global_solution_complex_counter_pressure | IX1: L6_attr_global_solution_complex_net_score | IY1: L6_threat_score | IZ1: L6_protection_score | JA1: L6_balance_score | JB1: L6_primary_threats | JC1: L6_primary_protections | JD1: L6_character_posture | JE1: L6_integrity_profiles | JF1: L6_top_supported_1 | JG1: L6_top_supported_2 | JH1: L6_top_risky_1 | JI1: L6_top_risky_2 | JJ1: L7_centrality_within_series | JK1: L7_cluster | JL1: L8_nrc_status | JM1: L8_nrc_fear | JN1: L8_nrc_anger | JO1: L8_nrc_anticipation | JP1: L8_nrc_trust | JQ1: L8_nrc_surprise | JR1: L8_nrc_positive | JS1: L8_nrc_negative | JT1: L8_nrc_sadness | JU1: L8_nrc_disgust | JV1: L8_nrc_joy | JW1: L8_nrc_top_emotions | JX1: L8_goemotions_status | JY1: L8_fruit_emo_love | JZ1: L8_fruit_emo_love_pos | KA1: L8_fruit_emo_love_neg | KB1: L8_fruit_emo_joy | KC1: L8_fruit_emo_joy_pos | KD1: L8_fruit_emo_joy_neg | KE1: L8_fruit_emo_peace | KF1: L8_fruit_emo_peace_pos | KG1: L8_fruit_emo_peace_neg | KH1: L8_fruit_emo_patience | KI1: L8_fruit_emo_patience_pos | KJ1: L8_fruit_emo_patience_neg | KK1: L8_fruit_emo_kindness | KL1: L8_fruit_emo_kindness_pos | KM1: L8_fruit_emo_kindness_neg | KN1: L8_fruit_emo_goodness | KO1: L8_fruit_emo_goodness_pos | KP1: L8_fruit_emo_goodness_neg | KQ1: L8_fruit_emo_faithfulness | KR1: L8_fruit_emo_faithfulness_pos | KS1: L8_fruit_emo_faithfulness_neg | KT1: L8_fruit_emo_gentleness | KU1: L8_fruit_emo_gentleness_pos | KV1: L8_fruit_emo_gentleness_neg | KW1: L8_fruit_emo_self_control | KX1: L8_fruit_emo_self_control_pos | KY1: L8_fruit_emo_self_control_neg | KZ1: L8_anti_emo_hatred | LA1: L8_anti_emo_despair | LB1: L8_anti_emo_conflict | LC1: L8_anti_emo_impatience | LD1: L8_anti_emo_cruelty | LE1: L8_anti_emo_corruption | LF1: L8_anti_emo_betrayal | LG1: L8_anti_emo_harshness | LH1: L8_anti_emo_indulgence | LI1: L8_fruit_emo_composite | LJ1: L8_anti_emo_composite | LK1: L8_fruit_emo_net | LL1: L8_emo_dominant | LM1: L8_emo_top_5 | LN1: L8_fruit_emo_strongest | LO1: L8_fruit_emo_weakest | LP1: L9_textdescriptives_status | LQ1: L9_lr_ttr | LR1: L9_lr_rttr | LS1: L9_lr_cttr | LT1: L9_lr_words | LU1: L9_lr_terms | LV1: L9_lr_mtld | LW1: L9_lr_mattr | LX1: L10_idea_density_mean | LY1: L10_idea_density_min | LZ1: L10_idea_density_max | MA1: L10_idea_density_std | MB1: L10_idea_total_propositions | MC1: L10_idea_paragraphs_analyzed | MD1: L10_idea_density_status | ME1: L10_idea_density_level
A2: P-ad6fd537b9df | B2: MDA-000-series-map.md | C2: BA-733478a8bf | D2: 20260530_220100 | E2: 2026.04.07-B | F2: C:\Users\lowes\Documents\Codex\2026-05-30\okay-let-find-the-open-ai\work\deploy_ready_extracted_md_20260530_220012\MDA-000-series-map.md | G2: 2026-05-30T22:01:00.860876 | H2: C:\Users\lowes\Documents\Codex\2026-05-30\okay-let-find-the-open-ai\outputs\deploy_ready_full_pipeline_20260530\paper_intelligence\snapshots\P-ad6fd537b9df_snapshot.json | I2: L1:ok,L10:ok,L13:skipped,L2:ok,L3:ok,L4:skipped,L5:ok,L6:ok,L7:ok,L8:ok,L9:ok,PA:ok | J2: 367 | K2: 189 | L2: 0.515 | M2: 10 | N2: 2 | O2: 1 | P2: 36.7 | Q2: 5 | R2: 16.8 | S2: 4.6 | T2: 5.7 | U2: 1.7 | V2: 4.4 | W2: 0 | X2: 0 | Y2: 0 | Z2: 0 | AA2: 0 | AB2: MIXED | AC2: FALSE | AD2: sentence-transformers not available | AE2: 0.5304 | AF2: MODERATE | AG2: 0.1771 | AH2: 0.0384 | AI2: 0.7913 | AJ2: textstat not available | AK2: 7.3 | AL2: 16 | AM2: HIGH | AN2: 0 | AO2: 0 | AP2: 11 | AQ2: 29.97 | AR2: 11 | AS2: 0 | AT2: A — Evidence-Rich | AU2: 40 | AV2: 4 | AW2: HIGH | AX2: 2 | AY2: 5.45 | AZ2: 0 | BA2: 2 | BB2: 0 | BC2: 0 | BD2: 0 | BE2: 2 | BF2: 0 | BG2: 2 | BH2: 2 | BI2: 0 | BJ2: TRUE | BK2: FALSE | BL2: 2 | BM2: 1 | BN2: 1 | BO2: 0 | BP2: 0 | BQ2: 1 | BR2: 0 | BS2: 367 | BT2: 189 | BU2: 0.515 | BV2: 3 | BW2: 1 | BX2: 122.3 | BZ2: Series Map(0.0009) | Home Home(0.0019) | Home Previous(0.0027) | Main Index(0.0043) | Series Home(0.0056) | Master HTMl(0.0071) | Map(0.0073) | Moral Decline(0.0086) | Home Back(0.0093) | America Home(0.0099) | Series(0.0214) | Decline(0.0249) | CA2: series map | moral decline | decline america | map moral | entry and | and series | CB2: moral decline america | series map moral | map moral decline | entry and series | CC2: Series Map | Moral Decline of America | CD2: 0 | CE2: 0 | CF2: 0 | CG2: 0 | CH2: 1 | CI2: entropy | CJ2: 4 | CK2: 10.87 | CL2: 3/7 | CM2: 1 | CN2: 0 | CO2: FALSE | CP2: TRUE | CQ2: TRUE | CR2: FALSE | CS2: TRUE | CT2: FALSE | CU2: FALSE | CV2: 0 | CW2: 0 | CX2: 0 | CY2: 0 | CZ2: 0 | DA2: 11 | DB2: 29.89 | DC2: 11 | DD2: 0 | DE2: 0 | DF2: 0 | DG2: 0 | DH2: 1 | DI2: 2.72 | DJ2: 0 | DK2: 0 | DL2: 0 | DM2: 0 | DN2: 0 | DO2: 43 | DP2: 1 | DQ2: 2.72 | DR2: Ring 3 â€” Broader Context Related topics across the framework No connections mapped yet. | DS2: Ring 2 â€” Supporting Evidence Deeper dives and formal treatments No connections mapped yet. | DT2: the Modern State Research Method Human-led research with AI as collaborator, not authority The Trinity-Wave Collapse Mechanism How Father, Son, and Spirit actualize every quantum moment Deep Dives Supplementary analysis and academic papers. | DU2: Introduction: The Lowe Family 1900 Samuel, 1900 1926 Henry, 1926 1950 William, 1950 1974 Thomas, 1974 1998 Jacob, 1998 2025 Jacob, 2025 Core Papers & Domain Analysis The theoretical framework, empirical evidence, and domain-level deep resea | DV2: The Complete Analysis Trans-domain analysis of American moral decline FACTS: The Academic Case The formal academic framework and methodology Technology & Entropy How technological acceleration drives moral entropy Historical Timeline: 1900- | DW2: 2.14 | DX2: 0 | DY2: 2 | DZ2: 5 | EA2: 0 | EB2: 9.14 | EC2: D (Light) | ED2: D (Light) | EE2: 9.78 | EF2: HIGH | EG2: 0.82 | EH2: 4.89 | EI2: 0.167 | EJ2: KNOWLEDGE-DOMINANT | EK2: 1.63 | EL2: goodness | EM2: goodness:3, love:0, joy:0, peace:0, patience:0 | EN2: 2.45 | EO2: E_entropy_engagement | EP2: 0 | EQ2: 1 | ER2: 56.9 | ES2: C — Moderate | ET2: 0 | EU2: 0 | EV2: 8.15 | EW2: 2.72 | EX2: 0.91 | EY2: 0 | EZ2: 1.81 | FA2: 6.34 | FB2: 1.81 | FC2: 2.72 | FD2: not run (use --openai flag) | FE2: 70 | FF2: Samuel, William, Thomas, Jacob, Founders | FG2: HTMl\K-Production-Ready\03-moral-decline\DEPLOY-READY\00-entry-and-series-map\MDA-000-series-map.html, Semantic Collapse, Core Papers & Domain Analysis, American Christianity, The Entropic Society Technology | FH2: American | FI2: ORG, CARDINAL, DATE, WORK_OF_ART, PERSON, FAC, NORP, GPE | FJ2: --- source_html: "\\dlowenas\HPWorkstation\Desktop\Master HTMl\K-Production-Ready\03-moral-decline\DEPLOY-READY\00-entry-and-series-map\MDA-000-series-map | FK2: html" deploy_relative: "00-entry-and-series-map\MDA-000-series-map | FL2: html" title: "Series Map | Moral Decline of America" --- Series Map | Moral Decline of America ﻿ Series Map | Moral Decline of America Home Home Previous | Next Series Home Back to Main Index A Ten- | FM2: 0 | FN2: 0.637 | FO2: 0.775 | FP2: 0.6949 | FQ2: 0.7 | FR2: 0 | FS2: 0 | FT2: 0 | FU2: 0 | FV2: 0.2 | FW2: 0 | FX2: 0.125 | FY2: 0.375 | FZ2: 0 | GA2: 10 | GB2: 1 | GC2: 1 | GD2: 8 | GE2: 0 | GF2: 1 | GG2: 0 | GH2: 0 | GI2: 0 | GJ2: 0 | GK2: 0 | GL2: 0 | GM2: 0 | GN2: 0 | GO2: 0 | GP2: 0.75 | GQ2: 0 | GR2: 0 | GS2: 0.375 | GT2: 0 | GU2: 0 | GV2: 0 | GW2: 0 | GX2: 0 | GY2: 0 | GZ2: 0 | HA2: 0 | HB2: 0 | HC2: protective | HD2: 0 | HE2: 0 | HF2: 0 | HG2: 0 | HH2: 0 | HI2: protective | HJ2: 0 | HK2: 0 | HL2: 0 | HM2: 0 | HN2: 0 | HO2: protective | HP2: 0 | HQ2: 0 | HR2: 0 | HS2: 0 | HT2: 0 | HU2: protective | HV2: 0 | HW2: 0 | HX2: 0 | HY2: 0 | HZ2: 0 | IA2: threat | IB2: 0 | IC2: 0 | ID2: 0 | IE2: 0 | IF2: 0 | IG2: threat | IH2: 0 | II2: 0 | IJ2: 0 | IK2: 0 | IL2: 0 | IM2: threat | IN2: 0 | IO2: 0 | IP2: 0 | IQ2: 0 | IR2: 0 | IS2: threat | IT2: 0 | IU2: 0 | IV2: 0 | IW2: 0 | IX2: 0 | IY2: 0 | IZ2: 0 | JA2: 0 | JD2: disciplined; spiritually ordered; technically strong, spiritually ordered | JE2: coherent but cold; forceful and disciplined; precise but lifeless; technically strong, morally vacant; publication-ready but adversarially incomplete | JF2: Why the Bad Is Easier Than the Good The asymmetry problem — entropy, shortcuts, and the structural cost of virtue The Coherence Metric A physics-based framework for measuring structural integrity across domains The Empirical Evidence Four predictions, four tests, all confirmed — R̄ = 0.986, p < 10⁻⁸ The Great Reconfiguration A century of structural change in American Christianity (1900–2024) The Entropic Society Technology, obsolescence, and the devaluation of American moral capital (1950–2025) The Regulatory Impulse (1900–1910) Defining America’s moral foundation in the Progressive Era The Biaxiosum Audit Name your bias — the Founders vs. | JG2: The Complete Analysis Trans-domain analysis of American moral decline FACTS: The Academic Case The formal academic framework and methodology Technology & Entropy How technological acceleration drives moral entropy Historical Timeline: 1900-2025 125 years of inflection points mapped chronologically The Moral Decline of America — A Genesis-to-Quantum Investigation Related Work Core article, supporting evidence, and broader context Ring 1 â€” This Article The core argument You are here. | JH2: The Ï‡-field measured across a civilization. | JI2: The decline made personal. | JJ2: 0.6167 | JK2: 0 | JL2: fallback: NRCLex not installed | JM2: 0 | JN2: 0 | JO2: 0 | JP2: 0 | JQ2: 0 | JR2: 0 | JS2: 0 | JT2: 0 | JU2: 0 | JV2: 0 | JX2: fallback: PreTrainedTokenizerFast._batch_encode_plus() got an unexpected keyword argument 'local_files_only' | JY2: 0 | JZ2: 0 | KA2: 1 | KB2: 0 | KC2: 0 | KD2: 1 | KE2: 0 | KF2: 0 | KG2: 1 | KH2: 0 | KI2: 0 | KJ2: 1 | KK2: 0 | KL2: 0 | KM2: 1 | KN2: 0 | KO2: 0 | KP2: 1 | KQ2: 0 | KR2: 0 | KS2: 1 | KT2: 0 | KU2: 0 | KV2: 1 | KW2: 0 | KX2: 0 | KY2: 1 | KZ2: 0 | LA2: 0 | LB2: 0 | LC2: 0 | LD2: 0 | LE2: 0 | LF2: 0 | LG2: 0 | LH2: 0 | LI2: 0 | LJ2: 0 | LK2: 0 | LN2: love | LO2: self_control | LP2: fallback: textdescriptives not installed | LQ2: 0.5783 | LR2: 10.2307 | LS2: 7.2342 | LT2: 313 | LU2: 181 | LV2: 78.25 | LW2: 0.8511 | LX2: 0.5272 | LY2: 0.5272 | LZ2: 0.5272 | MA2: 0 | MB2: 165 | MC2: 1 | MD2: fallback: lexical proposition estimate | ME2: HIGH (academic)
A3: P-77064a67c17b | B3: MDA-001-story-introduction.md | C3: BA-733478a8bf | D3: 20260530_220100 | E3: 2026.04.07-B | F3: C:\Users\lowes\Documents\Codex\2026-05-30\okay-let-find-the-open-ai\work\deploy_ready_extracted_md_20260530_220012\MDA-001-story-introduction.md | G3: 2026-05-30T22:01:51.444135 | H3: C:\Users\lowes\Documents\Codex\2026-05-30\okay-let-find-the-open-ai\outputs\deploy_ready_full_pipeline_20260530\paper_intelligence\snapshots\P-77064a67c17b_snapshot.json | I3: L1:ok,L10:ok,L13:skipped,L2:ok,L3:ok,L4:skipped,L5:ok,L6:ok,L7:ok,L8:ok,L9:ok,PA:ok | J3: 902 | K3: 407 | L3: 0.4512 | M3: 70 | N3: 3 | O3: 1 | P3: 12.9 | Q3: 23.3 | R3: 17.9 | S3: 8.9 | T3: 4.9 | U3: 3.2 | V3: 3.9 | W3: 2 | X3: 2 | Y3: 6 | Z3: 1 | AA3: 6 | AB3: MIXED | AC3: FALSE | AD3: sentence-transformers not available | AE3: 0.4781 | AF3: MODERATE | AG3: 0.2639 | AH3: 0.0422 | AI3: 0.705 | AJ3: textstat not available | AK3: 3.7 | AL3: 8 | AM3: MODERATE | AN3: 0 | AO3: 0 | AP3: 3 | AQ3: 3.33 | AR3: 3 | AS3: 0 | AT3: A — Evidence-Rich | AU3: 24.3 | AV3: 17 | AW3: MODERATE | AX3: 7 | AY3: 7.76 | AZ3: 0 | BA3: 6 | BB3: 1 | BC3: 0 | BD3: 0 | BE3: 7 | BF3: 0 | BG3: 7 | BH3: 1 | BI3: 0 | BJ3: FALSE | BK3: FALSE | BL3: 3 | BM3: 3 | BN3: 2 | BO3: 1 | BP3: 0 | BQ3: 1 | BR3: 0 | BS3: 902 | BT3: 407 | BU3: 0.4512 | BV3: 3 | BW3: 1 | BX3: 300.7 | BZ3: Moral Decline(0.0003) | Decline Introduction(0.0021) | Mode Standard(0.0028) | Standard Current(0.0028) | Academic Method(0.0077) | American Story(0.0077) | Decline(0.008) | Moral(0.0083) | Master HTMl(0.0084) | Standard active(0.0092) | bridge Standard(0.0092) | pressure Standard(0.0106) | CA3: moral decline | the father | american story | the son | the truth | truth and | CB3: the truth and | mda story introduction | american story moral | story moral decline | CC3: An American Story | Moral Decline of America | CD3: 0 | CE3: 0 | CF3: 0 | CG3: 0 | CH3: 0 | CJ3: 1 | CK3: 1.11 | CL3: 2/7 | CM3: 1 | CN3: 0 | CO3: FALSE | CP3: TRUE | CQ3: TRUE | CR3: FALSE | CS3: FALSE | CT3: FALSE | CU3: FALSE | CV3: 0 | CW3: 0 | CX3: 0 | CY3: 0 | CZ3: 0 | DA3: 3 | DB3: 3.32 | DC3: 3 | DD3: 0 | DE3: 0 | DF3: 0 | DG3: 0 | DH3: 2 | DI3: 2.21 | DJ3: 0 | DK3: 0 | DL3: 1 | DM3: 0 | DN3: 0 | DO3: 32 | DP3: 0 | DQ3: 0 | DR3: Each of these requires time and structure to develop. | DS3: Part IV: Thomas (1974) - The Breaking 5. | DT3: What was once imposed can now be chosen. | DU3: Ring 2 — Supporting Evidence Deeper dives and formal treatments No connections mapped yet. | DV3: Series Start Series Home Next Theophysics Home MDA-001 of 54 Related Work Core article, supporting evidence, and broader context Ring 1 — This Article The core argument You are here. | DW3: 1.43 | DX3: 0 | DY3: 2 | DZ3: 5 | EA3: 0.5 | EB3: 8.93 | EC3: D (Light) | ED3: F (Needs Citations) | EE3: 3.54 | EF3: WEAK | EG3: 1.55 | EH3: 1.44 | EI3: 1.077 | EJ3: BALANCED | EK3: 4.65 | EL3: goodness | EM3: goodness:6, love:2, peace:2, patience:2, kindness:2 | EN3: 1.99 | EO3: T_time_eternity | EP3: 0 | EQ3: 0 | ER3: 28.7 | ES3: D — Developing | ET3: 1.85 | EU3: 0.74 | EV3: 2.21 | EW3: 4.8 | EX3: 5.54 | EY3: 0.74 | EZ3: 1.11 | FA3: 0 | FB3: 1.48 | FC3: 1.48 | FD3: not run (use --openai flag) | FE3: 76 | FF3: Reader Mode Standard, Standard, Samuel, Henry, Bill | FG3: HTMl\K-Production-Ready\03-moral-decline\DEPLOY-READY\01-story-thread\MDA-001, Delta, The Thesis Behavior, apps7, Matrix - Domain & Virtue Audit Series | FH3: American | FI3: ORG, CARDINAL, NORP, PERSON, WORK_OF_ART, PRODUCT, DATE, GPE, ORDINAL, LOC, QUANTITY, TIME | FJ3: --- source_html: "\\dlowenas\HPWorkstation\Desktop\Master HTMl\K-Production-Ready\03-moral-decline\DEPLOY-READY\01-story-thread\MDA-001-story-introduction | FK3: html" deploy_relative: "01-story-thread\MDA-001-story-introduction | FL3: html" title: "An American Story | Moral Decline of America" --- An American Story | Moral Decline of America ﻿ An American Story | Moral Decline of America Home Home Previous | Next Series Home THEO | FM3: 0 | FN3: 0.5169 | FO3: 0.775 | FP3: 0.6253 | FQ3: 0.4286 | FR3: 0 | FS3: 0 | FT3: 0 | FU3: 0.0071 | FV3: 0.12 | FW3: 0.2137 | FX3: 0.285 | FY3: 0.5089 | FZ3: 0.0158 | GA3: 70 | GB3: 1 | GC3: 1 | GD3: 30 | GE3: 0 | GF3: 19 | GG3: 0 | GH3: 0 | GI3: 0 | GJ3: 0 | GK3: 0.285 | GL3: 0.1425 | GM3: 0.285 | GN3: 0.285 | GO3: 0.1425 | GP3: 0.5701 | GQ3: 0.285 | GR3: 0.1425 | GS3: 0.285 | GT3: 0 | GU3: 0 | GV3: 0.1425 | GW3: 0 | GX3: 0 | GY3: 0 | GZ3: 0 | HA3: 0 | HB3: 0 | HC3: protective | HD3: 0 | HE3: 0 | HF3: 0 | HG3: 0 | HH3: 0 | HI3: protective | HJ3: 0 | HK3: 0 | HL3: 0 | HM3: 0 | HN3: 0 | HO3: protective | HP3: 0 | HQ3: 0 | HR3: 0 | HS3: 0 | HT3: 0 | HU3: protective | HV3: 0 | HW3: 0 | HX3: 0 | HY3: 0 | HZ3: 0 | IA3: threat | IB3: 0 | IC3: 0 | ID3: 0 | IE3: 0 | IF3: 0 | IG3: threat | IH3: 0 | II3: 0 | IJ3: 0 | IK3: 0 | IL3: 0 | IM3: threat | IN3: 0 | IO3: 0 | IP3: 0 | IQ3: 0 | IR3: 0 | IS3: threat | IT3: 0 | IU3: 0 | IV3: 0 | IW3: 0 | IX3: 0 | IY3: 0 | IZ3: 0 | JA3: 0 | JD3: agitated or reactionary; charitable; disciplined; spiritually ordered; technically strong, spiritually ordered | JE3: forceful and disciplined; narrow but rigorous; publication-ready but adversarially incomplete | JF3: The Technology Thread Each generation lives inside a different technological environment: EraTechnologyPaceSilence 1900NoneWalk pace; 6-mile journey to see a girlTotal; stars and crickets 1926Radio, Model TShrinking distance; voices from far awayInvaded 1hr/night 1950Television4hrs/day; images of strangersFamily gathers around one screen 1974TV everywhere, The Pill6hrs/day; chaos in living roomCan't remember last silence 1998Internet, early phonesAlways on; infinite scroll beginsNotifications interrupt thought 2025Smartphone, AI, dating apps7+ hours screen timeMust be *chosen* Technology is not the villain. | JG3: ﻿ An American Story | Moral Decline of America Home Home Previous | Next Series Home THEOPHYSICS Moral Decline Introduction Reader Mode Standard active Easy Plain-language bridge Standard Current article Academic Method + caveats Proof Proof pressure Standard is the live article. | JH3: But optional is not impossible. | JI3: Each man facing the same fundamental questions: Who will I marry? | JJ3: 0.4667 | JK3: 0 | JL3: fallback: NRCLex not installed | JM3: 0 | JN3: 0 | JO3: 0 | JP3: 0 | JQ3: 0 | JR3: 0 | JS3: 0 | JT3: 0 | JU3: 0 | JV3: 0 | JX3: fallback: PreTrainedTokenizerFast._batch_encode_plus() got an unexpected keyword argument 'local_files_only' | JY3: 0 | JZ3: 0 | KA3: 1 | KB3: 0 | KC3: 0 | KD3: 1 | KE3: 0 | KF3: 0 | KG3: 1 | KH3: 0 | KI3: 0 | KJ3: 1 | KK3: 0 | KL3: 0 | KM3: 1 | KN3: 0 | KO3: 0 | KP3: 1 | KQ3: 0 | KR3: 0 | KS3: 1 | KT3: 0 | KU3: 0 | KV3: 1 | KW3: 0 | KX3: 0 | KY3: 1 | KZ3: 0 | LA3: 0 | LB3: 0 | LC3: 0 | LD3: 0 | LE3: 0 | LF3: 0 | LG3: 0 | LH3: 0 | LI3: 0 | LJ3: 0 | LK3: 0 | LN3: love | LO3: self_control | LP3: fallback: textdescriptives not installed | LQ3: 0.442 | LR3: 12.9769 | LS3: 9.1761 | LT3: 862 | LU3: 381 | LV3: 59.6164 | LW3: 0.8298 | LX3: 0.4723 | LY3: 0.4723 | LZ3: 0.4723 | MA3: 0 | MB3: 400 | MC3: 1 | MD3: fallback: lexical proposition estimate | ME3: HIGH (academic)
A4: P-fae02a8699be | B4: MDA-002-samuel-1900.md | C4: BA-733478a8bf | D4: 20260530_220100 | E4: 2026.04.07-B | F4: C:\Users\lowes\Documents\Codex\2026-05-30\okay-let-find-the-open-ai\work\deploy_ready_extracted_md_20260530_220012\MDA-002-samuel-1900.md | G4: 2026-05-30T22:01:52.389328 | H4: C:\Users\lowes\Documents\Codex\2026-05-30\okay-let-find-the-open-ai\outputs\deploy_ready_full_pipeline_20260530\paper_intelligence\snapshots\P-fae02a8699be_snapshot.json | I4: L1:ok,L10:ok,L13:skipped,L2:ok,L3:ok,L4:skipped,L5:ok,L6:ok,L7:ok,L8:ok,L9:ok,PA:ok | J4: 366 | K4: 192 | L4: 0.5246 | M4: 23 | N4: 3 | O4: 1 | P4: 15.9 | Q4: 7.7 | R4: 19.4 | S4: 7.2 | T4: 6.5 | U4: 3.2 | V4: 5.6 | W4: 2 | X4: 6.2 | Y4: 1 | Z4: 0 | AA4: 1 | AB4: MIXED | AC4: FALSE | AD4: sentence-transformers not available | AE4: 0.5262 | AF4: MODERATE | AG4: 0.2322 | AH4: 0.0604 | AI4: 0.7214 | AJ4: textstat not available | AK4: 4.09 | AL4: 7 | AM4: HIGH | AN4: 0 | AO4: 0 | AP4: 3 | AQ4: 8.2 | AR4: 3 | AS4: 0 | AT4: A — Evidence-Rich | AU4: 26.1 | AV4: 6 | AW4: HIGH | AX4: 5 | AY4: 13.66 | AZ4: 0 | BA4: 5 | BB4: 0 | BC4: 0 | BD4: 0 | BE4: 5 | BF4: 0 | BG4: 5 | BH4: 0 | BI4: 0 | BJ4: FALSE | BK4: FALSE | BL4: 3 | BM4: 3 | BN4: 2 | BO4: 1 | BP4: 0 | BQ4: 1 | BR4: 0 | BS4: 366 | BT4: 192 | BU4: 0.5246 | BV4: 3 | BW4: 1 | BX4: 122 | BZ4: Moral Decline(0.0014) | Mode Standard(0.0036) | Standard Current(0.0036) | Moral Weight(0.0047) | Reader Mode(0.0049) | Master HTMl(0.0079) | Academic Method(0.0084) | Standard active(0.0107) | bridge Standard(0.0107) | Easy Plain-language(0.0123) | Decline(0.0131) | pressure Standard(0.0135) | CA4: moral decline | distance still | still had | had moral | moral weight | mda samuel | CB4: distance still had | still had moral | had moral weight | moral weight moral | CC4: When Distance Still Had Moral Weight | Moral Decline of America | CD4: 0 | CE4: 0 | CF4: 0 | CG4: 0 | CH4: 0 | CJ4: 1 | CK4: 2.72 | CL4: 1/7 | CM4: 1 | CN4: 0 | CO4: FALSE | CP4: FALSE | CQ4: TRUE | CR4: FALSE | CS4: FALSE | CT4: FALSE | CU4: FALSE | CV4: 0 | CW4: 0 | CX4: 0 | CY4: 0 | CZ4: 0 | DA4: 3 | DB4: 8.17 | DC4: 3 | DD4: 0 | DE4: 0 | DF4: 0 | DG4: 0 | DH4: 0 | DI4: 0 | DJ4: 0 | DK4: 0 | DL4: 0 | DM4: 0 | DN4: 0 | DO4: 22 | DP4: 0 | DQ4: 0 | DR4: What was once imposed can now be chosen. | DS4: Sixty percent of Americans live in rural areas. | DT4: You learn to wait, because waiting is what life is. | DU4: Ring 2 — Supporting Evidence Deeper dives and formal treatments No connections mapped yet. | DV4: Previous Series Home Next Theophysics Home MDA-002 of 54 Related Work Core article, supporting evidence, and broader context Ring 1 — This Article The core argument You are here. | DW4: 0.71 | DX4: 0 | DY4: 2 | DZ4: 3.67 | EA4: 0 | EB4: 6.38 | EC4: D (Light) | ED4: F (Needs Citations) | EE4: 3 | EF4: WEAK | EG4: 0 | EH4: 3.27 | EI4: 0 | EJ4: KNOWLEDGE-DOMINANT | EK4: 1.63 | EL4: patience | EM4: patience:3, love:0, joy:0, peace:0, kindness:0 | EN4: 1.18 | EO4: E_entropy_engagement | EP4: 0 | EQ4: 0 | ER4: 26 | ES4: D — Developing | ET4: 0 | EU4: 0 | EV4: 2.72 | EW4: 2.72 | EX4: 0.91 | EY4: 0.91 | EZ4: 1.82 | FA4: 0 | FB4: 1.82 | FC4: 0.91 | FD4: not run (use --openai flag) | FE4: 26 | FF4: Samuel Reader Mode Standard, Standard, Samuel, Samuel Lowe, David Lowe | FG4: HTMl\K-Production-Ready\03-moral-decline\DEPLOY-READY\01-story-thread\MDA-002-, Coherence, Information Pace3 | FH4: Americans, American | FI4: ORG, CARDINAL, PERSON, WORK_OF_ART, DATE, PRODUCT, GPE, QUANTITY, PERCENT, NORP, MONEY, TIME | FJ4: --- source_html: "\\dlowenas\HPWorkstation\Desktop\Master HTMl\K-Production-Ready\03-moral-decline\DEPLOY-READY\01-story-thread\MDA-002-samuel-1900 | FK4: html" title: "When Distance Still Had Moral Weight | Moral Decline of America" --- When Distance Still Had Moral Weight | Moral Decline of America ﻿ When Distance Still Had Moral Weight | Moral Decl | FL4: Proof Pressure Layer Vetted Claims for MDA-002-samuel-1900 No promoted claim No claim from this article survived the deterministic Axiom + 7Q gate strongly enough for the proof layer yet | FM4: 0 | FN4: 0.5356 | FO4: 0.775 | FP4: 0.6361 | FQ4: 0.4348 | FR4: 0 | FS4: 0 | FT4: 0 | FU4: 0 | FV4: 0.2 | FW4: 0 | FX4: 0.2299 | FY4: 0.3266 | FZ4: 0 | GA4: 23 | GB4: 1 | GC4: 1 | GD4: 15 | GE4: 0 | GF4: 8 | GG4: 0 | GH4: 0 | GI4: 0 | GJ4: 0 | GK4: 0 | GL4: 0 | GM4: 0 | GN4: 0.6897 | GO4: 0 | GP4: 0 | GQ4: 0 | GR4: 0 | GS4: 0 | GT4: 0 | GU4: 0 | GV4: 0 | GW4: 0 | GX4: 0 | GY4: 0 | GZ4: 0 | HA4: 0 | HB4: 0 | HC4: protective | HD4: 0 | HE4: 0 | HF4: 0 | HG4: 0 | HH4: 0 | HI4: protective | HJ4: 0 | HK4: 0 | HL4: 0 | HM4: 0 | HN4: 0 | HO4: protective | HP4: 0 | HQ4: 0 | HR4: 0 | HS4: 0 | HT4: 0 | HU4: protective | HV4: 0 | HW4: 0 | HX4: 0 | HY4: 0 | HZ4: 0 | IA4: threat | IB4: 0 | IC4: 0 | ID4: 0 | IE4: 0 | IF4: 0 | IG4: threat | IH4: 0 | II4: 0 | IJ4: 0 | IK4: 0 | IL4: 0 | IM4: threat | IN4: 0 | IO4: 0 | IP4: 0 | IQ4: 0 | IR4: 0 | IS4: threat | IT4: 0 | IU4: 0 | IV4: 0 | IW4: 0 | IX4: 0 | IY4: 0 | IZ4: 0 | JA4: 0 | JD4: technically strong, spiritually ordered | JE4: coherent but cold; forceful and disciplined; precise but lifeless; technically strong, morally vacant; publication-ready but adversarially incomplete | JF4: ﻿ When Distance Still Had Moral Weight | Moral Decline of America Home Home Previous | Next Series Home THEOPHYSICS Story 01: Samuel Reader Mode Standard active Easy Plain-language bridge Standard Current article Academic Method + caveats Proof Proof pressure Standard is the live article. | JG4: The Numbers of the Baseline Divorce Rate0.7 per 1,000 Fertility Rate3.5 children/woman Information Pace3 days / 50 miles Church AttendanceFunctionally Universal The silence is vast. | JH4: A world small enough to be whole. | JI4: Just darkness, stars, and the sound of your own breathing. | JJ4: 0.55 | JK4: 0 | JL4: fallback: NRCLex not installed | JM4: 0 | JN4: 0 | JO4: 0 | JP4: 0 | JQ4: 0 | JR4: 0 | JS4: 0 | JT4: 0 | JU4: 0 | JV4: 0 | JX4: fallback: PreTrainedTokenizerFast._batch_encode_plus() got an unexpected keyword argument 'local_files_only' | JY4: 0 | JZ4: 0 | KA4: 1 | KB4: 0 | KC4: 0 | KD4: 1 | KE4: 0 | KF4: 0 | KG4: 1 | KH4: 0 | KI4: 0 | KJ4: 1 | KK4: 0 | KL4: 0 | KM4: 1 | KN4: 0 | KO4: 0 | KP4: 1 | KQ4: 0 | KR4: 0 | KS4: 1 | KT4: 0 | KU4: 0 | KV4: 1 | KW4: 0 | KX4: 0 | KY4: 1 | KZ4: 0 | LA4: 0 | LB4: 0 | LC4: 0 | LD4: 0 | LE4: 0 | LF4: 0 | LG4: 0 | LH4: 0 | LI4: 0 | LJ4: 0 | LK4: 0 | LN4: love | LO4: self_control | LP4: fallback: textdescriptives not installed | LQ4: 0.5879 | LR4: 10.6793 | LS4: 7.5514 | LT4: 330 | LU4: 194 | LV4: 96.25 | LW4: 0.8761 | LX4: 0.4377 | LY4: 0.4377 | LZ4: 0.4377 | MA4: 0 | MB4: 144 | MC4: 1 | MD4: fallback: lexical proposition estimate | ME4: MODERATE (accessible)
A5: P-85382786a23d | B5: MDA-003-measuring-moral-health.md | C5: BA-733478a8bf | D5: 20260530_220100 | E5: 2026.04.07-B | F5: C:\Users\lowes\Documents\Codex\2026-05-30\okay-let-find-the-open-ai\work\deploy_ready_extracted_md_20260530_220012\MDA-003-measuring-moral-health.md | G5: 2026-05-30T22:01:52.855202 | H5: C:\Users\lowes\Documents\Codex\2026-05-30\okay-let-find-the-open-ai\outputs\deploy_ready_full_pipeline_20260530\paper_intelligence\snapshots\P-85382786a23d_snapshot.json | I5: L1:ok,L10:ok,L13:skipped,L2:ok,L3:ok,L4:skipped,L5:ok,L6:ok,L7:ok,L8:ok,L9:ok,PA:ok | J5: 882 | K5: 387 | L5: 0.4388 | M5: 63 | N5: 3 | O5: 1 | P5: 14 | Q5: 21 | R5: 16.6 | S5: 10.6 | T5: 6.7 | U5: 3.2 | V5: 4.6 | W5: 4 | X5: 3.3 | Y5: 14 | Z5: 0 | AA5: 14 | AB5: MIXED | AC5: FALSE | AD5: sentence-transformers not available | AE5: 0.4496 | AF5: MODERATE | AG5: 0.2336 | AH5: 0.0534 | AI5: 0.7255 | AJ5: textstat not available | AK5: 4.17 | AL5: 10 | AM5: HIGH | AN5: 0 | AO5: 0 | AP5: 5 | AQ5: 5.67 | AR5: 5 | AS5: 0 | AT5: A — Evidence-Rich | AU5: 28.6 | AV5: 18 | AW5: HIGH | AX5: 11 | AY5: 12.47 | AZ5: 0 | BA5: 10 | BB5: 1 | BC5: 0 | BD5: 0 | BE5: 11 | BF5: 0 | BG5: 11 | BH5: 0 | BI5: 0.17 | BJ5: FALSE | BK5: FALSE | BL5: 3 | BM5: 3 | BN5: 2 | BO5: 1 | BP5: 0 | BQ5: 1 | BR5: 0 | BS5: 882 | BT5: 387 | BU5: 0.4388 | BV5: 3 | BW5: 1 | BX5: 294 | BZ5: Moral Health(0.0041) | Moral Decline(0.0059) | Measure Moral(0.0083) | Coherence Factor(0.01) | Master HTMl(0.0105) | Coherence(0.0133) | Moral(0.0141) | Health(0.0319) | Decline(0.0363) | America(0.0386) | Factor(0.0392) | PART(0.0415) | CA5: moral health | the coherence | coherence factor | moral decline | can measure | measure moral | CB5: the coherence factor | can measure moral | measure moral health | moral decline america | CC5: Can We Measure Moral Health? | Moral Decline of America | CD5: 0 | CE5: 0 | CF5: 0 | CG5: 0 | CH5: 0 | CJ5: 2 | CK5: 2.27 | CL5: 1/7 | CM5: 1 | CN5: 0 | CO5: FALSE | CP5: FALSE | CQ5: TRUE | CR5: FALSE | CS5: FALSE | CT5: FALSE | CU5: FALSE | CV5: 0 | CW5: 0 | CX5: 0 | CY5: 0 | CZ5: 0 | DA5: 5 | DB5: 5.66 | DC5: 5 | DD5: 0 | DE5: 0 | DF5: 1 | DG5: 1.13 | DH5: 4 | DI5: 4.53 | DJ5: 0.25 | DK5: 0 | DL5: 0 | DM5: 0 | DN5: 0 | DO5: 43 | DP5: 6 | DQ5: 6.8 | DR5: Here's the trajectory: YearÏ‡Status 19000.85Highly coherent 19500.78Stable 19650.72Cracks forming 19730.55Critical drop 20000.40Below warning level 20240.24Below threshold The critical threshold—the point below which societies historically | DS5: GDP tells us how much money moves around. | DT5: You can have high GDP with low coherence. | DU5: If you're willing to follow the data wherever it leads, keep reading. | DV5: Ring 2 â€” Supporting Evidence Deeper dives and formal treatments No connections mapped yet. | DW5: 0.71 | DX5: 0 | DY5: 2 | DZ5: 5 | EA5: 0 | EB5: 7.71 | EC5: D (Light) | ED5: F (Needs Citations) | EE5: 8.89 | EF5: HIGH | EG5: 0.11 | EH5: 3.28 | EI5: 0.034 | EJ5: KNOWLEDGE-DOMINANT | EK5: 1.36 | EL5: peace | EM5: peace:3, love:1, faithfulness:1, hope:1, joy:0 | EN5: 2.57 | EO5: C_christ_coherence | EP5: 0 | EQ5: 0 | ER5: 69.5 | ES5: B — Strong | ET5: 1.13 | EU5: 4.15 | EV5: 3.02 | EW5: 0.76 | EX5: 0.38 | EY5: 1.89 | EZ5: 1.89 | FA5: 0 | FB5: 4.53 | FC5: 7.93 | FD5: not run (use --openai flag) | FE5: 59 | FF5: Reader Mode Standard, Standard, David Lowe • Theophysics Institute, Ring 1 â€, Ring 2 â€ | FG5: HTMl\K-Production-Ready\03-moral-decline\DEPLOY-READY\02-method, Coherence | FH5: Amish, Democrats, Republicans | FI5: ORG, CARDINAL, WORK_OF_ART, PERSON, PRODUCT, GPE, DATE, NORP, FAC | FJ5: --- source_html: "\\dlowenas\HPWorkstation\Desktop\Master HTMl\K-Production-Ready\03-moral-decline\DEPLOY-READY\02-method-and-metrics\MDA-003-measuring-moral-health | FK5: html" deploy_relative: "02-method-and-metrics\MDA-003-measuring-moral-health | FL5: | Moral Decline of America Home Home Previous | Next Series Home Reader Mode Standard active Easy Plain-language bridge Standard Current article Academic Method + caveats Proof Proof pressure Standard | FM5: 0 | FN5: 0.5064 | FO5: 0.775 | FP5: 0.6192 | FQ5: 0.4426 | FR5: 0 | FS5: 0.0164 | FT5: 0 | FU5: 0 | FV5: 0.1443 | FW5: 0.0729 | FX5: 0 | FY5: 0.2824 | FZ5: 0 | GA5: 61 | GB5: 1 | GC5: 1 | GD5: 28 | GE5: 0 | GF5: 14 | GG5: 0 | GH5: 0 | GI5: 0 | GJ5: 0 | GK5: 0.1458 | GL5: 0 | GM5: 0.1458 | GN5: 0 | GO5: 0 | GP5: 0 | GQ5: 0 | GR5: 0 | GS5: 0 | GT5: 0 | GU5: 0 | GV5: 0 | GW5: 0 | GX5: 0 | GY5: 0 | GZ5: 0 | HA5: 0 | HB5: 0 | HC5: protective | HD5: 0 | HE5: 0 | HF5: 0 | HG5: 0 | HH5: 0 | HI5: protective | HJ5: 0 | HK5: 0 | HL5: 0 | HM5: 0 | HN5: 0 | HO5: protective | HP5: 0 | HQ5: 0 | HR5: 0 | HS5: 0 | HT5: 0 | HU5: protective | HV5: 0 | HW5: 0 | HX5: 0 | HY5: 0 | HZ5: 0 | IA5: threat | IB5: 0 | IC5: 0 | ID5: 0 | IE5: 0 | IF5: 0 | IG5: threat | IH5: 0 | II5: 0 | IJ5: 0 | IK5: 0 | IL5: 0 | IM5: threat | IN5: 0 | IO5: 0 | IP5: 0 | IQ5: 0 | IR5: 0 | IS5: threat | IT5: 0 | IU5: 0 | IV5: 0 | IW5: 0 | IX5: 0 | IY5: 0 | IZ5: 0 | JA5: 0 | JD5: mixed spiritual posture | JE5: coherent but cold; forceful and disciplined; precise but lifeless; technically strong, morally vacant; narrow but rigorous | JF5: What This Series Will Show You Over the next nine articles, we're going to: Define exactly what Ï‡ measures (Part 2) Show you what Ï‡ = 0.85 looked like (Part 3) Trace the decline year by year (Parts 4-6) Prove it didn't have to happen (Part 7: The Amish) Show cases where Ï‡ was restored (Parts 8-9) Ask the question that matters (Part 10) By the end, you'll understand: Why everything feels like it's falling apart (it is) Why it happened (we did it to ourselves) Why it didn't have to happen (the Amish prove it) Whether recovery is possible (historically, yes—but only one way) A Warning This series is not about politics. | JG5: Moral Decline of America • Theophysics Institute David Lowe • Theophysics Institute • 2024-2026 Previous Series Home Next Theophysics Home MDA-003 of 54 Related Work Core article, supporting evidence, and broader context Ring 1 â€” This Article The core argument You are here. | JH5: ﻿ Can We Measure Moral Health? | JI5: GDP tells us how much money moves around. | JJ5: 0.4167 | JK5: 0 | JL5: fallback: NRCLex not installed | JM5: 0 | JN5: 0 | JO5: 0 | JP5: 0 | JQ5: 0 | JR5: 0 | JS5: 0 | JT5: 0 | JU5: 0 | JV5: 0 | JX5: fallback: PreTrainedTokenizerFast._batch_encode_plus() got an unexpected keyword argument 'local_files_only' | JY5: 0 | JZ5: 0 | KA5: 1 | KB5: 0 | KC5: 0 | KD5: 1 | KE5: 0 | KF5: 0 | KG5: 1 | KH5: 0 | KI5: 0 | KJ5: 1 | KK5: 0 | KL5: 0 | KM5: 1 | KN5: 0 | KO5: 0 | KP5: 1 | KQ5: 0 | KR5: 0 | KS5: 1 | KT5: 0 | KU5: 0 | KV5: 1 | KW5: 0 | KX5: 0 | KY5: 1 | KZ5: 0 | LA5: 0 | LB5: 0 | LC5: 0 | LD5: 0 | LE5: 0 | LF5: 0 | LG5: 0 | LH5: 0 | LI5: 0 | LJ5: 0 | LK5: 0 | LN5: love | LO5: self_control | LP5: fallback: textdescriptives not installed | LQ5: 0.433 | LR5: 12.52 | LS5: 8.853 | LT5: 836 | LU5: 362 | LV5: 66.9872 | LW5: 0.8582 | LX5: 0.5441 | LY5: 0.5441 | LZ5: 0.5441 | MA5: 0 | MB5: 444 | MC5: 1 | MD5: fallback: lexical proposition estimate | ME5: HIGH (academic)
A6: P-5115499be213 | B6: MDA-005-empirical-evidence.md | C6: BA-733478a8bf | D6: 20260530_220100 | E6: 2026.04.07-B | F6: C:\Users\lowes\Documents\Codex\2026-05-30\okay-let-find-the-open-ai\work\deploy_ready_extracted_md_20260530_220012\MDA-005-empirical-evidence.md | G6: 2026-05-30T22:01:53.785228 | H6: C:\Users\lowes\Documents\Codex\2026-05-30\okay-let-find-the-open-ai\outputs\deploy_ready_full_pipeline_20260530\paper_intelligence\snapshots\P-5115499be213_snapshot.json | I6: L1:ok,L10:ok,L13:skipped,L2:ok,L3:ok,L4:skipped,L5:ok,L6:ok,L7:ok,L8:ok,L9:ok,PA:ok | J6: 1251 | K6: 465 | L6: 0.3717 | M6: 60 | N6: 3 | O6: 1 | P6: 20.9 | Q6: 20 | R6: 22 | S6: 5.4 | T6: 8.8 | U6: 1.8 | V6: 5.5 | W6: 7 | X6: 8.8 | Y6: 9 | Z6: 0 | AA6: 9 | AB6: CONCEPTUAL | AC6: FALSE | AD6: sentence-transformers not available | AE6: 0.417 | AF6: MODERATE | AG6: 0.1863 | AH6: 0.0857 | AI6: 0.744 | AJ6: textstat not available | AK6: 4.87 | AL6: 9 | AM6: HIGH | AN6: 0 | AO6: 0 | AP6: 43 | AQ6: 34.37 | AR6: 43 | AS6: 12 | AT6: A — Evidence-Rich | AU6: 16.7 | AV6: 10 | AW6: MODERATE | AX6: 9 | AY6: 7.19 | AZ6: 0 | BA6: 9 | BB6: 0 | BC6: 0 | BD6: 0 | BE6: 9 | BF6: 0 | BG6: 9 | BH6: 1 | BI6: 0 | BJ6: FALSE | BK6: FALSE | BL6: 3 | BM6: 3 | BN6: 2 | BO6: 1 | BP6: 0 | BQ6: 1 | BR6: 0 | BS6: 1251 | BT6: 465 | BU6: 0.3717 | BV6: 3 | BW6: 1 | BX6: 417 | BZ6: Mode Standard(0.0036) | Standard Current(0.0036) | Reader Mode(0.0055) | Empirical Evidence(0.0116) | Master HTMl(0.0132) | Easy Plain-language(0.0143) | Standard active(0.0149) | bridge Standard(0.0149) | Standard(0.0164) | Decline(0.0165) | pressure Standard(0.0197) | Plain-language bridge(0.0225) | CA6: empirical evidence | phase transition | seven domains | maximum decline | moral decline | the empirical | CB6: the empirical evidence | did not adopt | mda empirical evidence | empirical evidence moral | CC6: The Empirical Evidence | Moral Decline of America | CD6: 0 | CE6: 0 | CF6: 0 | CG6: 0 | CH6: 0 | CJ6: 7 | CK6: 5.59 | CL6: 3/7 | CM6: 1 | CN6: 0 | CO6: FALSE | CP6: FALSE | CQ6: TRUE | CR6: TRUE | CS6: FALSE | CT6: TRUE | CU6: FALSE | CV6: 0 | CW6: 0 | CX6: 0 | CY6: 0 | CZ6: 0 | DA6: 43 | DB6: 34.35 | DC6: 43 | DD6: 5 | DE6: 3.99 | DF6: 0 | DG6: 0 | DH6: 7 | DI6: 5.59 | DJ6: 0 | DK6: 0 | DL6: 9 | DM6: 0 | DN6: 0 | DO6: 165 | DP6: 8 | DQ6: 6.39 | DR6: Across all 21 domain pairs Fisher z-Test z = 7.44 What this equation says in English This is a statistical check. | DS6: p << 0.0001 Threshold Exceeded 21 / 21 All pairs exceed critical r = 0.602 What this equation says in English This is a statistical check. | DT6: Method: Compute pairwise Pearson correlations across all seven domain indices for the full measurement period (1940–2024, n = 11 time points). | DU6: Summary of Evidence Test Prediction Result Significance Cross-domain correlation R̄ ≫ 0 R̄ = 0.986 p << 0.0001 Structural synchronization Breaks in same window 6/7 in 1968–1973 p < 10−8 Threshold behavior Discontinuous decline 2.5x faster a | DV6: It reports whether the measured pattern is strong enough to treat as evidence rather than as a loose impression. | DW6: 2.14 | DX6: 0 | DY6: 2 | DZ6: 5 | EA6: 5 | EB6: 14.14 | EC6: C (Developing) | ED6: D (Light) | EE6: 3.87 | EF6: WEAK | EG6: 0 | EH6: 4.07 | EI6: 0 | EJ6: KNOWLEDGE-DOMINANT | EK6: 1.28 | EL6: peace | EM6: peace:7, self_control:1, love:0, joy:0, patience:0 | EN6: 1.36 | EO6: T_time_eternity | EP6: 0 | EQ6: 0 | ER6: 60.4 | ES6: B — Strong | ET6: 0.53 | EU6: 1.86 | EV6: 1.06 | EW6: 1.33 | EX6: 2.4 | EY6: 0 | EZ6: 0.8 | FA6: 2.13 | FB6: 1.06 | FC6: 2.4 | FD6: not run (use --openai flag) | FE6: 182 | FF6: Reader Mode Standard, Standard, David Lowe • Theophysics Institute, Domains, Maximum Decline | FG6: HTMl\K-Production-Ready\03-moral-decline\DEPLOY-READY\02-method-and-metrics\MDA-005, Collapse, Pairwise Pearson Correlation Matrix, Media, Fisher z-Test | FH6: American, Amish, Roe v. Wade Reproductive | FI6: ORG, CARDINAL, WORK_OF_ART, PERSON, PRODUCT, NORP, DATE, LANGUAGE, GPE, QUANTITY, PERCENT, MONEY, LAW, EVENT | FJ6: --- source_html: "\\dlowenas\HPWorkstation\Desktop\Master HTMl\K-Production-Ready\03-moral-decline\DEPLOY-READY\02-method-and-metrics\MDA-005-empirical-evidence | FK6: html" deploy_relative: "02-method-and-metrics\MDA-005-empirical-evidence | FL6: html" title: "The Empirical Evidence | Moral Decline of America" --- The Empirical Evidence | Moral Decline of America ﻿ The Empirical Evidence | Moral Decline of America Home Home Previous | Next S | FM6: 0 | FN6: 0.6109 | FO6: 0.775 | FP6: 0.6798 | FQ6: 0.6333 | FR6: 0 | FS6: 0 | FT6: 0 | FU6: 0 | FV6: 0.21 | FW6: 0 | FX6: 0.16 | FY6: 0.3033 | FZ6: 0 | GA6: 60 | GB6: 1 | GC6: 1 | GD6: 43 | GE6: 0 | GF6: 10 | GG6: 0 | GH6: 0 | GI6: 0 | GJ6: 0 | GK6: 0 | GL6: 0 | GM6: 0 | GN6: 0 | GO6: 0 | GP6: 0 | GQ6: 0 | GR6: 0 | GS6: 0.48 | GT6: 0 | GU6: 0 | GV6: 0 | GW6: 0 | GX6: 0 | GY6: 0 | GZ6: 0 | HA6: 0 | HB6: 0 | HC6: protective | HD6: 0 | HE6: 0 | HF6: 0 | HG6: 0 | HH6: 0 | HI6: protective | HJ6: 0 | HK6: 0 | HL6: 0 | HM6: 0 | HN6: 0 | HO6: protective | HP6: 0 | HQ6: 0 | HR6: 0 | HS6: 0 | HT6: 0 | HU6: protective | HV6: 0 | HW6: 0 | HX6: 0 | HY6: 0 | HZ6: 0 | IA6: threat | IB6: 0 | IC6: 0 | ID6: 0 | IE6: 0 | IF6: 0 | IG6: threat | IH6: 0 | II6: 0 | IJ6: 0 | IK6: 0 | IL6: 0 | IM6: threat | IN6: 0 | IO6: 0 | IP6: 0 | IQ6: 0 | IR6: 0 | IS6: threat | IT6: 0 | IU6: 0 | IV6: 0 | IW6: 0 | IX6: 0 | IY6: 0 | IZ6: 0 | JA6: 0 | JD6: disciplined; technically strong, spiritually ordered | JE6: coherent but cold; forceful and disciplined; precise but lifeless; technically strong, morally vacant; publication-ready but adversarially incomplete | JF6: If maximum declines were uniformly distributed across 84 years (1940–2024), the probability of 6 or more domains peaking within the same 5-year window is: Probability of Coincidence p < 10-8 This is not coincidence. | JG6: American data, 1900–2025 David Lowe • Theophysics Institute If social coherence (Ï‡) is a real order parameter governed by constraint pressure (P), it makes specific, falsifiable predictions. | JH6: Not vague directional claims. | JI6: Social coherence (Ï‡) behaves as a real order parameter. | JJ6: 0.5667 | JK6: 0 | JL6: fallback: NRCLex not installed | JM6: 0 | JN6: 0 | JO6: 0 | JP6: 0 | JQ6: 0 | JR6: 0 | JS6: 0 | JT6: 0 | JU6: 0 | JV6: 0 | JX6: fallback: PreTrainedTokenizerFast._batch_encode_plus() got an unexpected keyword argument 'local_files_only' | JY6: 0 | JZ6: 0 | KA6: 1 | KB6: 0 | KC6: 0 | KD6: 1 | KE6: 0 | KF6: 0 | KG6: 1 | KH6: 0 | KI6: 0 | KJ6: 1 | KK6: 0 | KL6: 0 | KM6: 1 | KN6: 0 | KO6: 0 | KP6: 1 | KQ6: 0 | KR6: 0 | KS6: 1 | KT6: 0 | KU6: 0 | KV6: 1 | KW6: 0 | KX6: 0 | KY6: 1 | KZ6: 0 | LA6: 0 | LB6: 0 | LC6: 0 | LD6: 0 | LE6: 0 | LF6: 0 | LG6: 0 | LH6: 0 | LI6: 0 | LJ6: 0 | LK6: 0 | LN6: love | LO6: self_control | LP6: fallback: textdescriptives not installed | LQ6: 0.3797 | LR6: 12.2618 | LS6: 8.6704 | LT6: 1043 | LU6: 396 | LV6: 62.214 | LW6: 0.8561 | LX6: 0.5528 | LY6: 0.5528 | LZ6: 0.5528 | MA6: 0 | MB6: 576 | MC6: 1 | MD6: fallback: lexical proposition estimate | ME6: VERY HIGH (dense academic)
A7: P-d67cbfce1ec4 | B7: MDA-006-research-method.md | C7: BA-733478a8bf | D7: 20260530_220100 | E7: 2026.04.07-B | F7: C:\Users\lowes\Documents\Codex\2026-05-30\okay-let-find-the-open-ai\work\deploy_ready_extracted_md_20260530_220012\MDA-006-research-method.md | G7: 2026-05-30T22:01:54.981274 | H7: C:\Users\lowes\Documents\Codex\2026-05-30\okay-let-find-the-open-ai\outputs\deploy_ready_full_pipeline_20260530\paper_intelligence\snapshots\P-d67cbfce1ec4_snapshot.json | I7: L1:ok,L10:ok,L13:skipped,L2:ok,L3:ok,L4:skipped,L5:ok,L6:ok,L7:ok,L8:ok,L9:ok,PA:ok | J7: 1167 | K7: 448 | L7: 0.3839 | M7: 81 | N7: 3 | O7: 1 | P7: 14.4 | Q7: 27 | R7: 18.3 | S7: 11.9 | T7: 5.9 | U7: 3.3 | V7: 6.1 | W7: 12 | X7: 7.2 | Y7: 4 | Z7: 2 | AA7: 2 | AB7: MIXED | AC7: FALSE | AD7: sentence-transformers not available | AE7: 0.4312 | AF7: MODERATE | AG7: 0.3059 | AH7: 0.0609 | AI7: 0.6518 | AJ7: textstat not available | AK7: 4.4 | AL7: 10 | AM7: HIGH | AN7: 0 | AO7: 0 | AP7: 15 | AQ7: 12.85 | AR7: 15 | AS7: 2 | AT7: A — Evidence-Rich | AU7: 25.9 | AV7: 21 | AW7: HIGH | AX7: 6 | AY7: 5.14 | AZ7: 0 | BA7: 4 | BB7: 1 | BC7: 1 | BD7: 0 | BE7: 5 | BF7: 0 | BG7: 5 | BH7: 0 | BI7: 0.04 | BJ7: FALSE | BK7: FALSE | BL7: 3 | BM7: 3 | BN7: 2 | BO7: 1 | BP7: 0 | BQ7: 1 | BR7: 0 | BS7: 1167 | BT7: 448 | BU7: 0.3839 | BV7: 3 | BW7: 1 | BX7: 389 | BZ7: Mode Standard(0.0032) | Standard Current(0.0032) | Reader Mode(0.005) | Measure Decline(0.0056) | Master HTMl(0.0104) | Standard active(0.0116) | bridge Standard(0.0116) | Moral Decline(0.012) | pressure Standard(0.0124) | Easy Plain-language(0.0124) | Standard(0.015) | Question(0.0162) | CA7: moral decline | the research | file question | how measure | measure decline | decline america | CB7: how measure decline | moral decline america | mda research method | measure decline moral | CC7: How We Measure Decline | Moral Decline of America | CD7: 0 | CE7: 0 | CF7: 0 | CG7: 0 | CH7: 1 | CI7: complexity | CJ7: 7 | CK7: 5.99 | CL7: 3/7 | CM7: 1 | CN7: 0 | CO7: FALSE | CP7: FALSE | CQ7: TRUE | CR7: FALSE | CS7: FALSE | CT7: TRUE | CU7: TRUE | CV7: 0 | CW7: 0 | CX7: 0 | CY7: 0 | CZ7: 0 | DA7: 15 | DB7: 12.84 | DC7: 15 | DD7: 1 | DE7: 0.86 | DF7: 1 | DG7: 0.86 | DH7: 6 | DI7: 5.14 | DJ7: 0.17 | DK7: 0 | DL7: 0 | DM7: 2 | DN7: 2 | DO7: 25 | DP7: 1 | DQ7: 0.86 | DR7: It requires a method that can hold that complexity without collapsing it. | DS7: 15 + 15 = 100 David Lowe • Theophysics Institute Previous Series Home Next Theophysics Home MDA-006 of 54 Related Work Core article, supporting evidence, and broader context Ring 1 â€” This Article The core argument You are here. | DT7: Do not judge it yet â€” just collect it. | DU7: Primary sources, data links, study citations, statistics with dates and sourcing. | DV7: File: Quotes_Domains_Links_[Question].md What AI Does â€” and Does Not Do AI Is Used To Map intellectual terrain quickly across multiple disciplines Surface contradictions between competing interpretations Organize competing frameworks side | DW7: 2.14 | DX7: 0 | DY7: 2 | DZ7: 5 | EA7: 1 | EB7: 10.14 | EC7: D (Light) | ED7: D (Light) | EE7: 2.35 | EF7: WEAK | EG7: 0.26 | EH7: 2.14 | EI7: 0.12 | EJ7: KNOWLEDGE-DOMINANT | EK7: 0.51 | EL7: self_control | EM7: self_control:2, kindness:1, love:0, joy:0, peace:0 | EN7: 1.23 | EO7: S_spacetime_structure | EP7: 0 | EQ7: 0 | ER7: 46.8 | ES7: C — Moderate | ET7: 0 | EU7: 0.86 | EV7: 2.85 | EW7: 3.14 | EX7: 2.28 | EY7: 0 | EZ7: 0.86 | FA7: 0.29 | FB7: 1.14 | FC7: 0.86 | FD7: not run (use --openai flag) | FE7: 60 | FF7: Reader Mode Standard, Standard, David Lowe • Theophysics Institute, David Lowe, Captures | FG7: HTMl\K-Production-Ready\03-moral-decline\DEPLOY-READY\02-method, AI, Research Workspace Evidence & Links, Contradictions & Resolution Sense-Making, Domains, & Links Shared Library | FH7: Contradictions | FI7: ORG, CARDINAL, WORK_OF_ART, PERSON, PRODUCT, GPE, DATE, NORP | FJ7: --- source_html: "\\dlowenas\HPWorkstation\Desktop\Master HTMl\K-Production-Ready\03-moral-decline\DEPLOY-READY\02-method-and-metrics\MDA-006-research-method | FK7: html" deploy_relative: "02-method-and-metrics\MDA-006-research-method | FL7: html" title: "How We Measure Decline | Moral Decline of America" --- How We Measure Decline | Moral Decline of America ﻿ How We Measure Decline | Moral Decline of America Home Home Previous | Next S | FM7: 0 | FN7: 0.5495 | FO7: 0.775 | FP7: 0.6442 | FQ7: 0.4938 | FR7: 0 | FS7: 0 | FT7: 0 | FU7: 0 | FV7: 0.2 | FW7: 0.0269 | FX7: 0.0359 | FY7: 0.2739 | FZ7: 0 | GA7: 81 | GB7: 1 | GC7: 1 | GD7: 49 | GE7: 0 | GF7: 18 | GG7: 0 | GH7: 0 | GI7: 0 | GJ7: 0 | GK7: 0 | GL7: 0 | GM7: 0 | GN7: 0 | GO7: 0.1077 | GP7: 0 | GQ7: 0 | GR7: 0 | GS7: 0.1077 | GT7: 0 | GU7: 0 | GV7: 0 | GW7: 0 | GX7: 0 | GY7: 0 | GZ7: 0 | HA7: 0 | HB7: 0 | HC7: protective | HD7: 0 | HE7: 0 | HF7: 0 | HG7: 0 | HH7: 0 | HI7: protective | HJ7: 0 | HK7: 0 | HL7: 0 | HM7: 0 | HN7: 0 | HO7: protective | HP7: 0 | HQ7: 0 | HR7: 0 | HS7: 0 | HT7: 0 | HU7: protective | HV7: 0 | HW7: 0 | HX7: 0 | HY7: 0 | HZ7: 0 | IA7: threat | IB7: 0 | IC7: 0 | ID7: 0 | IE7: 0 | IF7: 0 | IG7: threat | IH7: 0 | II7: 0 | IJ7: 0 | IK7: 0 | IL7: 0 | IM7: threat | IN7: 0 | IO7: 0 | IP7: 0 | IQ7: 0 | IR7: 0 | IS7: threat | IT7: 0 | IU7: 0 | IV7: 0 | IW7: 0 | IX7: 0 | IY7: 0 | IZ7: 0 | JA7: 0 | JD7: mixed spiritual posture | JE7: coherent but cold; forceful and disciplined; precise but lifeless; technically strong, morally vacant; publication-ready but adversarially incomplete | JF7: File: Quotes_Domains_Links_[Question].md What AI Does â€” and Does Not Do AI Is Used To Map intellectual terrain quickly across multiple disciplines Surface contradictions between competing interpretations Organize competing frameworks side by side Suggest where deeper primary-source study is needed Stress-test early conclusions against counterarguments AI Is Not Used To Decide what is true Replace primary-source verification Frame the initial question before the researcher does Select which evidence counts as significant Resolve contradictions that require human judgment Some AI outputs in this project are incomplete. | JG7: 15 + 15 = 100 David Lowe • Theophysics Institute Previous Series Home Next Theophysics Home MDA-006 of 54 Related Work Core article, supporting evidence, and broader context Ring 1 â€” This Article The core argument You are here. | JH7: Some outputs may be incomplete or wrong. | JI7: The research question isn't academic to me. | JJ7: 0.65 | JK7: 0 | JL7: fallback: NRCLex not installed | JM7: 0 | JN7: 0 | JO7: 0 | JP7: 0 | JQ7: 0 | JR7: 0 | JS7: 0 | JT7: 0 | JU7: 0 | JV7: 0 | JX7: fallback: PreTrainedTokenizerFast._batch_encode_plus() got an unexpected keyword argument 'local_files_only' | JY7: 0 | JZ7: 0 | KA7: 1 | KB7: 0 | KC7: 0 | KD7: 1 | KE7: 0 | KF7: 0 | KG7: 1 | KH7: 0 | KI7: 0 | KJ7: 1 | KK7: 0 | KL7: 0 | KM7: 1 | KN7: 0 | KO7: 0 | KP7: 1 | KQ7: 0 | KR7: 0 | KS7: 1 | KT7: 0 | KU7: 0 | KV7: 1 | KW7: 0 | KX7: 0 | KY7: 1 | KZ7: 0 | LA7: 0 | LB7: 0 | LC7: 0 | LD7: 0 | LE7: 0 | LF7: 0 | LG7: 0 | LH7: 0 | LI7: 0 | LJ7: 0 | LK7: 0 | LN7: love | LO7: self_control | LP7: fallback: textdescriptives not installed | LQ7: 0.3996 | LR7: 13.47 | LS7: 9.5247 | LT7: 1136 | LU7: 454 | LV7: 84.2637 | LW7: 0.8817 | LX7: 0.4942 | LY7: 0.4942 | LZ7: 0.4942 | MA7: 0 | MB7: 557 | MC7: 1 | MD7: fallback: lexical proposition estimate | ME7: HIGH (academic)
A8: P-c38c656b2b9b | B8: MDA-007-nine-domains.md | C8: BA-733478a8bf | D8: 20260530_220100 | E8: 2026.04.07-B | F8: C:\Users\lowes\Documents\Codex\2026-05-30\okay-let-find-the-open-ai\work\deploy_ready_extracted_md_20260530_220012\MDA-007-nine-domains.md | G8: 2026-05-30T22:01:56.042056 | H8: C:\Users\lowes\Documents\Codex\2026-05-30\okay-let-find-the-open-ai\outputs\deploy_ready_full_pipeline_20260530\paper_intelligence\snapshots\P-c38c656b2b9b_snapshot.json | I8: L1:ok,L10:ok,L13:skipped,L2:ok,L3:ok,L4:skipped,L5:ok,L6:ok,L7:ok,L8:ok,L9:ok,PA:ok | J8: 1077 | K8: 487 | L8: 0.4522 | M8: 64 | N8: 3 | O8: 1 | P8: 16.8 | Q8: 21.3 | R8: 23.2 | S8: 8 | T8: 6.4 | U8: 2.5 | V8: 4.9 | W8: 6 | X8: 5.4 | Y8: 8 | Z8: 2 | AA8: 4 | AB8: CONCEPTUAL | AC8: FALSE | AD8: sentence-transformers not available | AE8: 0.4438 | AF8: MODERATE | AG8: 0.1681 | AH8: 0.0428 | AI8: 0.7963 | AJ8: textstat not available | AK8: 4.57 | AL8: 9 | AM8: HIGH | AN8: 1 | AO8: 0.93 | AP8: 3 | AQ8: 2.79 | AR8: 3 | AS8: 1 | AT8: A — Evidence-Rich | AU8: 21.9 | AV8: 14 | AW8: MODERATE | AX8: 15 | AY8: 13.93 | AZ8: 0 | BA8: 13 | BB8: 2 | BC8: 0 | BD8: 0 | BE8: 15 | BF8: 0 | BG8: 15 | BH8: 1 | BI8: 0 | BJ8: FALSE | BK8: FALSE | BL8: 3 | BM8: 3 | BN8: 2 | BO8: 1 | BP8: 0 | BQ8: 1 | BR8: 0 | BS8: 1077 | BT8: 487 | BU8: 0.4522 | BV8: 3 | BW8: 1 | BX8: 359 | BZ8: Mode Standard(0.0037) | Reader Mode(0.0054) | Academic Method(0.0094) | Master HTMl(0.0119) | Easy Plain-language(0.0141) | Standard active(0.0141) | bridge Standard(0.0141) | pressure Standard(0.0147) | Standard(0.0167) | America(0.0185) | Coherence Factor(0.02) | Plain-language bridge(0.0209) | CA8: why matters | nine domains | moral decline | coherence factor | civic participation | shared meaning | CB8: moral decline america | the coherence factor | mda nine domains | america made moral | CC8: What America Is Made Of | Moral Decline of America | CD8: 0 | CE8: 0 | CF8: 0 | CG8: 0 | CH8: 0 | CJ8: 1 | CK8: 0.93 | CL8: 1/7 | CM8: 1 | CN8: 0 | CO8: FALSE | CP8: FALSE | CQ8: TRUE | CR8: FALSE | CS8: FALSE | CT8: FALSE | CU8: FALSE | CV8: 0 | CW8: 0 | CX8: 0 | CY8: 1 | CZ8: 0.93 | DA8: 3 | DB8: 2.78 | DC8: 3 | DD8: 1 | DE8: 0.93 | DF8: 0 | DG8: 0 | DH8: 16 | DI8: 14.84 | DJ8: 0 | DK8: 0 | DL8: 0 | DM8: 0 | DN8: 0 | DO8: 115 | DP8: 6 | DQ8: 5.57 | DR8: When it disappears, everything must be argued. | DS8: The Threshold Question Why do we say Ï‡ = 0.35 is the threshold? | DT8: Without it, every transaction requires verification, every promise requires enforcement, and coordination becomes impossible. | DU8: Ring 2 â€” Supporting Evidence Deeper dives and formal treatments No connections mapped yet. | DV8: Moral Decline of America • Theophysics Institute David Lowe • Theophysics Institute • 2024-2026 Previous Series Home Next Theophysics Home MDA-007 of 54 Related Work Core article, supporting evidence, and broader context Ring 1 â€” This Art | DW8: 0.71 | DX8: 0 | DY8: 2.17 | DZ8: 5 | EA8: 1 | EB8: 8.88 | EC8: D (Light) | ED8: F (Needs Citations) | EE8: 6.82 | EF8: STRONG | EG8: 0.19 | EH8: 1.86 | EI8: 0.1 | EJ8: KNOWLEDGE-DOMINANT | EK8: 1.11 | EL8: self_control | EM8: self_control:3, love:1, faithfulness:1, hope:1, joy:0 | EN8: 2.72 | EO8: C_christ_coherence | EP8: 0 | EQ8: 0 | ER8: 47.1 | ES8: C — Moderate | ET8: 1.86 | EU8: 4.95 | EV8: 3.09 | EW8: 0.93 | EX8: 0.62 | EY8: 2.78 | EZ8: 1.86 | FA8: 0.62 | FB8: 4.95 | FC8: 5.57 | FD8: not run (use --openai flag) | FE8: 87 | FF8: Reader Mode Standard, Standard, David Lowe • Theophysics Institute, Civic, Jumps | FG8: HTMl\K-Production-Ready\03-moral-decline\DEPLOY-READY\02-method, Social Trust, Safety (S, Self-Control (C, STD | FH8: Mental | FI8: ORG, CARDINAL, WORK_OF_ART, GPE, PERSON, PRODUCT, DATE, EVENT, NORP, ORDINAL, PERCENT | FJ8: --- source_html: "\\dlowenas\HPWorkstation\Desktop\Master HTMl\K-Production-Ready\03-moral-decline\DEPLOY-READY\02-method-and-metrics\MDA-007-nine-domains | FK8: html" deploy_relative: "02-method-and-metrics\MDA-007-nine-domains | FL8: html" title: "What America Is Made Of | Moral Decline of America" --- What America Is Made Of | Moral Decline of America ﻿ What America Is Made Of | Moral Decline of America Home Home Previous | Nex | FM8: 0 | FN8: 0.5422 | FO8: 0.775 | FP8: 0.64 | FQ8: 0.4545 | FR8: 0 | FS8: 0 | FT8: 0 | FU8: 0.0152 | FV8: 0.197 | FW8: 0.0315 | FX8: 0.1261 | FY8: 0.2787 | FZ8: 0.042 | GA8: 66 | GB8: 1 | GC8: 1 | GD8: 40 | GE8: 0 | GF8: 18 | GG8: 1 | GH8: 0 | GI8: 0 | GJ8: 0 | GK8: 0.1261 | GL8: 0 | GM8: 0 | GN8: 0 | GO8: 0 | GP8: 0 | GQ8: 0 | GR8: 0 | GS8: 0.3782 | GT8: 0 | GU8: 0.1261 | GV8: 0.2521 | GW8: 0 | GX8: 0 | GY8: 0 | GZ8: 0 | HA8: 0 | HB8: 0 | HC8: protective | HD8: 0 | HE8: 0 | HF8: 0 | HG8: 0 | HH8: 0 | HI8: protective | HJ8: 0 | HK8: 0 | HL8: 0 | HM8: 0 | HN8: 0 | HO8: protective | HP8: 0 | HQ8: 0 | HR8: 0 | HS8: 0 | HT8: 0 | HU8: protective | HV8: 0 | HW8: 0 | HX8: 0 | HY8: 0 | HZ8: 0 | IA8: threat | IB8: 0 | IC8: 0 | ID8: 0 | IE8: 0 | IF8: 0 | IG8: threat | IH8: 0 | II8: 0 | IJ8: 0 | IK8: 0 | IL8: 0 | IM8: threat | IN8: 0 | IO8: 0 | IP8: 0 | IQ8: 0 | IR8: 0 | IS8: threat | IT8: 0 | IU8: 0 | IV8: 0 | IW8: 0 | IX8: 0 | IY8: 0 | IZ8: 0 | JA8: 0 | JD8: agitated or reactionary; disciplined | JE8: coherent but cold; forceful and disciplined; precise but lifeless; technically strong, morally vacant; publication-ready but adversarially incomplete | JF8: 1900 score0.92 2024 score0.20 The Coherence Factor Formula Ï‡ is calculated as the weighted average of all nine domains: Coherence Factor Ï‡ = (F + T + S + C + M + E + P + Σ + I) / 9 Each domain is normalized to a 0–1 scale using historical benchmarks. | JG8: ﻿ What America Is Made Of | Moral Decline of America Home Home Previous | Next Series Home Reader Mode Standard active Easy Plain-language bridge Standard Current article Academic Method + caveats Proof Proof pressure Standard is the live article. | JH8: When people fear each other, community becomes impossible. | JI8: Now let's open the hood. | JJ8: 0.55 | JK8: 0 | JL8: fallback: NRCLex not installed | JM8: 0 | JN8: 0 | JO8: 0 | JP8: 0 | JQ8: 0 | JR8: 0 | JS8: 0 | JT8: 0 | JU8: 0 | JV8: 0 | JX8: fallback: PreTrainedTokenizerFast._batch_encode_plus() got an unexpected keyword argument 'local_files_only' | JY8: 0 | JZ8: 0 | KA8: 1 | KB8: 0 | KC8: 0 | KD8: 1 | KE8: 0 | KF8: 0 | KG8: 1 | KH8: 0 | KI8: 0 | KJ8: 1 | KK8: 0 | KL8: 0 | KM8: 1 | KN8: 0 | KO8: 0 | KP8: 1 | KQ8: 0 | KR8: 0 | KS8: 1 | KT8: 0 | KU8: 0 | KV8: 1 | KW8: 0 | KX8: 0 | KY8: 1 | KZ8: 0 | LA8: 0 | LB8: 0 | LC8: 0 | LD8: 0 | LE8: 0 | LF8: 0 | LG8: 0 | LH8: 0 | LI8: 0 | LJ8: 0 | LK8: 0 | LN8: love | LO8: self_control | LP8: fallback: textdescriptives not installed | LQ8: 0.4432 | LR8: 13.9806 | LS8: 9.8858 | LT8: 995 | LU8: 441 | LV8: 79.7276 | LW8: 0.8873 | LX8: 0.6029 | LY8: 0.6029 | LZ8: 0.6029 | MA8: 0 | MB8: 592 | MC8: 1 | MD8: fallback: lexical proposition estimate | ME8: VERY HIGH (dense academic)
A9: P-5eaaaea5ccd2 | B9: MDA-008-henry-1926.md | C9: BA-733478a8bf | D9: 20260530_220100 | E9: 2026.04.07-B | F9: C:\Users\lowes\Documents\Codex\2026-05-30\okay-let-find-the-open-ai\work\deploy_ready_extracted_md_20260530_220012\MDA-008-henry-1926.md | G9: 2026-05-30T22:01:57.146552 | H9: C:\Users\lowes\Documents\Codex\2026-05-30\okay-let-find-the-open-ai\outputs\deploy_ready_full_pipeline_20260530\paper_intelligence\snapshots\P-5eaaaea5ccd2_snapshot.json | I9: L1:ok,L10:ok,L13:skipped,L2:ok,L3:ok,L4:skipped,L5:ok,L6:ok,L7:ok,L8:ok,L9:ok,PA:ok | J9: 3803 | K9: 1147 | L9: 0.3016 | M9: 318 | N9: 3 | O9: 1 | P9: 12 | Q9: 106 | R9: 15.7 | S9: 11.5 | T9: 4.3 | U9: 4.2 | V9: 7.6 | W9: 17 | X9: 3.1 | Y9: 28 | Z9: 3 | AA9: 9.33 | AB9: MIXED | AC9: FALSE | AD9: sentence-transformers not available | AE9: 0.4233 | AF9: MODERATE | AG9: 0.3455 | AH9: 0.0308 | AI9: 0.6343 | AJ9: textstat not available | AK9: 3.5 | AL9: 7 | AM9: MODERATE | AN9: 0 | AO9: 0 | AP9: 3 | AQ9: 0.79 | AR9: 3 | AS9: 0 | AT9: A — Evidence-Rich | AU9: 21.7 | AV9: 69 | AW9: MODERATE | AX9: 15 | AY9: 3.94 | AZ9: 0 | BA9: 15 | BB9: 0 | BC9: 0 | BD9: 0 | BE9: 15 | BF9: 0 | BG9: 15 | BH9: 1 | BI9: 0 | BJ9: FALSE | BK9: FALSE | BL9: 3 | BM9: 3 | BN9: 2 | BO9: 1 | BP9: 0 | BQ9: 1 | BR9: 0 | BS9: 3803 | BT9: 1147 | BU9: 0.3016 | BV9: 3 | BW9: 1 | BX9: 1267.7 | BZ9: Henry(0.0028) | Mode Standard(0.0032) | Standard Current(0.0032) | Reader Mode(0.0053) | Academic Method(0.0091) | Henry Reader(0.0105) | Samuel(0.0111) | Voices Entered(0.0121) | Master HTMl(0.0133) | Easy Plain-language(0.0135) | Standard active(0.0139) | bridge Standard(0.0139) | CA9: his father | the world | the radio | the same | the farm | doesn know | CB9: voices entered the | entered the home | the home moral | home moral decline | CC9: When Voices Entered the Home | Moral Decline of America | CD9: 0 | CE9: 0 | CF9: 0 | CG9: 0 | CH9: 0 | CJ9: 1 | CK9: 0.26 | CL9: 1/7 | CM9: 1 | CN9: 0 | CO9: FALSE | CP9: FALSE | CQ9: TRUE | CR9: FALSE | CS9: FALSE | CT9: FALSE | CU9: FALSE | CV9: 0 | CW9: 0 | CX9: 0 | CY9: 1 | CZ9: 0.26 | DA9: 3 | DB9: 0.79 | DC9: 3 | DD9: 0 | DE9: 0 | DF9: 10 | DG9: 2.63 | DH9: 15 | DI9: 3.94 | DJ9: 0.67 | DK9: 0 | DL9: 3 | DM9: 9 | DN9: 1 | DO9: 67 | DP9: 0 | DQ9: 0 | DR9: He lives in a world where patience is required, where faithfulness is expected, where the costs of failure are high and visible. | DS9: Samuel holds his gaze for a long moment. | DT9: The radio says so, when they turn it on. | DU9: Ring 2 — Supporting Evidence Deeper dives and formal treatments No connections mapped yet. | DV9: Previous Series Home Next Theophysics Home MDA-008 of 54 Related Work Core article, supporting evidence, and broader context Ring 1 — This Article The core argument You are here. | DW9: 0.71 | DX9: 0 | DY9: 2.17 | DZ9: 5 | EA9: 1.5 | EB9: 9.38 | EC9: D (Light) | ED9: F (Needs Citations) | EE9: 1.66 | EF9: WEAK | EG9: 0.26 | EH9: 0.32 | EI9: 0.833 | EJ9: KNOWLEDGE-DOMINANT | EK9: 1.74 | EL9: goodness | EM9: goodness:10, patience:7, faithfulness:5, love:3, kindness:3 | EN9: 1.13 | EO9: T_time_eternity | EP9: 0 | EQ9: 0 | ER9: 19.3 | ES9: F — Needs Work | ET9: 0.88 | EU9: 0.79 | EV9: 1.49 | EW9: 1.75 | EX9: 3.15 | EY9: 0.35 | EZ9: 0.35 | FA9: 0.53 | FB9: 0.61 | FC9: 1.4 | FD9: not run (use --openai flag) | FE9: 285 | FF9: Henry Reader Mode Standard, Standard, Samuel, Lowe, Henry | FG9: HTMl\K-Production-Ready\03-moral-decline\DEPLOY-READY\01-story-thread\MDA-008-henry-1926.html, Radiola, Mercers, The Options Henry's, Richland | FH9: American, Americans | FI9: ORG, CARDINAL, PERSON, WORK_OF_ART, PRODUCT, GPE, DATE, QUANTITY, NORP, TIME, ORDINAL, MONEY, PERCENT, EVENT, FAC | FJ9: --- source_html: "\\dlowenas\HPWorkstation\Desktop\Master HTMl\K-Production-Ready\03-moral-decline\DEPLOY-READY\01-story-thread\MDA-008-henry-1926 | FK9: html" title: "When Voices Entered the Home | Moral Decline of America" --- When Voices Entered the Home | Moral Decline of America ﻿ When Voices Entered the Home | Moral Decline of America Home Home | FL9: Proof Pressure Layer Vetted Claims for MDA-008-henry-1926 No promoted claim No claim from this article survived the deterministic Axiom + 7Q gate strongly enough for the proof layer yet | FM9: 0 | FN9: 0.5195 | FO9: 0.775 | FP9: 0.6268 | FQ9: 0.4726 | FR9: 0.003 | FS9: 0.0305 | FT9: 0 | FU9: 0.0072 | FV9: 0.1402 | FW9: 0.0165 | FX9: 0.0883 | FY9: 0.3066 | FZ9: 0.0147 | GA9: 328 | GB9: 1 | GC9: 1 | GD9: 153 | GE9: 1 | GF9: 63 | GG9: 2 | GH9: 2 | GI9: 0 | GJ9: 0 | GK9: 0 | GL9: 0 | GM9: 0 | GN9: 0.0993 | GO9: 0.0662 | GP9: 0.2648 | GQ9: 0.1324 | GR9: 0 | GS9: 0.0331 | GT9: 0.0331 | GU9: 0.0331 | GV9: 0.0331 | GW9: 0 | GX9: 0.0331 | GY9: 0 | GZ9: 0 | HA9: 0 | HB9: 0 | HC9: protective | HD9: 0 | HE9: 0 | HF9: 0 | HG9: 0 | HH9: 0 | HI9: protective | HJ9: 0 | HK9: 0 | HL9: 0 | HM9: 0 | HN9: 0 | HO9: protective | HP9: 0 | HQ9: 0 | HR9: 0 | HS9: 0 | HT9: 0 | HU9: protective | HV9: 0 | HW9: 0 | HX9: 0 | HY9: 0 | HZ9: 0 | IA9: threat | IB9: 0 | IC9: 0 | ID9: 0 | IE9: 0 | IF9: 0 | IG9: threat | IH9: 0 | II9: 0 | IJ9: 0 | IK9: 0 | IL9: 0 | IM9: threat | IN9: 0 | IO9: 0 | IP9: 0 | IQ9: 0 | IR9: 0 | IS9: threat | IT9: 0 | IU9: 0 | IV9: 0 | IW9: 0 | IX9: 0 | IY9: 0 | IZ9: 0 | JA9: 0 | JD9: technically strong, spiritually ordered | JE9: coherent but cold; forceful and disciplined; precise but lifeless; technically strong, morally vacant; narrow but rigorous | JF9: He just knows it's 1945, and the war is over, and his son is thirteen, and the farm is still here, and that's enough. | JG9: "This is when you find out who you are," Samuel tells Henry in the winter of 1931. | JH9: Moments in the car when he could push further. | JI9: Importantly, nothing appears broken. | JJ9: 0.3667 | JK9: 0 | JL9: fallback: NRCLex not installed | JM9: 0 | JN9: 0 | JO9: 0 | JP9: 0 | JQ9: 0 | JR9: 0 | JS9: 0 | JT9: 0 | JU9: 0 | JV9: 0 | JX9: fallback: PreTrainedTokenizerFast._batch_encode_plus() got an unexpected keyword argument 'local_files_only' | JY9: 0 | JZ9: 0 | KA9: 1 | KB9: 0 | KC9: 0 | KD9: 1 | KE9: 0 | KF9: 0 | KG9: 1 | KH9: 0 | KI9: 0 | KJ9: 1 | KK9: 0 | KL9: 0 | KM9: 1 | KN9: 0 | KO9: 0 | KP9: 1 | KQ9: 0 | KR9: 0 | KS9: 1 | KT9: 0 | KU9: 0 | KV9: 1 | KW9: 0 | KX9: 0 | KY9: 1 | KZ9: 0 | LA9: 0 | LB9: 0 | LC9: 0 | LD9: 0 | LE9: 0 | LF9: 0 | LG9: 0 | LH9: 0 | LI9: 0 | LJ9: 0 | LK9: 0 | LN9: love | LO9: self_control | LP9: fallback: textdescriptives not installed | LQ9: 0.2861 | LR9: 17.6912 | LS9: 12.5096 | LT9: 3824 | LU9: 1094 | LV9: 86.9397 | LW9: 0.8774 | LX9: 0.4213 | LY9: 0.4213 | LZ9: 0.4213 | MA9: 0 | MB9: 1561 | MC9: 1 | MD9: fallback: lexical proposition estimate | ME9: MODERATE (accessible)
A10: P-6174b3e6eed2 | B10: MDA-009-the-1900-baseline.md | C10: BA-733478a8bf | D10: 20260530_220100 | E10: 2026.04.07-B | F10: C:\Users\lowes\Documents\Codex\2026-05-30\okay-let-find-the-open-ai\work\deploy_ready_extracted_md_20260530_220012\MDA-009-the-1900-baseline.md | G10: 2026-05-30T22:02:00.087004 | H10: C:\Users\lowes\Documents\Codex\2026-05-30\okay-let-find-the-open-ai\outputs\deploy_ready_full_pipeline_20260530\paper_intelligence\snapshots\P-6174b3e6eed2_snapshot.json | I10: L1:ok,L10:ok,L13:skipped,L2:ok,L3:ok,L4:skipped,L5:ok,L6:ok,L7:ok,L8:ok,L9:ok,PA:ok | J10: 1327 | K10: 589 | L10: 0.4439 | M10: 106 | N10: 3 | O10: 1 | P10: 12.5 | Q10: 35.3 | R10: 20.2 | S10: 8.9 | T10: 7.1 | U10: 2.7 | V10: 4 | W10: 8 | X10: 5.2 | Y10: 7 | Z10: 0 | AA10: 7 | AB10: CONCEPTUAL | AC10: FALSE | AD10: sentence-transformers not available | AE10: 0.4601 | AF10: MODERATE | AG10: 0.2487 | AH10: 0.0498 | AI10: 0.7139 | AJ10: textstat not available | AK10: 3.73 | AL10: 9 | AM10: MODERATE | AN10: 0 | AO10: 0 | AP10: 5 | AQ10: 3.77 | AR10: 5 | AS10: 0 | AT10: A — Evidence-Rich | AU10: 17.9 | AV10: 19 | AW10: MODERATE | AX10: 13 | AY10: 9.8 | AZ10: 0 | BA10: 13 | BB10: 0 | BC10: 0 | BD10: 0 | BE10: 13 | BF10: 0 | BG10: 13 | BH10: 0 | BI10: 0 | BJ10: FALSE | BK10: FALSE | BL10: 3 | BM10: 3 | BN10: 2 | BO10: 1 | BP10: 0 | BQ10: 1 | BR10: 0 | BS10: 1327 | BT10: 589 | BU10: 0.4439 | BV10: 3 | BW10: 1 | BX10: 442.3 | BZ10: Mode Standard(0.003) | Reader Mode(0.0048) | Master HTMl(0.0092) | Standard active(0.0103) | bridge Standard(0.0103) | pressure Standard(0.0115) | Easy Plain-language(0.0117) | Standard(0.0144) | Standard Current(0.0164) | Plain-language bridge(0.0166) | Home Reader(0.0231) | people(0.0241) | CA10: the baseline | the numbers | meant practice | moral decline | decline america | the coherence | CB10: moral decline america | mda the baseline | the baseline moral | baseline moral decline | CC10: The 1900 Baseline | Moral Decline of America | CD10: 0 | CE10: 0 | CF10: 0 | CG10: 0 | CH10: 0 | CJ10: 1 | CK10: 0.75 | CL10: 2/7 | CM10: 1 | CN10: 0 | CO10: FALSE | CP10: FALSE | CQ10: TRUE | CR10: FALSE | CS10: FALSE | CT10: FALSE | CU10: TRUE | CV10: 0 | CW10: 0 | CX10: 0 | CY10: 1 | CZ10: 0.75 | DA10: 5 | DB10: 3.77 | DC10: 5 | DD10: 0 | DE10: 0 | DF10: 1 | DG10: 0.75 | DH10: 3 | DI10: 2.26 | DJ10: 0.33 | DK10: 0 | DL10: 0 | DM10: 0 | DN10: 0 | DO10: 83 | DP10: 17 | DQ10: 12.8 | DR10: Overeating was physically difficult—food required preparation. | DS10: What did America look like when Ï‡ = 0.85? | DT10: Self-Control Ï‡C = 0.80 The numbers Obesity rate: ~5% (vs. | DU10: Ring 2 â€” Supporting Evidence Deeper dives and formal treatments No connections mapped yet. | DV10: Moral Decline of America • Theophysics Institute David Lowe • Theophysics Institute • 2024-2026 Previous Series Home Next Theophysics Home MDA-009 of 54 Related Work Core article, supporting evidence, and broader context Ring 1 â€” This Art | DW10: 1.43 | DX10: 0 | DY10: 2.17 | DZ10: 5 | EA10: 0 | EB10: 8.6 | EC10: D (Light) | ED10: F (Needs Citations) | EE10: 4.22 | EF10: MODERATE | EG10: 0.15 | EH10: 1.43 | EI10: 0.105 | EJ10: KNOWLEDGE-DOMINANT | EK10: 1.66 | EL10: self_control | EM10: self_control:3, love:2, peace:1, goodness:1, faithfulness:1 | EN10: 1.91 | EO10: T_time_eternity | EP10: 0 | EQ10: 0 | ER10: 36.1 | ES10: D — Developing | ET10: 2.26 | EU10: 2.76 | EV10: 2.26 | EW10: 0.75 | EX10: 3.01 | EY10: 2.51 | EZ10: 0.5 | FA10: 0.25 | FB10: 2.26 | FC10: 2.51 | FD10: not run (use --openai flag) | FE10: 92 | FF10: Reader Mode Standard, Standard, David Lowe • Theophysics Institute, Volunteer, Adam | FG10: HTMl\K-Production-Ready\03-moral-decline\DEPLOY-READY\03-evidence-chronology\MDA-009-, MDA-009, Mental Health, Civic, Elks | FH10: Christian | FI10: ORG, DATE, CARDINAL, WORK_OF_ART, PERSON, PRODUCT, GPE, PERCENT, ORDINAL, NORP | FJ10: --- source_html: "\\dlowenas\HPWorkstation\Desktop\Master HTMl\K-Production-Ready\03-moral-decline\DEPLOY-READY\03-evidence-chronology\MDA-009-the-1900-baseline | FK10: html" deploy_relative: "03-evidence-chronology\MDA-009-the-1900-baseline | FL10: html" title: "The 1900 Baseline | Moral Decline of America" --- The 1900 Baseline | Moral Decline of America ﻿ The 1900 Baseline | Moral Decline of America Home Home Previous | Next Series Home Read | FM10: 0 | FN10: 0.4662 | FO10: 0.775 | FP10: 0.5959 | FQ10: 0.2661 | FR10: 0.0092 | FS10: 0 | FT10: 0 | FU10: 0.0046 | FV10: 0.0606 | FW10: 0.0495 | FX10: 0.0989 | FY10: 0.2945 | FZ10: 0.033 | GA10: 109 | GB10: 1 | GC10: 1 | GD10: 28 | GE10: 1 | GF10: 10 | GG10: 0 | GH10: 0 | GI10: 0 | GJ10: 0 | GK10: 0.1979 | GL10: 0 | GM10: 0 | GN10: 0 | GO10: 0 | GP10: 0.0989 | GQ10: 0 | GR10: 0 | GS10: 0.2968 | GT10: 0 | GU10: 0.0989 | GV10: 0.0989 | GW10: 0 | GX10: 0.0989 | GY10: 0 | GZ10: 0 | HA10: 0 | HB10: 0 | HC10: protective | HD10: 0 | HE10: 0 | HF10: 0 | HG10: 0 | HH10: 0 | HI10: protective | HJ10: 0 | HK10: 0 | HL10: 0 | HM10: 0 | HN10: 0 | HO10: protective | HP10: 0 | HQ10: 0 | HR10: 0 | HS10: 0 | HT10: 0 | HU10: protective | HV10: 0 | HW10: 0 | HX10: 0 | HY10: 0 | HZ10: 0 | IA10: threat | IB10: 0 | IC10: 0 | ID10: 0 | IE10: 0 | IF10: 0 | IG10: threat | IH10: 0 | II10: 0 | IJ10: 0 | IK10: 0 | IL10: 0 | IM10: threat | IN10: 0 | IO10: 0 | IP10: 0 | IQ10: 0 | IR10: 0 | IS10: threat | IT10: 0 | IU10: 0 | IV10: 0 | IW10: 0 | IX10: 0 | IY10: 0 | IZ10: 0 | JA10: 0 | JD10: disciplined | JE10: coherent but cold; technically strong, morally vacant; narrow but rigorous; publication-ready but adversarially incomplete | JF10: Civic Ï‡P = 0.88 The numbers Civic organization membership: 60%+ of adults Church attendance: 40% weekly Voter participation: ~70% in major elections Volunteer rates: Immeasurable (not tracked because it was assumed) What it meant in practice You belonged to things. | JG10: Trust Ï‡T = 0.85 The numbers 75%+ reported trusting "most people" Handshake deals were legally and socially binding Contracts were short—often one page Neighbors left doors unlocked What it meant in practice If someone gave you their word, that meant something. | JH10: They've never experienced it. | JI10: Real problems existed. | JJ10: 0.4833 | JK10: 0 | JL10: fallback: NRCLex not installed | JM10: 0 | JN10: 0 | JO10: 0 | JP10: 0 | JQ10: 0 | JR10: 0 | JS10: 0 | JT10: 0 | JU10: 0 | JV10: 0 | JX10: fallback: PreTrainedTokenizerFast._batch_encode_plus() got an unexpected keyword argument 'local_files_only' | JY10: 0 | JZ10: 0 | KA10: 1 | KB10: 0 | KC10: 0 | KD10: 1 | KE10: 0 | KF10: 0 | KG10: 1 | KH10: 0 | KI10: 0 | KJ10: 1 | KK10: 0 | KL10: 0 | KM10: 1 | KN10: 0 | KO10: 0 | KP10: 1 | KQ10: 0 | KR10: 0 | KS10: 1 | KT10: 0 | KU10: 0 | KV10: 1 | KW10: 0 | KX10: 0 | KY10: 1 | KZ10: 0 | LA10: 0 | LB10: 0 | LC10: 0 | LD10: 0 | LE10: 0 | LF10: 0 | LG10: 0 | LH10: 0 | LI10: 0 | LJ10: 0 | LK10: 0 | LN10: love | LO10: self_control | LP10: fallback: textdescriptives not installed | LQ10: 0.4328 | LR10: 15.3437 | LS10: 10.8497 | LT10: 1257 | LU10: 544 | LV10: 89.7857 | LW10: 0.8754 | LX10: 0.5587 | LY10: 0.5587 | LZ10: 0.5587 | MA10: 0 | MB10: 685 | MC10: 1 | MD10: fallback: lexical proposition estimate | ME10: VERY HIGH (dense academic)
A11: P-b16210a6fece | B11: MDA-010-pre-modern-baseline.md | C11: BA-733478a8bf | D11: 20260530_220100 | E11: 2026.04.07-B | F11: C:\Users\lowes\Documents\Codex\2026-05-30\okay-let-find-the-open-ai\work\deploy_ready_extracted_md_20260530_220012\MDA-010-pre-modern-baseline.md | G11: 2026-05-30T22:02:01.419459 | H11: C:\Users\lowes\Documents\Codex\2026-05-30\okay-let-find-the-open-ai\outputs\deploy_ready_full_pipeline_20260530\paper_intelligence\snapshots\P-b16210a6fece_snapshot.json | I11: L1:ok,L10:ok,L13:skipped,L2:ok,L3:ok,L4:skipped,L5:ok,L6:ok,L7:ok,L8:ok,L9:ok,PA:ok | J11: 3453 | K11: 1294 | L11: 0.3747 | M11: 156 | N11: 3 | O11: 1 | P11: 22.1 | Q11: 52 | R11: 20.7 | S11: 7.1 | T11: 13.9 | U11: 2.7 | V11: 8.5 | W11: 26 | X11: 8.8 | Y11: 3 | Z11: 3 | AA11: 1 | AB11: CONCEPTUAL | AC11: TRUE | AD11: sentence-transformers not available | AE11: 0.397 | AF11: HIGH | AG11: 0.2577 | AH11: 0.033 | AI11: 0.7178 | AJ11: textstat not available | AK11: 4.9 | AL11: 9 | AM11: HIGH | AN11: 2 | AO11: 0.58 | AP11: 15 | AQ11: 4.34 | AR11: 7.5 | AS11: 0 | AT11: A — Evidence-Rich | AU11: 37.8 | AV11: 59 | AW11: HIGH | AX11: 15 | AY11: 4.34 | AZ11: 0 | BA11: 11 | BB11: 0 | BC11: 4 | BD11: 0 | BE11: 11 | BF11: 0 | BG11: 11 | BH11: 2 | BI11: 0.73 | BJ11: FALSE | BK11: FALSE | BL11: 3 | BM11: 3 | BN11: 2 | BO11: 1 | BP11: 0 | BQ11: 1 | BR11: 0 | BS11: 3453 | BT11: 1294 | BU11: 0.3747 | BV11: 3 | BW11: 1 | BX11: 1151 | BZ11: Key Statistics(0.0058) | Statistics Metric(0.0058) | Moral(0.0069) | rate(0.0089) | divorce rate(0.0094) | social(0.0103) | federal(0.0105) | Master HTMl(0.0132) | Easy Plain-language(0.0134) | Illiteracy Rate(0.0154) | Pre-Modern Baseline(0.0167) | Child Labor(0.0172) | CA11: and the | pre modern | modern baseline | key statistics | statistics metric | for the | CB11: pre modern baseline | key statistics metric | statistics metric source | the pre modern | CC11: The Pre-Modern Baseline | Moral Decline of America | CD11: 0 | CE11: 0 | CF11: 0 | CG11: 0 | CH11: 1 | CI11: complexity | CJ11: 5 | CK11: 1.45 | CL11: 2/7 | CM11: 1 | CN11: 0 | CO11: FALSE | CP11: FALSE | CQ11: TRUE | CR11: FALSE | CS11: FALSE | CT11: TRUE | CU11: FALSE | CV11: 0 | CW11: 0 | CX11: 0 | CY11: 3 | CZ11: 0.87 | DA11: 15 | DB11: 4.34 | DC11: 5 | DD11: 0 | DE11: 0 | DF11: 6 | DG11: 1.74 | DH11: 6 | DI11: 1.74 | DJ11: 1 | DK11: 1 | DL11: 3 | DM11: 4 | DN11: 0 | DO11: 209 | DP11: 2 | DQ11: 0.58 | DR11: Prohibition itself, achieved through central state power, paradoxically established a moral standard that was instantly national and highly centralized â€” and therefore ripe for mass, organized evasion in the 1920s. | DS11: A critical complexity in the South must be acknowledged: white Progressives viewed the disfranchisement of Black citizens and the codification of Jim Crow segregation as necessary reforms to ensure racial peace and clean up electoral corrup | DT11: The draft and industrial mobilization required immediate, unprecedented federal intervention in daily life. | DU11: 15 + 15 = 100 David Lowe • Theophysics Institute Previous Series Home Next Theophysics Home MDA-010 of 54 Related Work Core article, supporting evidence, and broader context Ring 1 â€” This Article The core argument You are here. | DV11: But the data underneath the facade tells a different story. | DW11: 1.43 | DX11: 0 | DY11: 2.5 | DZ11: 5 | EA11: 2 | EB11: 10.93 | EC11: D (Light) | ED11: D (Light) | EE11: 3.45 | EF11: WEAK | EG11: 0.09 | EH11: 0.75 | EI11: 0.115 | EJ11: KNOWLEDGE-DOMINANT | EK11: 1.16 | EL11: peace | EM11: peace:5, self_control:5, faithfulness:3, hope:3, gentleness:2 | EN11: 1.05 | EO11: M_mass_meaning | EP11: 3 | EQ11: 6 | ER11: 64.2 | ES11: B — Strong | ET11: 0.29 | EU11: 2.9 | EV11: 1.54 | EW11: 1.54 | EX11: 0.97 | EY11: 0.29 | EZ11: 0.39 | FA11: 0.39 | FB11: 1.54 | FC11: 0.68 | FD11: not run (use --openai flag) | FE11: 227 | FF11: Reader Mode Standard, Standard, David Lowe • Theophysics Institute, Key Statistics Metric 1900, Juvenile Delinquency | FG11: HTMl\K-Production-Ready\03-moral-decline\DEPLOY-READY\03-evidence-chronology\MDA-010-pre, The Pre-Modern Baseline, the Comstock Acts, Black, the Pure Food and Drug Act | FH11: Victorian, Progressive, Catholic, Jewish | FI11: ORG, CARDINAL, WORK_OF_ART, PERSON, PRODUCT, FAC, DATE, NORP, GPE, EVENT, LOC, LAW, MONEY, PERCENT, QUANTITY, TIME, ORDINAL | FJ11: --- source_html: "\\dlowenas\HPWorkstation\Desktop\Master HTMl\K-Production-Ready\03-moral-decline\DEPLOY-READY\03-evidence-chronology\MDA-010-pre-modern-baseline | FK11: html" deploy_relative: "03-evidence-chronology\MDA-010-pre-modern-baseline | FL11: html" title: "The Pre-Modern Baseline | Moral Decline of America" --- The Pre-Modern Baseline | Moral Decline of America ﻿ The Pre-Modern Baseline | Moral Decline of America Home Home Previous | Nex | FM11: 0 | FN11: 0.5773 | FO11: 0.775 | FP11: 0.6603 | FQ11: 0.6218 | FR11: 0.0064 | FS11: 0.0128 | FT11: 0 | FU11: 0 | FV11: 0.1679 | FW11: 0.0463 | FX11: 0.0123 | FY11: 0.2734 | FZ11: 0.0082 | GA11: 156 | GB11: 1 | GC11: 1 | GD11: 122 | GE11: 1 | GF11: 38 | GG11: 0 | GH11: 0 | GI11: 0 | GJ11: 1 | GK11: 0.1482 | GL11: 0 | GM11: 0.037 | GN11: 0 | GO11: 0 | GP11: 0.037 | GQ11: 0 | GR11: 0 | GS11: 0.037 | GT11: 0 | GU11: 0 | GV11: 0.0741 | GW11: 0 | GX11: 0 | GY11: 0 | GZ11: 0 | HA11: 0 | HB11: 0 | HC11: protective | HD11: 0 | HE11: 0 | HF11: 0 | HG11: 0 | HH11: 0 | HI11: protective | HJ11: 0 | HK11: 0 | HL11: 0 | HM11: 0 | HN11: 0 | HO11: protective | HP11: 0 | HQ11: 0 | HR11: 0 | HS11: 0 | HT11: 0 | HU11: protective | HV11: 0 | HW11: 0 | HX11: 0 | HY11: 0 | HZ11: 0 | IA11: threat | IB11: 0 | IC11: 0 | ID11: 0 | IE11: 0 | IF11: 0 | IG11: threat | IH11: 0 | II11: 0 | IJ11: 0 | IK11: 0 | IL11: 0 | IM11: threat | IN11: 0 | IO11: 0 | IP11: 0 | IQ11: 0 | IR11: 0 | IS11: threat | IT11: 0 | IU11: 0 | IV11: 0 | IW11: 0 | IX11: 0 | IY11: 0 | IZ11: 0 | JA11: 0 | JD11: mixed spiritual posture | JE11: coherent but cold; forceful and disciplined; precise but lifeless; technically strong, morally vacant; publication-ready but adversarially incomplete | JF11: 15 + 15 = 100 David Lowe • Theophysics Institute Previous Series Home Next Theophysics Home MDA-010 of 54 Related Work Core article, supporting evidence, and broader context Ring 1 â€” This Article The core argument You are here. | JG11: Decade Deep-Dive • 1900â€“1919 The Pre-Modern Baseline The Victorian End Game (1900â€“1919) When stability was forced by constraint, not consensus David Lowe • Theophysics Institute The two decades from 1900 to 1919 are the final structural expression of Victorian moral standards in America â€” the last clean readout before mass media, the automobile, and two World Wars rewrote the operating system. | JH11: Everything we measure later, we measure against this. | JI11: On paper, it looked like consensus. | JJ11: 0.5833 | JK11: 0 | JL11: fallback: NRCLex not installed | JM11: 0 | JN11: 0 | JO11: 0 | JP11: 0 | JQ11: 0 | JR11: 0 | JS11: 0 | JT11: 0 | JU11: 0 | JV11: 0 | JX11: fallback: PreTrainedTokenizerFast._batch_encode_plus() got an unexpected keyword argument 'local_files_only' | JY11: 0 | JZ11: 0 | KA11: 1 | KB11: 0 | KC11: 0 | KD11: 1 | KE11: 0 | KF11: 0 | KG11: 1 | KH11: 0 | KI11: 0 | KJ11: 1 | KK11: 0 | KL11: 0 | KM11: 1 | KN11: 0 | KO11: 0 | KP11: 1 | KQ11: 0 | KR11: 0 | KS11: 1 | KT11: 0 | KU11: 0 | KV11: 1 | KW11: 0 | KX11: 0 | KY11: 1 | KZ11: 0 | LA11: 0 | LB11: 0 | LC11: 0 | LD11: 0 | LE11: 0 | LF11: 0 | LG11: 0 | LH11: 0 | LI11: 0 | LJ11: 0 | LK11: 0 | LN11: love | LO11: self_control | LP11: fallback: textdescriptives not installed | LQ11: 0.3629 | LR11: 20.9715 | LS11: 14.8291 | LT11: 3340 | LU11: 1212 | LV11: 121.8935 | LW11: 0.8938 | LX11: 0.5803 | LY11: 0.5803 | LZ11: 0.5803 | MA11: 0 | MB11: 1933 | MC11: 1 | MD11: fallback: lexical proposition estimate | ME11: VERY HIGH (dense academic)
A12: P-5714a123d5b0 | B12: MDA-011-collective-security-1930.md | C12: BA-733478a8bf | D12: 20260530_220100 | E12: 2026.04.07-B | F12: C:\Users\lowes\Documents\Codex\2026-05-30\okay-let-find-the-open-ai\work\deploy_ready_extracted_md_20260530_220012\MDA-011-collective-security-1930.md | G12: 2026-05-30T22:02:04.314456 | H12: C:\Users\lowes\Documents\Codex\2026-05-30\okay-let-find-the-open-ai\outputs\deploy_ready_full_pipeline_20260530\paper_intelligence\snapshots\P-5714a123d5b0_snapshot.json | I12: L1:ok,L10:ok,L13:skipped,L2:ok,L3:ok,L4:skipped,L5:ok,L6:ok,L7:ok,L8:ok,L9:ok,PA:ok | J12: 1732 | K12: 723 | L12: 0.4174 | M12: 65 | N12: 3 | O12: 1 | P12: 26.6 | Q12: 21.7 | R12: 18.6 | S12: 6.8 | T12: 10.8 | U12: 2.2 | V12: 8.7 | W12: 4 | X12: 2.8 | Y12: 5 | Z12: 0 | AA12: 5 | AB12: MIXED | AC12: FALSE | AD12: sentence-transformers not available | AE12: 0.4249 | AF12: MODERATE | AG12: 0.2592 | AH12: 0.0526 | AI12: 0.7018 | AJ12: textstat not available | AK12: 6.03 | AL12: 11 | AM12: HIGH | AN12: 0 | AO12: 0 | AP12: 32 | AQ12: 18.48 | AR12: 32 | AS12: 0 | AT12: A — Evidence-Rich | AU12: 44.6 | AV12: 29 | AW12: HIGH | AX12: 26 | AY12: 15.01 | AZ12: 20 | BA12: 6 | BB12: 0 | BC12: 0 | BD12: 0 | BE12: 6 | BF12: 20 | BG12: 0.3 | BH12: 0 | BI12: 0 | BJ12: FALSE | BK12: FALSE | BL12: 3 | BM12: 3 | BN12: 2 | BO12: 1 | BP12: 0 | BQ12: 1 | BR12: 0 | BS12: 1732 | BT12: 723 | BU12: 0.4174 | BV12: 3 | BW12: 1 | BX12: 577.3 | BZ12: Moral Decline(0.0026) | Mode Standard(0.003) | Standard Current(0.003) | Reader Mode(0.0049) | Collective Security(0.0055) | Moral(0.006) | Academic Method(0.0083) | America Home(0.0085) | Social Security(0.0095) | Security(0.0098) | Master HTMl(0.0107) | Standard active(0.0112) | CA12: collective security | was the | for the | the moral | the new | new deal | CB12: the new deal | the most influential | development was the | the age collective | CC12: The Age of Collective Security | Moral Decline of America | CD12: 20 | CE12: 0 | CF12: 20 | CG12: 11.54 | CH12: 0 | CJ12: 2 | CK12: 1.15 | CL12: 3/7 | CM12: 1 | CN12: 0 | CO12: FALSE | CP12: FALSE | CQ12: TRUE | CR12: FALSE | CS12: TRUE | CT12: TRUE | CU12: FALSE | CV12: 0 | CW12: 0 | CX12: 0 | CY12: 0 | CZ12: 0 | DA12: 32 | DB12: 18.47 | DC12: 32 | DD12: 0 | DE12: 0 | DF12: 3 | DG12: 1.73 | DH12: 0 | DI12: 0 | DJ12: 3 | DK12: 0 | DL12: 0 | DM12: 11 | DN12: 0 | DO12: 120 | DP12: 1 | DQ12: 0.58 | DR12: The 1930s did not invent the welfare state. | DS12: Sympathy for "crime, wrongdoing, evil, or sin" was prohibited. | DT12: history, a majority of American youth completed secondary education. | DU12: 6) [19]EBSCO â€” Commercial Radio Broadcasting Begins [20]Congress.gov â€” A Brief Examination of Union Membership Data [26]Wyoming EAD â€” Historical Census of Housing: Homeownership Rates 1900 to 2020 [31]Wikipedia â€” Hays Code 15 + 15 = | DV12: of Chicago Press â€” Marriage and Divorce Rates in Wisconsin, 1920â€“35 [6]Our World in Data â€” Marriages and Divorces [7]ASPE / HHS â€” Trends in Family Structure [8]PBS â€” The First Measured Century: Data Disruption Timeline [9]Sociolog | DW12: 2.14 | DX12: 5 | DY12: 2 | DZ12: 5 | EA12: 0 | EB12: 14.14 | EC12: C (Developing) | ED12: C (Moderate) | EE12: 1.7 | EF12: WEAK | EG12: 0.29 | EH12: 1.21 | EI12: 0.238 | EJ12: KNOWLEDGE-DOMINANT | EK12: 1.04 | EL12: goodness | EM12: goodness:4, peace:2, hope:2, love:1, joy:0 | EN12: 0.81 | EO12: M_mass_meaning | EP12: 0 | EQ12: 2 | ER12: 93.5 | ES12: A — Publication Grade | ET12: 0 | EU12: 1.92 | EV12: 0.77 | EW12: 1.73 | EX12: 0.77 | EY12: 0 | EZ12: 0.58 | FA12: 0.58 | FB12: 1.15 | FC12: 0.58 | FD12: not run (use --openai flag) | FE12: 180 | FF12: Reader Mode Standard, Standard, David Lowe • Theophysics Institute, Syphilis prevalence1, Sympathy | FG12: HTMl\K-Production-Ready\03-moral-decline\DEPLOY-READY\03-evidence-chronology\MDA-011, Social Security, the Progressive Era's, the Repeal of Prohibition, HS | FH12: American, Americans, Progressive, National Labor Relations Act | FI12: ORG, CARDINAL, WORK_OF_ART, PERSON, PRODUCT, GPE, DATE, EVENT, ORDINAL, PERCENT, NORP, TIME, LAW, LOC | FJ12: --- source_html: "\\dlowenas\HPWorkstation\Desktop\Master HTMl\K-Production-Ready\03-moral-decline\DEPLOY-READY\03-evidence-chronology\MDA-011-collective-security-1930 | FK12: html" deploy_relative: "03-evidence-chronology\MDA-011-collective-security-1930 | FL12: html" title: "The Age of Collective Security | Moral Decline of America" --- The Age of Collective Security | Moral Decline of America ﻿ The Age of Collective Security | Moral Decline of America Hom | FM12: 0 | FN12: 0.6002 | FO12: 0.775 | FP12: 0.6736 | FQ12: 0.6923 | FR12: 0 | FS12: 0.0154 | FT12: 0 | FU12: 0 | FV12: 0.1754 | FW12: 0 | FX12: 0.0512 | FY12: 0.3012 | FZ12: 0 | GA12: 65 | GB12: 1 | GC12: 1 | GD12: 52 | GE12: 0 | GF12: 12 | GG12: 0 | GH12: 1 | GI12: 0 | GJ12: 0 | GK12: 0 | GL12: 0 | GM12: 0 | GN12: 0 | GO12: 0 | GP12: 0.3071 | GQ12: 0 | GR12: 0 | GS12: 0.1536 | GT12: 0 | GU12: 0 | GV12: 0 | GW12: 0 | GX12: 0 | GY12: 0 | GZ12: 0 | HA12: 0 | HB12: 0 | HC12: protective | HD12: 0 | HE12: 0 | HF12: 0 | HG12: 0 | HH12: 0 | HI12: protective | HJ12: 0 | HK12: 0 | HL12: 0 | HM12: 0 | HN12: 0 | HO12: protective | HP12: 0 | HQ12: 0 | HR12: 0 | HS12: 0 | HT12: 0 | HU12: protective | HV12: 0 | HW12: 0 | HX12: 0 | HY12: 0 | HZ12: 0 | IA12: threat | IB12: 0 | IC12: 0 | ID12: 0 | IE12: 0 | IF12: 0 | IG12: threat | IH12: 0 | II12: 0 | IJ12: 0 | IK12: 0 | IL12: 0 | IM12: threat | IN12: 0 | IO12: 0 | IP12: 0 | IQ12: 0 | IR12: 0 | IS12: threat | IT12: 0 | IU12: 0 | IV12: 0 | IW12: 0 | IX12: 0 | IY12: 0 | IZ12: 0 | JA12: 0 | JD12: disciplined; technically strong, spiritually ordered | JE12: coherent but cold; forceful and disciplined; precise but lifeless; technically strong, morally vacant; publication-ready but adversarially incomplete | JF12: 6) [19]EBSCO â€” Commercial Radio Broadcasting Begins [20]Congress.gov â€” A Brief Examination of Union Membership Data [26]Wyoming EAD â€” Historical Census of Housing: Homeownership Rates 1900 to 2020 [31]Wikipedia â€” Hays Code 15 + 15 = 100 David Lowe • Theophysics Institute Previous Series Home Next Theophysics Home MDA-011 of 54 Related Work Core article, supporting evidence, and broader context Ring 1 â€” This Article The core argument You are here. | JG12: Part 1 Â· Verified Statistical Data (1930â€“1940) The statistics of the 1930s primarily reveal the consequences of economic hardship, which both suppressed the preceding decade's cultural rebellion and simultaneously forced deep institutional changes. | JH12: This act was the formal, constitutional rejection of the core belief of the Progressive movement: that government could â€” or should â€” enforce personal moral virtue. | JI12: Married couples appeared in separate beds. | JJ12: 0.4167 | JK12: 0 | JL12: fallback: NRCLex not installed | JM12: 0 | JN12: 0 | JO12: 0 | JP12: 0 | JQ12: 0 | JR12: 0 | JS12: 0 | JT12: 0 | JU12: 0 | JV12: 0 | JX12: fallback: PreTrainedTokenizerFast._batch_encode_plus() got an unexpected keyword argument 'local_files_only' | JY12: 0 | JZ12: 0 | KA12: 1 | KB12: 0 | KC12: 0 | KD12: 1 | KE12: 0 | KF12: 0 | KG12: 1 | KH12: 0 | KI12: 0 | KJ12: 1 | KK12: 0 | KL12: 0 | KM12: 1 | KN12: 0 | KO12: 0 | KP12: 1 | KQ12: 0 | KR12: 0 | KS12: 1 | KT12: 0 | KU12: 0 | KV12: 1 | KW12: 0 | KX12: 0 | KY12: 1 | KZ12: 0 | LA12: 0 | LB12: 0 | LC12: 0 | LD12: 0 | LE12: 0 | LF12: 0 | LG12: 0 | LH12: 0 | LI12: 0 | LJ12: 0 | LK12: 0 | LN12: love | LO12: self_control | LP12: fallback: textdescriptives not installed | LQ12: 0.4195 | LR12: 16.8277 | LS12: 11.899 | LT12: 1609 | LU12: 675 | LV12: 92.4756 | LW12: 0.8704 | LX12: 0.5153 | LY12: 0.5153 | LZ12: 0.5153 | MA12: 0 | MB12: 824 | MC12: 1 | MD12: fallback: lexical proposition estimate | ME12: HIGH (academic)
A13: P-45de3640a23d | B13: MDA-012-william-1950.md | C13: BA-733478a8bf | D13: 20260530_220100 | E13: 2026.04.07-B | F13: C:\Users\lowes\Documents\Codex\2026-05-30\okay-let-find-the-open-ai\work\deploy_ready_extracted_md_20260530_220012\MDA-012-william-1950.md | G13: 2026-05-30T22:02:05.881000 | H13: C:\Users\lowes\Documents\Codex\2026-05-30\okay-let-find-the-open-ai\outputs\deploy_ready_full_pipeline_20260530\paper_intelligence\snapshots\P-45de3640a23d_snapshot.json | I13: L1:ok,L10:ok,L13:skipped,L2:ok,L3:ok,L4:skipped,L5:ok,L6:ok,L7:ok,L8:ok,L9:ok,PA:ok | J13: 3812 | K13: 1200 | L13: 0.3148 | M13: 324 | N13: 3 | O13: 1 | P13: 11.8 | Q13: 108 | R13: 15.3 | S13: 10.6 | T13: 4.9 | U13: 3.5 | V13: 7.5 | W13: 17 | X13: 3.3 | Y13: 20 | Z13: 4 | AA13: 5 | AB13: MIXED | AC13: FALSE | AD13: sentence-transformers not available | AE13: 0.4322 | AF13: MODERATE | AG13: 0.3316 | AH13: 0.0333 | AI13: 0.6461 | AJ13: textstat not available | AK13: 3.57 | AL13: 9 | AM13: MODERATE | AN13: 0 | AO13: 0 | AP13: 5 | AQ13: 1.31 | AR13: 5 | AS13: 0 | AT13: A — Evidence-Rich | AU13: 17 | AV13: 55 | AW13: MODERATE | AX13: 19 | AY13: 4.98 | AZ13: 0 | BA13: 16 | BB13: 2 | BC13: 1 | BD13: 0 | BE13: 18 | BF13: 0 | BG13: 18 | BH13: 0 | BI13: 0.02 | BJ13: FALSE | BK13: FALSE | BL13: 3 | BM13: 3 | BN13: 2 | BO13: 1 | BP13: 0 | BQ13: 1 | BR13: 0 | BS13: 3812 | BT13: 1200 | BU13: 0.3148 | BV13: 3 | BW13: 1 | BX13: 1270.7 | BZ13: Bill(0.0036) | Moral Decline(0.0036) | Reader Mode(0.0051) | Academic Method(0.0088) | Decline(0.0089) | Mary(0.0097) | Master HTMl(0.0123) | Comfort Replaced(0.0123) | Replaced Necessity(0.0125) | Easy Plain-language(0.013) | Mary Hendricks(0.0149) | Henry(0.0156) | CA13: doesn know | the world | the first | for the | his father | first time | CB13: for the first | the first time | comfort replaced necessity | doesn know the | CC13: When Comfort Replaced Necessity | Moral Decline of America | CD13: 0 | CE13: 0 | CF13: 0 | CG13: 0 | CH13: 0 | CJ13: 1 | CK13: 0.26 | CL13: 2/7 | CM13: 1 | CN13: 0 | CO13: FALSE | CP13: FALSE | CQ13: TRUE | CR13: TRUE | CS13: FALSE | CT13: FALSE | CU13: FALSE | CV13: 0 | CW13: 0 | CX13: 0 | CY13: 0 | CZ13: 0 | DA13: 5 | DB13: 1.31 | DC13: 5 | DD13: 0 | DE13: 0 | DF13: 6 | DG13: 1.57 | DH13: 16 | DI13: 4.2 | DJ13: 0.38 | DK13: 1 | DL13: 2 | DM13: 17 | DN13: 1 | DO13: 91 | DP13: 2 | DQ13: 0.52 | DR13: He doesn't know he's living in the peak. | DS13: A comedian, a singer, a trained dog act. | DT13: Have a nice life in Ohio." She hangs up. | DU13: Ring 2 — Supporting Evidence Deeper dives and formal treatments No connections mapped yet. | DV13: Previous Series Home Next Theophysics Home MDA-012 of 54 Related Work Core article, supporting evidence, and broader context Ring 1 — This Article The core argument You are here. | DW13: 1.43 | DX13: 0 | DY13: 2 | DZ13: 5 | EA13: 1.5 | EB13: 9.93 | EC13: D (Light) | ED13: F (Needs Citations) | EE13: 0.93 | EF13: WEAK | EG13: 0.16 | EH13: 0.34 | EI13: 0.462 | EJ13: KNOWLEDGE-DOMINANT | EK13: 1.84 | EL13: goodness | EM13: goodness:13, peace:6, love:4, patience:3, gentleness:3 | EN13: 1 | EO13: T_time_eternity | EP13: 0 | EQ13: 0 | ER13: 15.7 | ES13: F — Needs Work | ET13: 1.22 | EU13: 0.96 | EV13: 1.4 | EW13: 1.49 | EX13: 2.27 | EY13: 0.17 | EZ13: 0.26 | FA13: 0.09 | FB13: 0.61 | FC13: 1.49 | FD13: not run (use --openai flag) | FE13: 321 | FF13: William Reader Mode Standard, Standard, Milton Berle, Ed Sullivan, William Lowe | FG13: HTMl\K-Production-Ready\03-moral-decline\DEPLOY-READY\01-story-thread\MDA-012-, Comfort Replaced Necessity, GI, The Federal Housing Administration, Park Forest | FH13: American, Philco | FI13: ORG, CARDINAL, PERSON, WORK_OF_ART, PRODUCT, DATE, GPE, PERCENT, NORP, ORDINAL, TIME, QUANTITY, MONEY, EVENT | FJ13: --- source_html: "\\dlowenas\HPWorkstation\Desktop\Master HTMl\K-Production-Ready\03-moral-decline\DEPLOY-READY\01-story-thread\MDA-012-william-1950 | FK13: html" title: "When Comfort Replaced Necessity | Moral Decline of America" --- When Comfort Replaced Necessity | Moral Decline of America ﻿ When Comfort Replaced Necessity | Moral Decline of America | FL13: Proof Pressure Layer Vetted Claims for MDA-012-william-1950 No promoted claim No claim from this article survived the deterministic Axiom + 7Q gate strongly enough for the proof layer yet | FM13: 0 | FN13: 0.5329 | FO13: 0.775 | FP13: 0.6346 | FQ13: 0.5549 | FR13: 0 | FS13: 0.0183 | FT13: 2 | FU13: 0.0088 | FV13: 0.1384 | FW13: 0.042 | FX13: 0.0336 | FY13: 0.326 | FZ13: 0.0037 | GA13: 328 | GB13: 1 | GC13: 1 | GD13: 154 | GE13: 0 | GF13: 46 | GG13: 1 | GH13: 3 | GI13: 2 | GJ13: 0 | GK13: 0.1008 | GL13: 0 | GM13: 0.0672 | GN13: 0.0336 | GO13: 0 | GP13: 0.4369 | GQ13: 0.0336 | GR13: 0 | GS13: 0.0336 | GT13: 0 | GU13: 0 | GV13: 0.0336 | GW13: 0 | GX13: 0 | GY13: 0 | GZ13: 0 | HA13: 0 | HB13: 0 | HC13: protective | HD13: 0 | HE13: 0 | HF13: 0 | HG13: 0 | HH13: 0 | HI13: protective | HJ13: 0 | HK13: 0 | HL13: 0 | HM13: 0 | HN13: 0 | HO13: protective | HP13: 0 | HQ13: 0 | HR13: 0 | HS13: 0 | HT13: 0 | HU13: protective | HV13: 0 | HW13: 0 | HX13: 0 | HY13: 0 | HZ13: 0 | IA13: threat | IB13: 0 | IC13: 0 | ID13: 0 | IE13: 0 | IF13: 0 | IG13: threat | IH13: 0 | II13: 0 | IJ13: 0 | IK13: 0 | IL13: 0 | IM13: threat | IN13: 0 | IO13: 0 | IP13: 0 | IQ13: 0 | IR13: 0 | IS13: threat | IT13: 0 | IU13: 0 | IV13: 0 | IW13: 0 | IX13: 0 | IY13: 0 | IZ13: 0 | JA13: 0 | JD13: technically strong, spiritually ordered | JE13: coherent but cold; forceful and disciplined; precise but lifeless; technically strong, morally vacant; narrow but rigorous | JF13: Ohio, 1950 William Lowe - Bill, everyone calls him Bill - is eighteen years old, and for the first time in three generations, a Lowe boy is not thinking primarily about the farm. | JG13: Communication is faster - long distance phone calls are common now, you can talk to someone across the country in real time. | JH13: He could have chosen that. | JI13: She looks at him like he might be worth looking at. | JJ13: 0.3333 | JK13: 0 | JL13: fallback: NRCLex not installed | JM13: 0 | JN13: 0 | JO13: 0 | JP13: 0 | JQ13: 0 | JR13: 0 | JS13: 0 | JT13: 0 | JU13: 0 | JV13: 0 | JX13: fallback: PreTrainedTokenizerFast._batch_encode_plus() got an unexpected keyword argument 'local_files_only' | JY13: 0 | JZ13: 0 | KA13: 1 | KB13: 0 | KC13: 0 | KD13: 1 | KE13: 0 | KF13: 0 | KG13: 1 | KH13: 0 | KI13: 0 | KJ13: 1 | KK13: 0 | KL13: 0 | KM13: 1 | KN13: 0 | KO13: 0 | KP13: 1 | KQ13: 0 | KR13: 0 | KS13: 1 | KT13: 0 | KU13: 0 | KV13: 1 | KW13: 0 | KX13: 0 | KY13: 1 | KZ13: 0 | LA13: 0 | LB13: 0 | LC13: 0 | LD13: 0 | LE13: 0 | LF13: 0 | LG13: 0 | LH13: 0 | LI13: 0 | LJ13: 0 | LK13: 0 | LN13: love | LO13: self_control | LP13: fallback: textdescriptives not installed | LQ13: 0.2952 | LR13: 18.2236 | LS13: 12.886 | LT13: 3811 | LU13: 1125 | LV13: 88.6867 | LW13: 0.8745 | LX13: 0.4459 | LY13: 0.4459 | LZ13: 0.4459 | MA13: 0 | MB13: 1640 | MC13: 1 | MD13: fallback: lexical proposition estimate | ME13: MODERATE (accessible)
A14: P-b1721534cce8 | B14: MDA-013-peak-coherence-1940.md | C14: BA-733478a8bf | D14: 20260530_220100 | E14: 2026.04.07-B | F14: C:\Users\lowes\Documents\Codex\2026-05-30\okay-let-find-the-open-ai\work\deploy_ready_extracted_md_20260530_220012\MDA-013-peak-coherence-1940.md | G14: 2026-05-30T22:02:08.729023 | H14: C:\Users\lowes\Documents\Codex\2026-05-30\okay-let-find-the-open-ai\outputs\deploy_ready_full_pipeline_20260530\paper_intelligence\snapshots\P-b1721534cce8_snapshot.json | I14: L1:ok,L10:ok,L13:skipped,L2:ok,L3:ok,L4:skipped,L5:ok,L6:ok,L7:ok,L8:ok,L9:ok,PA:ok | J14: 2144 | K14: 890 | L14: 0.4151 | M14: 129 | N14: 3 | O14: 1 | P14: 16.6 | Q14: 43 | R14: 21.3 | S14: 7.7 | T14: 10.5 | U14: 2.9 | V14: 8.2 | W14: 11 | X14: 5.5 | Y14: 14 | Z14: 1 | AA14: 14 | AB14: CONCEPTUAL | AC14: FALSE | AD14: sentence-transformers not available | AE14: 0.431 | AF14: MODERATE | AG14: 0.2799 | AH14: 0.0322 | AI14: 0.6969 | AJ14: textstat not available | AK14: 5.2 | AL14: 11 | AM14: HIGH | AN14: 2 | AO14: 0.93 | AP14: 12 | AQ14: 5.6 | AR14: 6 | AS14: 0 | AT14: A — Evidence-Rich | AU14: 22.5 | AV14: 29 | AW14: MODERATE | AX14: 18 | AY14: 8.4 | AZ14: 0 | BA14: 18 | BB14: 0 | BC14: 0 | BD14: 0 | BE14: 18 | BF14: 0 | BG14: 18 | BH14: 0 | BI14: 0 | BJ14: FALSE | BK14: FALSE | BL14: 3 | BM14: 3 | BN14: 2 | BO14: 1 | BP14: 0 | BQ14: 1 | BR14: 0 | BS14: 2144 | BT14: 890 | BU14: 0.4151 | BV14: 3 | BW14: 1 | BX14: 714.7 | BZ14: Mode Standard(0.0029) | Standard Current(0.0029) | Moral Decline(0.0031) | Reader Mode(0.0048) | Master HTMl(0.0103) | Standard active(0.0108) | Academic Method(0.0112) | Easy Plain-language(0.0118) | Moral(0.0126) | America Home(0.0133) | pressure Standard(0.0134) | Decline(0.0135) | CA14: union density | post war | peak coherence | and the | the decade | hays code | CB14: the crucible consensus | the hays code | the single income | mda peak coherence | CC14: The Crucible of Consensus | Moral Decline of America | CD14: 0 | CE14: 0 | CF14: 0 | CG14: 0 | CH14: 1 | CI14: entropy | CJ14: 4 | CK14: 1.86 | CL14: 3/7 | CM14: 1 | CN14: 0 | CO14: FALSE | CP14: FALSE | CQ14: TRUE | CR14: TRUE | CS14: TRUE | CT14: FALSE | CU14: FALSE | CV14: 0 | CW14: 0 | CX14: 0 | CY14: 1 | CZ14: 0.47 | DA14: 14 | DB14: 6.53 | DC14: 14 | DD14: 0 | DE14: 0 | DF14: 8 | DG14: 3.73 | DH14: 10 | DI14: 4.66 | DJ14: 0.8 | DK14: 1 | DL14: 0 | DM14: 0 | DN14: 0 | DO14: 176 | DP14: 2 | DQ14: 0.93 | DR14: That comfort gave the next generation the economic freedom to break free from family and institutional controls â€” rendering the single-income model unnecessary, and therefore negotiable. | DS14: Marshall 1880â€“1959 · Chief of Staff → Secretary of State Marshall embodied the subordination of the individual to collective purpose. | DT14: 15 + 15 = 100 David Lowe • Theophysics Institute Previous Series Home Next Theophysics Home MDA-013 of 54 Related Work Core article, supporting evidence, and broader context Ring 1 â€” This Article The core argument You are here. | DU14: 15 + 15 = 100 David Lowe • Theophysics Institute Previous Series Home Next Theophysics Home MDA-013 of 54 Related Work Core article, supporting evidence, and broader context Ring 1 â€” This Article The core argument You are here. | DV14: When Kinsey’s data dropped, it didn’t create the deviance. | DW14: 2.14 | DX14: 0 | DY14: 2.17 | DZ14: 5 | EA14: 0.5 | EB14: 9.81 | EC14: D (Light) | ED14: D (Light) | EE14: 4.59 | EF14: MODERATE | EG14: 0.23 | EH14: 1.59 | EI14: 0.147 | EJ14: KNOWLEDGE-DOMINANT | EK14: 0.93 | EL14: peace | EM14: peace:2, gentleness:2, humility:2, love:1, goodness:1 | EN14: 1.44 | EO14: C_christ_coherence | EP14: 0 | EQ14: 1 | ER14: 46 | ES14: C — Moderate | ET14: 0.31 | EU14: 2.8 | EV14: 1.55 | EW14: 1.86 | EX14: 1.86 | EY14: 0.47 | EZ14: 0.31 | FA14: 0.62 | FB14: 0.93 | FC14: 3.73 | FD14: not run (use --openai flag) | FE14: 209 | FF14: Reader Mode Standard, Standard, David Lowe • Theophysics Institute, Kinsey, Alfred Kinsey | FG14: HTMl\K-Production-Ready\03-moral-decline\DEPLOY-READY\03-evidence-chronology\MDA-013, Theophysics, Men)24.3â€”22.7U.S. Census Median, Women)21.5â€”20.3U.S. Census Out-of-wedlock, Media | FH14: American, Americans, the Marshall Plan | FI14: ORG, CARDINAL, WORK_OF_ART, PERSON, PRODUCT, DATE, NORP, ORDINAL, PERCENT, EVENT, GPE, LAW, LOC | FJ14: --- source_html: "\\dlowenas\HPWorkstation\Desktop\Master HTMl\K-Production-Ready\03-moral-decline\DEPLOY-READY\03-evidence-chronology\MDA-013-peak-coherence-1940 | FK14: html" deploy_relative: "03-evidence-chronology\MDA-013-peak-coherence-1940 | FL14: html" title: "The Crucible of Consensus | Moral Decline of America" --- The Crucible of Consensus | Moral Decline of America ﻿ The Crucible of Consensus | Moral Decline of America Home Home Previous | FM14: 0 | FN14: 0.5579 | FO14: 0.775 | FP14: 0.6491 | FQ14: 0.6047 | FR14: 0 | FS14: 0.0465 | FT14: 0 | FU14: 0.0134 | FV14: 0.1473 | FW14: 0 | FX14: 0.0203 | FY14: 0.2635 | FZ14: 0 | GA14: 129 | GB14: 1 | GC14: 1 | GD14: 80 | GE14: 0 | GF14: 20 | GG14: 2 | GH14: 2 | GI14: 0 | GJ14: 0 | GK14: 0 | GL14: 0 | GM14: 0 | GN14: 0 | GO14: 0 | GP14: 0.0609 | GQ14: 0 | GR14: 0 | GS14: 0.0609 | GT14: 0 | GU14: 0 | GV14: 0 | GW14: 0 | GX14: 0 | GY14: 0 | GZ14: 0 | HA14: 0 | HB14: 0 | HC14: protective | HD14: 0 | HE14: 0 | HF14: 0 | HG14: 0 | HH14: 0 | HI14: protective | HJ14: 0 | HK14: 0 | HL14: 0 | HM14: 0 | HN14: 0 | HO14: protective | HP14: 0 | HQ14: 0 | HR14: 0 | HS14: 0 | HT14: 0 | HU14: protective | HV14: 0 | HW14: 0 | HX14: 0 | HY14: 0 | HZ14: 0 | IA14: threat | IB14: 0 | IC14: 0 | ID14: 0 | IE14: 0 | IF14: 0 | IG14: threat | IH14: 0 | II14: 0 | IJ14: 0 | IK14: 0 | IL14: 0 | IM14: threat | IN14: 0 | IO14: 0 | IP14: 0 | IQ14: 0 | IR14: 0 | IS14: threat | IT14: 0 | IU14: 0 | IV14: 0 | IW14: 0 | IX14: 0 | IY14: 0 | IZ14: 0 | JA14: 0 | JD14: mixed spiritual posture | JE14: coherent but cold; forceful and disciplined; precise but lifeless; technically strong, morally vacant; narrow but rigorous | JF14: That single institutional change is one of the six simultaneous structural breaks in the 1968â€“1973 decoupling that the framework predicts. | JG14: But there is a number you have to look at squarely if you are going to be honest about this decade. | JH14: The result was what cultural analysts call a binary moral universe: wrongdoing on screen was never sympathetically portrayed, and consequence was always visible. | JI14: That number never recovered. | JJ14: 0.6833 | JK14: 0 | JL14: fallback: NRCLex not installed | JM14: 0 | JN14: 0 | JO14: 0 | JP14: 0 | JQ14: 0 | JR14: 0 | JS14: 0 | JT14: 0 | JU14: 0 | JV14: 0 | JX14: fallback: PreTrainedTokenizerFast._batch_encode_plus() got an unexpected keyword argument 'local_files_only' | JY14: 0 | JZ14: 0 | KA14: 1 | KB14: 0 | KC14: 0 | KD14: 1 | KE14: 0 | KF14: 0 | KG14: 1 | KH14: 0 | KI14: 0 | KJ14: 1 | KK14: 0 | KL14: 0 | KM14: 1 | KN14: 0 | KO14: 0 | KP14: 1 | KQ14: 0 | KR14: 0 | KS14: 1 | KT14: 0 | KU14: 0 | KV14: 1 | KW14: 0 | KX14: 0 | KY14: 1 | KZ14: 0 | LA14: 0 | LB14: 0 | LC14: 0 | LD14: 0 | LE14: 0 | LF14: 0 | LG14: 0 | LH14: 0 | LI14: 0 | LJ14: 0 | LK14: 0 | LN14: love | LO14: self_control | LP14: fallback: textdescriptives not installed | LQ14: 0.3909 | LR14: 17.8486 | LS14: 12.6209 | LT14: 2085 | LU14: 815 | LV14: 115.8333 | LW14: 0.8802 | LX14: 0.506 | LY14: 0.506 | LZ14: 0.506 | MA14: 0 | MB14: 1055 | MC14: 1 | MD14: fallback: lexical proposition estimate | ME14: HIGH (academic)
A15: P-10c538ca5abc | B15: MDA-014-fissure-1950.md | C15: BA-733478a8bf | D15: 20260530_220100 | E15: 2026.04.07-B | F15: C:\Users\lowes\Documents\Codex\2026-05-30\okay-let-find-the-open-ai\work\deploy_ready_extracted_md_20260530_220012\MDA-014-fissure-1950.md | G15: 2026-05-30T22:02:10.443118 | H15: C:\Users\lowes\Documents\Codex\2026-05-30\okay-let-find-the-open-ai\outputs\deploy_ready_full_pipeline_20260530\paper_intelligence\snapshots\P-10c538ca5abc_snapshot.json | I15: L1:ok,L10:ok,L13:skipped,L2:ok,L3:ok,L4:skipped,L5:ok,L6:ok,L7:ok,L8:ok,L9:ok,PA:ok | J15: 1887 | K15: 704 | L15: 0.3731 | M15: 102 | N15: 3 | O15: 1 | P15: 18.5 | Q15: 34 | R15: 20.3 | S15: 7.4 | T15: 9.2 | U15: 3 | V15: 9.9 | W15: 8 | X15: 4.9 | Y15: 9 | Z15: 0 | AA15: 9 | AB15: CONCEPTUAL | AC15: FALSE | AD15: sentence-transformers not available | AE15: 0.4343 | AF15: MODERATE | AG15: 0.3164 | AH15: 0.0302 | AI15: 0.663 | AJ15: textstat not available | AK15: 4.3 | AL15: 11 | AM15: HIGH | AN15: 0 | AO15: 0 | AP15: 10 | AQ15: 5.3 | AR15: 10 | AS15: 0 | AT15: A — Evidence-Rich | AU15: 24.5 | AV15: 25 | AW15: MODERATE | AX15: 8 | AY15: 4.24 | AZ15: 0 | BA15: 8 | BB15: 0 | BC15: 0 | BD15: 0 | BE15: 8 | BF15: 0 | BG15: 8 | BH15: 1 | BI15: 0 | BJ15: FALSE | BK15: FALSE | BL15: 3 | BM15: 3 | BN15: 2 | BO15: 1 | BP15: 0 | BQ15: 1 | BR15: 0 | BS15: 1887 | BT15: 704 | BU15: 0.3731 | BV15: 3 | BW15: 1 | BX15: 629 | BZ15: Moral Decline(0.0026) | Reader Mode(0.0049) | Moral(0.0075) | Academic Method(0.0083) | Master HTMl(0.0106) | Easy Plain-language(0.012) | Decline(0.0137) | Moral Authority(0.0183) | Plain-language bridge(0.0185) | Current article(0.0191) | Home Reader(0.0193) | American(0.021) | CA15: the equation | and the | the same | was the | the fissure | fissure conformity | CB15: the fissure conformity | fissure conformity moral | conformity moral decline | moral decline america | CC15: The Fissure in Conformity | Moral Decline of America | CD15: 0 | CE15: 0 | CF15: 0 | CG15: 0 | CH15: 1 | CI15: epistemology | CJ15: 4 | CK15: 2.12 | CL15: 2/7 | CM15: 1 | CN15: 0 | CO15: FALSE | CP15: FALSE | CQ15: TRUE | CR15: TRUE | CS15: FALSE | CT15: FALSE | CU15: FALSE | CV15: 0 | CW15: 0 | CX15: 0 | CY15: 0 | CZ15: 0 | DA15: 10 | DB15: 5.3 | DC15: 10 | DD15: 0 | DE15: 0 | DF15: 2 | DG15: 1.06 | DH15: 7 | DI15: 3.71 | DJ15: 0.29 | DK15: 0 | DL15: 0 | DM15: 1 | DN15: 0 | DO15: 98 | DP15: 6 | DQ15: 3.18 | DR15: Household Debt-to-Income Ratio 0.31 → 0.55 1950 to 1960 — a 77% increase in a single decade Read this as a moral statistic, not a financial one. | DS15: 15 + 15 = 100 David Lowe • Theophysics Institute Previous Series Home Next Theophysics Home MDA-014 of 54 Related Work Core article, supporting evidence, and broader context Ring 1 — This Article The core argument You are here. | DT15: Television Penetration 9% → 90% 1950 to 1960 — the fastest mass-media saturation in American history The content in 1958 was conformist — Leave It to Beaver, Father Knows Best, the idealized suburban nuclear family broadcast as universal no | DU15: 15 + 15 = 100 David Lowe • Theophysics Institute Previous Series Home Next Theophysics Home MDA-014 of 54 Related Work Core article, supporting evidence, and broader context Ring 1 — This Article The core argument You are here. | DV15: Empirical data became a higher court than tradition. | DW15: 1.43 | DX15: 0 | DY15: 2 | DZ15: 5 | EA15: 0 | EB15: 8.43 | EC15: D (Light) | ED15: D (Light) | EE15: 2.91 | EF15: WEAK | EG15: 0 | EH15: 1.48 | EI15: 0 | EJ15: KNOWLEDGE-DOMINANT | EK15: 0.95 | EL15: peace | EM15: peace:4, gentleness:3, kindness:1, goodness:1, love:0 | EN15: 1.25 | EO15: M_mass_meaning | EP15: 0 | EQ15: 1 | ER15: 37.5 | ES15: D — Developing | ET15: 0.88 | EU15: 2.82 | EV15: 1.41 | EW15: 1.77 | EX15: 1.24 | EY15: 0 | EZ15: 0.71 | FA15: 0.88 | FB15: 1.24 | FC15: 1.59 | FD15: not run (use --openai flag) | FE15: 181 | FF15: Reader Mode Standard, Standard, David Lowe • Theophysics Institute, Teen Birth Rate, Eisenhower | FG15: HTMl\K-Production-Ready\03-moral-decline\DEPLOY-READY\03-evidence-chronology\MDA-014-fissure-1950.html, Peak Consensus, Hidden Cracks, Trust in Government, Median Marriage Age | FH15: American, Soviet, Americans, the Hays Production Code | FI15: ORG, CARDINAL, WORK_OF_ART, PERSON, PRODUCT, DATE, EVENT, GPE, PERCENT, ORDINAL, NORP, TIME, LAW | FJ15: --- source_html: "\\dlowenas\HPWorkstation\Desktop\Master HTMl\K-Production-Ready\03-moral-decline\DEPLOY-READY\03-evidence-chronology\MDA-014-fissure-1950 | FK15: html" deploy_relative: "03-evidence-chronology\MDA-014-fissure-1950 | FL15: html" title: "The Fissure in Conformity | Moral Decline of America" --- The Fissure in Conformity | Moral Decline of America ﻿ The Fissure in Conformity | Moral Decline of America Home Home Previous | FM15: 0 | FN15: 0.5739 | FO15: 0.775 | FP15: 0.6583 | FQ15: 0.6019 | FR15: 0 | FS15: 0.0194 | FT15: 1 | FU15: 0.007 | FV15: 0.1573 | FW15: 0.087 | FX15: 0 | FY15: 0.2887 | FZ15: 0 | GA15: 103 | GB15: 1 | GC15: 1 | GD15: 69 | GE15: 1 | GF15: 18 | GG15: 0 | GH15: 1 | GI15: 1 | GJ15: 0 | GK15: 0 | GL15: 0 | GM15: 0.2784 | GN15: 0 | GO15: 0.0696 | GP15: 0 | GQ15: 0 | GR15: 0 | GS15: 0 | GT15: 0 | GU15: 0 | GV15: 0 | GW15: 0 | GX15: 0 | GY15: 0 | GZ15: 0 | HA15: 0 | HB15: 0 | HC15: protective | HD15: 0 | HE15: 0 | HF15: 0 | HG15: 0 | HH15: 0 | HI15: protective | HJ15: 0 | HK15: 0 | HL15: 0 | HM15: 0 | HN15: 0 | HO15: protective | HP15: 0 | HQ15: 0 | HR15: 0 | HS15: 0 | HT15: 0 | HU15: protective | HV15: 0 | HW15: 0 | HX15: 0 | HY15: 0 | HZ15: 0 | IA15: threat | IB15: 0 | IC15: 0 | ID15: 0 | IE15: 0 | IF15: 0 | IG15: threat | IH15: 0 | II15: 0 | IJ15: 0 | IK15: 0 | IL15: 0 | IM15: threat | IN15: 0 | IO15: 0 | IP15: 0 | IQ15: 0 | IR15: 0 | IS15: threat | IT15: 0 | IU15: 0 | IV15: 0 | IW15: 0 | IX15: 0 | IY15: 0 | IZ15: 0 | JA15: 0 | JD15: mixed spiritual posture | JE15: coherent but cold; forceful and disciplined; narrow but rigorous; publication-ready but adversarially incomplete | JF15: The Veneer (1950–1960) Trust in Government (1958)73% Weekly Church Attendance49% Children in Two-Parent Homes87.5% Median Marriage Age (Female)20.3 Home Ownership (1960)62.1% The Underneath Household Debt-to-Income0.31 → 0.55 TV Ownership9% → 90% Union Density (1953 → 1960)33.2% → 30.7% Teen Birth Rate (per 1,000)89.1 Enovid (the Pill) Released1960 The veneer panel is the picture the decade told about itself. | JG15: That matters, because in the equation, a system with one negentropic source is structurally more fragile than a system with many. | JH15: There has never been another technology that achieved that kind of saturation that quickly. | JI15: Debt was no longer something you paid off so you could live free. | JJ15: 0.3833 | JK15: 0 | JL15: fallback: NRCLex not installed | JM15: 0 | JN15: 0 | JO15: 0 | JP15: 0 | JQ15: 0 | JR15: 0 | JS15: 0 | JT15: 0 | JU15: 0 | JV15: 0 | JX15: fallback: PreTrainedTokenizerFast._batch_encode_plus() got an unexpected keyword argument 'local_files_only' | JY15: 0 | JZ15: 0 | KA15: 1 | KB15: 0 | KC15: 0 | KD15: 1 | KE15: 0 | KF15: 0 | KG15: 1 | KH15: 0 | KI15: 0 | KJ15: 1 | KK15: 0 | KL15: 0 | KM15: 1 | KN15: 0 | KO15: 0 | KP15: 1 | KQ15: 0 | KR15: 0 | KS15: 1 | KT15: 0 | KU15: 0 | KV15: 1 | KW15: 0 | KX15: 0 | KY15: 1 | KZ15: 0 | LA15: 0 | LB15: 0 | LC15: 0 | LD15: 0 | LE15: 0 | LF15: 0 | LG15: 0 | LH15: 0 | LI15: 0 | LJ15: 0 | LK15: 0 | LN15: love | LO15: self_control | LP15: fallback: textdescriptives not installed | LQ15: 0.3805 | LR15: 16.0261 | LS15: 11.3321 | LT15: 1774 | LU15: 675 | LV15: 88.7034 | LW15: 0.8673 | LX15: 0.467 | LY15: 0.467 | LZ15: 0.467 | MA15: 0 | MB15: 827 | MC15: 1 | MD15: fallback: lexical proposition estimate | ME15: HIGH (academic)
A16: P-ac8790ade693 | B16: MDA-015-long-decline.md | C16: BA-733478a8bf | D16: 20260530_220100 | E16: 2026.04.07-B | F16: C:\Users\lowes\Documents\Codex\2026-05-30\okay-let-find-the-open-ai\work\deploy_ready_extracted_md_20260530_220012\MDA-015-long-decline.md | G16: 2026-05-30T22:02:11.853413 | H16: C:\Users\lowes\Documents\Codex\2026-05-30\okay-let-find-the-open-ai\outputs\deploy_ready_full_pipeline_20260530\paper_intelligence\snapshots\P-ac8790ade693_snapshot.json | I16: L1:ok,L10:ok,L13:skipped,L2:ok,L3:ok,L4:skipped,L5:ok,L6:ok,L7:ok,L8:ok,L9:ok,PA:ok | J16: 983 | K16: 523 | L16: 0.532 | M16: 74 | N16: 3 | O16: 1 | P16: 13.3 | Q16: 24.7 | R16: 21.7 | S16: 10 | T16: 8.5 | U16: 3.7 | V16: 4.8 | W16: 3 | X16: 2.4 | Y16: 6 | Z16: 0 | AA16: 6 | AB16: CONCEPTUAL | AC16: FALSE | AD16: sentence-transformers not available | AE16: 0.4815 | AF16: MODERATE | AG16: 0.176 | AH16: 0.0316 | AI16: 0.798 | AJ16: textstat not available | AK16: 3.93 | AL16: 10 | AM16: MODERATE | AN16: 0 | AO16: 0 | AP16: 5 | AQ16: 5.09 | AR16: 5 | AS16: 0 | AT16: A — Evidence-Rich | AU16: 16.2 | AV16: 12 | AW16: MODERATE | AX16: 9 | AY16: 9.16 | AZ16: 0 | BA16: 9 | BB16: 0 | BC16: 0 | BD16: 0 | BE16: 9 | BF16: 0 | BG16: 9 | BH16: 0 | BI16: 0 | BJ16: FALSE | BK16: FALSE | BL16: 3 | BM16: 3 | BN16: 2 | BO16: 1 | BP16: 0 | BQ16: 1 | BR16: 0 | BS16: 983 | BT16: 523 | BU16: 0.532 | BV16: 3 | BW16: 1 | BX16: 327.7 | BZ16: Reader Mode(0.0047) | Academic Method(0.0079) | Master HTMl(0.0086) | Long Decline(0.0093) | Easy Plain-language(0.0114) | Moral Decline(0.0134) | Plain-language bridge(0.0156) | Decline(0.0196) | Home Reader(0.0225) | Mode Standard(0.0254) | Proof pressure(0.0269) | Coherence(0.0288) | CA16: long decline | moral decline | the long | decline america | mda long | decline moral | CB16: the long decline | moral decline america | mda long decline | long decline moral | CC16: The Long Decline | Moral Decline of America | CD16: 0 | CE16: 0 | CF16: 0 | CG16: 0 | CH16: 0 | CJ16: 1 | CK16: 1.02 | CL16: 1/7 | CM16: 1 | CN16: 0 | CO16: FALSE | CP16: FALSE | CQ16: TRUE | CR16: FALSE | CS16: FALSE | CT16: FALSE | CU16: FALSE | CV16: 0 | CW16: 0 | CX16: 0 | CY16: 1 | CZ16: 1.02 | DA16: 5 | DB16: 5.08 | DC16: 5 | DD16: 0 | DE16: 0 | DF16: 4 | DG16: 4.07 | DH16: 1 | DI16: 1.02 | DJ16: 4 | DK16: 0 | DL16: 0 | DM16: 2 | DN16: 0 | DO16: 104 | DP16: 7 | DQ16: 7.11 | DR16: But it required new coherence structures to replace the old ones. | DS16: 1900: Ï‡ = 0.85 1965: Ï‡ = 0.72 Slow decline. | DT16: Ï‡ trajectory: 0.85 → 0.82 The move to cities wasn't inherently bad. | DU16: Ring 2 â€” Supporting Evidence Deeper dives and formal treatments No connections mapped yet. | DV16: Moral Decline of America • Theophysics Institute David Lowe • Theophysics Institute • 2024-2026 Previous Series Home Next Theophysics Home MDA-015 of 54 Related Work Core article, supporting evidence, and broader context Ring 1 â€” This Art | DW16: 0.71 | DX16: 0 | DY16: 2.17 | DZ16: 5 | EA16: 0 | EB16: 7.88 | EC16: D (Light) | ED16: F (Needs Citations) | EE16: 8.03 | EF16: HIGH | EG16: 0.1 | EH16: 1.83 | EI16: 0.056 | EJ16: KNOWLEDGE-DOMINANT | EK16: 1.02 | EL16: love | EM16: love:1, goodness:1, faithfulness:1, gentleness:1, humility:1 | EN16: 2.57 | EO16: C_christ_coherence | EP16: 0 | EQ16: 0 | ER16: 55.1 | ES16: C — Moderate | ET16: 1.69 | EU16: 4.4 | EV16: 2.71 | EW16: 3.39 | EX16: 0.68 | EY16: 1.02 | EZ16: 1.02 | FA16: 1.69 | FB16: 4.4 | FC16: 4.74 | FD16: not run (use --openai flag) | FE16: 95 | FF16: Reader Mode Standard, Standard, David Lowe • Theophysics Institute, Levittown, Civic | FG16: HTMl\K-Production-Ready\03-moral-decline\DEPLOY-READY\03-evidence-, Nobody Noticed, Secular, Mainline Protestant | FH16: Americans, Veterans, American, The Phase Transition | FI16: ORG, CARDINAL, WORK_OF_ART, PERSON, PRODUCT, GPE, DATE, PERCENT, ORDINAL, EVENT, NORP, LAW | FJ16: --- source_html: "\\dlowenas\HPWorkstation\Desktop\Master HTMl\K-Production-Ready\03-moral-decline\DEPLOY-READY\03-evidence-chronology\MDA-015-long-decline | FK16: html" deploy_relative: "03-evidence-chronology\MDA-015-long-decline | FL16: html" title: "The Long Decline | Moral Decline of America" --- The Long Decline | Moral Decline of America ﻿ The Long Decline | Moral Decline of America Home Home Previous | Next Series Home Reader | FM16: 0 | FN16: 0.4831 | FO16: 0.775 | FP16: 0.6057 | FQ16: 0.4324 | FR16: 0.0135 | FS16: 0.0405 | FT16: 0 | FU16: 0.0068 | FV16: 0.0622 | FW16: 0.0337 | FX16: 0 | FY16: 0.2799 | FZ16: 0 | GA16: 74 | GB16: 1 | GC16: 1 | GD16: 19 | GE16: 2 | GF16: 4 | GG16: 0 | GH16: 1 | GI16: 0 | GJ16: 1 | GK16: 0.1347 | GL16: 0 | GM16: 0 | GN16: 0 | GO16: 0 | GP16: 0.1347 | GQ16: 0 | GR16: 0 | GS16: 0 | GT16: 0 | GU16: 0 | GV16: 0 | GW16: 0 | GX16: 0 | GY16: 0 | GZ16: 0 | HA16: 0 | HB16: 0 | HC16: protective | HD16: 0 | HE16: 0 | HF16: 0 | HG16: 0 | HH16: 0 | HI16: protective | HJ16: 0 | HK16: 0 | HL16: 0 | HM16: 0 | HN16: 0 | HO16: protective | HP16: 0 | HQ16: 0 | HR16: 0 | HS16: 0 | HT16: 0 | HU16: protective | HV16: 0 | HW16: 0 | HX16: 0 | HY16: 0 | HZ16: 0 | IA16: threat | IB16: 0 | IC16: 0 | ID16: 0 | IE16: 0 | IF16: 0 | IG16: threat | IH16: 0 | II16: 0 | IJ16: 0 | IK16: 0 | IL16: 0 | IM16: threat | IN16: 0 | IO16: 0 | IP16: 0 | IQ16: 0 | IR16: 0 | IS16: threat | IT16: 0 | IU16: 0 | IV16: 0 | IW16: 0 | IX16: 0 | IY16: 0 | IZ16: 0 | JA16: 0 | JD16: mixed spiritual posture | JE16: coherent but cold; forceful and disciplined; technically strong, morally vacant; narrow but rigorous; publication-ready but adversarially incomplete | JF16: The Numbers Tell the Story Metric1900193019501965 Divorce rate0.71.62.62.5 Children with both parents95%90%88%85% Church attendance40%38%49%*42% Trust "most people"75%70%72%55% Civic org membership60%55%45%38% Multi-gen households25%18%12%8% *1950 church attendance spike was post-war anomaly, not trend reversal What Nobody Noticed The decline was invisible because: Economic growth masked it. | JG16: Wave 4: Suburbanization (1945–1965) What changed: Levittown model spreads nationwide Car ownership becomes universal White flight fragments urban communities Nuclear family becomes isolated unit Impact on Ï‡: Family: Extended family networks shattered Trust: Neighbors no longer share history Civic: Long commutes kill community involvement Intergenerational: Elderly separated from grandchildren Ï‡ trajectory: 0.76 → 0.72 The suburbs looked like the American Dream. | JH16: Who could see the pattern? | JI16: It could handle normal stress. | JJ16: 0.4833 | JK16: 0 | JL16: fallback: NRCLex not installed | JM16: 0 | JN16: 0 | JO16: 0 | JP16: 0 | JQ16: 0 | JR16: 0 | JS16: 0 | JT16: 0 | JU16: 0 | JV16: 0 | JX16: fallback: PreTrainedTokenizerFast._batch_encode_plus() got an unexpected keyword argument 'local_files_only' | JY16: 0 | JZ16: 0 | KA16: 1 | KB16: 0 | KC16: 0 | KD16: 1 | KE16: 0 | KF16: 0 | KG16: 1 | KH16: 0 | KI16: 0 | KJ16: 1 | KK16: 0 | KL16: 0 | KM16: 1 | KN16: 0 | KO16: 0 | KP16: 1 | KQ16: 0 | KR16: 0 | KS16: 1 | KT16: 0 | KU16: 0 | KV16: 1 | KW16: 0 | KX16: 0 | KY16: 1 | KZ16: 0 | LA16: 0 | LB16: 0 | LC16: 0 | LD16: 0 | LE16: 0 | LF16: 0 | LG16: 0 | LH16: 0 | LI16: 0 | LJ16: 0 | LK16: 0 | LN16: love | LO16: self_control | LP16: fallback: textdescriptives not installed | LQ16: 0.5424 | LR16: 16.2361 | LS16: 11.4807 | LT16: 896 | LU16: 486 | LV16: 139.0127 | LW16: 0.9117 | LX16: 0.6104 | LY16: 0.6104 | LZ16: 0.6104 | MA16: 0 | MB16: 542 | MC16: 1 | MD16: fallback: lexical proposition estimate | ME16: VERY HIGH (dense academic)
A17: P-dd73709327e1 | B17: MDA-016-thomas-1974.md | C17: BA-733478a8bf | D17: 20260530_220100 | E17: 2026.04.07-B | F17: C:\Users\lowes\Documents\Codex\2026-05-30\okay-let-find-the-open-ai\work\deploy_ready_extracted_md_20260530_220012\MDA-016-thomas-1974.md | G17: 2026-05-30T22:02:12.815208 | H17: C:\Users\lowes\Documents\Codex\2026-05-30\okay-let-find-the-open-ai\outputs\deploy_ready_full_pipeline_20260530\paper_intelligence\snapshots\P-dd73709327e1_snapshot.json | I17: L1:ok,L10:ok,L13:skipped,L2:ok,L3:ok,L4:skipped,L5:ok,L6:ok,L7:ok,L8:ok,L9:ok,PA:ok | J17: 3532 | K17: 1057 | L17: 0.2993 | M17: 313 | N17: 3 | O17: 1 | P17: 11.3 | Q17: 104.3 | R17: 14.9 | S17: 11.4 | T17: 5.1 | U17: 4 | V17: 6.7 | W17: 17 | X17: 3.3 | Y17: 19 | Z17: 3 | AA17: 6.33 | AB17: MIXED | AC17: FALSE | AD17: sentence-transformers not available | AE17: 0.4244 | AF17: MODERATE | AG17: 0.3151 | AH17: 0.0331 | AI17: 0.6622 | AJ17: textstat not available | AK17: 4.03 | AL17: 8 | AM17: HIGH | AN17: 0 | AO17: 0 | AP17: 4 | AQ17: 1.13 | AR17: 4 | AS17: 0 | AT17: A — Evidence-Rich | AU17: 22.4 | AV17: 70 | AW17: MODERATE | AX17: 18 | AY17: 5.1 | AZ17: 0 | BA17: 18 | BB17: 0 | BC17: 0 | BD17: 0 | BE17: 18 | BF17: 0 | BG17: 18 | BH17: 0 | BI17: 0 | BJ17: FALSE | BK17: FALSE | BL17: 3 | BM17: 3 | BN17: 2 | BO17: 1 | BP17: 0 | BQ17: 1 | BR17: 0 | BS17: 3532 | BT17: 1057 | BU17: 0.2993 | BV17: 3 | BW17: 1 | BX17: 1177.3 | BZ17: Reader Mode(0.0051) | Tommy(0.0051) | Academic Method(0.0088) | Bill(0.0108) | Master HTMl(0.0121) | Easy Plain-language(0.0129) | father(0.0161) | Current article(0.0209) | Plain-language bridge(0.0209) | Thomas Reader(0.0222) | Moral Decline(0.0303) | Thomas(0.0304) | CA17: his father | doesn know | the world | the way | and the | the same | CB17: find good woman | freedom became exit | good woman work | woman work stay | CC17: When Freedom Became Exit | Moral Decline of America | CD17: 0 | CE17: 0 | CF17: 0 | CG17: 0 | CH17: 1 | CI17: entropy | CJ17: 1 | CK17: 0.28 | CL17: 3/7 | CM17: 1 | CN17: 0 | CO17: FALSE | CP17: FALSE | CQ17: TRUE | CR17: TRUE | CS17: FALSE | CT17: TRUE | CU17: FALSE | CV17: 0 | CW17: 0 | CX17: 0 | CY17: 0 | CZ17: 0 | DA17: 4 | DB17: 1.13 | DC17: 4 | DD17: 0 | DE17: 0 | DF17: 4 | DG17: 1.13 | DH17: 25 | DI17: 7.08 | DJ17: 0.16 | DK17: 0 | DL17: 2 | DM17: 6 | DN17: 0 | DO17: 71 | DP17: 0 | DQ17: 0 | DR17: He is told he is "free," but he experiences this as a burden, because internal constraints must replace external ones, and the system has not prepared him for that. | DS17: What are you going to do?" Tommy shrugs. | DT17: He doesn't know how to hold it together. | DU17: Ring 2 — Supporting Evidence Deeper dives and formal treatments No connections mapped yet. | DV17: Previous Series Home Next Theophysics Home MDA-016 of 54 Related Work Core article, supporting evidence, and broader context Ring 1 — This Article The core argument You are here. | DW17: 2.14 | DX17: 0 | DY17: 2 | DZ17: 5 | EA17: 1 | EB17: 10.14 | EC17: D (Light) | ED17: F (Needs Citations) | EE17: 0.86 | EF17: WEAK | EG17: 0.14 | EH17: 0.37 | EI17: 0.385 | EJ17: KNOWLEDGE-DOMINANT | EK17: 2.55 | EL17: goodness | EM17: goodness:13, patience:10, gentleness:6, love:4, peace:3 | EN17: 1.09 | EO17: T_time_eternity | EP17: 0 | EQ17: 0 | ER17: 15.3 | ES17: F — Needs Work | ET17: 1.04 | EU17: 1.32 | EV17: 1.89 | EW17: 1.32 | EX17: 2.55 | EY17: 0.47 | EZ17: 0.38 | FA17: 0.38 | FB17: 0.66 | FC17: 0.94 | FD17: not run (use --openai flag) | FE17: 264 | FF17: Freedom Became Exit, Thomas Reader Mode Standard, Standard, Bill, Nixon | FG17: HTMl\K-Production-Ready\03-moral-decline\DEPLOY-READY\01-story-thread\MDA-016-thomas-1974.html, Saigon, Ford, Richland, Jake | FH17: American, Americans, Jake | FI17: ORG, CARDINAL, PERSON, WORK_OF_ART, PRODUCT, DATE, NORP, TIME, ORDINAL, EVENT, PERCENT, GPE, QUANTITY, MONEY | FJ17: --- source_html: "\\dlowenas\HPWorkstation\Desktop\Master HTMl\K-Production-Ready\03-moral-decline\DEPLOY-READY\01-story-thread\MDA-016-thomas-1974 | FK17: html" title: "When Freedom Became Exit | Moral Decline of America" --- When Freedom Became Exit | Moral Decline of America ﻿ When Freedom Became Exit | Moral Decline of America Home Home Previous | | FL17: Proof Pressure Layer Vetted Claims for MDA-016-thomas-1974 No promoted claim No claim from this article survived the deterministic Axiom + 7Q gate strongly enough for the proof layer yet | FM17: 0 | FN17: 0.4966 | FO17: 0.775 | FP17: 0.6135 | FQ17: 0.4543 | FR17: 0 | FS17: 0.0213 | FT17: 0 | FU17: 0.0197 | FV17: 0.1171 | FW17: 0.063 | FX17: 0.12 | FY17: 0.3594 | FZ17: 0.004 | GA17: 328 | GB17: 1 | GC17: 1 | GD17: 128 | GE17: 3 | GF17: 49 | GG17: 3 | GH17: 0 | GI17: 0 | GJ17: 0 | GK17: 0.108 | GL17: 0 | GM17: 0.072 | GN17: 0.1801 | GO17: 0 | GP17: 0.3962 | GQ17: 0.072 | GR17: 0.072 | GS17: 0.108 | GT17: 0 | GU17: 0 | GV17: 0 | GW17: 0 | GX17: 0.036 | GY17: 0 | GZ17: 0 | HA17: 0 | HB17: 0 | HC17: protective | HD17: 0 | HE17: 0 | HF17: 0 | HG17: 0 | HH17: 0 | HI17: protective | HJ17: 0 | HK17: 0 | HL17: 0 | HM17: 0 | HN17: 0 | HO17: protective | HP17: 0 | HQ17: 0 | HR17: 0 | HS17: 0 | HT17: 0 | HU17: protective | HV17: 0 | HW17: 0 | HX17: 0 | HY17: 0 | HZ17: 0 | IA17: threat | IB17: 0 | IC17: 0 | ID17: 0 | IE17: 0 | IF17: 0 | IG17: threat | IH17: 0 | II17: 0 | IJ17: 0 | IK17: 0 | IL17: 0 | IM17: threat | IN17: 0 | IO17: 0 | IP17: 0 | IQ17: 0 | IR17: 0 | IS17: threat | IT17: 0 | IU17: 0 | IV17: 0 | IW17: 0 | IX17: 0 | IY17: 0 | IZ17: 0 | JA17: 0 | JD17: spiritually ordered; technically strong, spiritually ordered | JE17: coherent but cold; forceful and disciplined; technically strong, morally vacant; narrow but rigorous; publication-ready but adversarially incomplete | JF17: He won't have to go to Vietnam, which is good because Vietnam is over, which is good because they lost anyway. | JG17: He just knows it's 1985, and his marriage is over, and his son is five years old, and the TV is on, and he has no idea what comes next. | JH17: maybe it sounds like peace? | JI17: Maybe community college. | JJ17: 0.3333 | JK17: 0 | JL17: fallback: NRCLex not installed | JM17: 0 | JN17: 0 | JO17: 0 | JP17: 0 | JQ17: 0 | JR17: 0 | JS17: 0 | JT17: 0 | JU17: 0 | JV17: 0 | JX17: fallback: PreTrainedTokenizerFast._batch_encode_plus() got an unexpected keyword argument 'local_files_only' | JY17: 0 | JZ17: 0 | KA17: 1 | KB17: 0 | KC17: 0 | KD17: 1 | KE17: 0 | KF17: 0 | KG17: 1 | KH17: 0 | KI17: 0 | KJ17: 1 | KK17: 0 | KL17: 0 | KM17: 1 | KN17: 0 | KO17: 0 | KP17: 1 | KQ17: 0 | KR17: 0 | KS17: 1 | KT17: 0 | KU17: 0 | KV17: 1 | KW17: 0 | KX17: 0 | KY17: 1 | KZ17: 0 | LA17: 0 | LB17: 0 | LC17: 0 | LD17: 0 | LE17: 0 | LF17: 0 | LG17: 0 | LH17: 0 | LI17: 0 | LJ17: 0 | LK17: 0 | LN17: love | LO17: self_control | LP17: fallback: textdescriptives not installed | LQ17: 0.2839 | LR17: 16.9348 | LS17: 11.9747 | LT17: 3557 | LU17: 1010 | LV17: 68.4434 | LW17: 0.8502 | LX17: 0.4642 | LY17: 0.4642 | LZ17: 0.4642 | MA17: 0 | MB17: 1587 | MC17: 1 | MD17: fallback: lexical proposition estimate | ME17: HIGH (academic)
A18: P-58a9cda404de | B18: MDA-017-unraveling-1960.md | C18: BA-733478a8bf | D18: 20260530_220100 | E18: 2026.04.07-B | F18: C:\Users\lowes\Documents\Codex\2026-05-30\okay-let-find-the-open-ai\work\deploy_ready_extracted_md_20260530_220012\MDA-017-unraveling-1960.md | G18: 2026-05-30T22:02:15.565294 | H18: C:\Users\lowes\Documents\Codex\2026-05-30\okay-let-find-the-open-ai\outputs\deploy_ready_full_pipeline_20260530\paper_intelligence\snapshots\P-58a9cda404de_snapshot.json | I18: L1:ok,L10:ok,L13:skipped,L2:ok,L3:ok,L4:skipped,L5:ok,L6:ok,L7:ok,L8:ok,L9:ok,PA:ok | J18: 1648 | K18: 702 | L18: 0.426 | M18: 56 | N18: 3 | O18: 1 | P18: 29.4 | Q18: 18.7 | R18: 19.9 | S18: 6.4 | T18: 10.5 | U18: 2.9 | V18: 8.4 | W18: 5 | X18: 3.9 | Y18: 2 | Z18: 0 | AA18: 2 | AB18: MIXED | AC18: FALSE | AD18: sentence-transformers not available | AE18: 0.4337 | AF18: MODERATE | AG18: 0.2451 | AH18: 0.034 | AI18: 0.7292 | AJ18: textstat not available | AK18: 6.37 | AL18: 14 | AM18: HIGH | AN18: 0 | AO18: 0 | AP18: 32 | AQ18: 19.42 | AR18: 32 | AS18: 0 | AT18: A — Evidence-Rich | AU18: 39.3 | AV18: 22 | AW18: HIGH | AX18: 33 | AY18: 20.02 | AZ18: 24 | BA18: 9 | BB18: 0 | BC18: 0 | BD18: 0 | BE18: 9 | BF18: 24 | BG18: 0.38 | BH18: 0 | BI18: 0 | BJ18: FALSE | BK18: FALSE | BL18: 3 | BM18: 3 | BN18: 2 | BO18: 1 | BP18: 0 | BQ18: 1 | BR18: 0 | BS18: 1648 | BT18: 702 | BU18: 0.426 | BV18: 3 | BW18: 1 | BX18: 549.3 | BZ18: Mode Standard(0.003) | Standard Current(0.003) | Reader Mode(0.0048) | Academic Method(0.0082) | Unraveling Begins(0.0098) | Moral(0.0102) | Master HTMl(0.0104) | pressure Standard(0.0115) | Easy Plain-language(0.0119) | Vietnam War(0.0128) | Standard(0.0142) | high school(0.0157) | CA18: was the | high school | the unraveling | vietnam war | the moral | trust government | CB18: the most influential | the unraveling begins | high school graduation | school graduation rate | CC18: The Unraveling Begins | Moral Decline of America | CD18: 24 | CE18: 2 | CF18: 22 | CG18: 14.55 | CH18: 1 | CI18: emergence | CJ18: 2 | CK18: 1.21 | CL18: 3/7 | CM18: 1 | CN18: 0 | CO18: FALSE | CP18: FALSE | CQ18: TRUE | CR18: TRUE | CS18: FALSE | CT18: TRUE | CU18: FALSE | CV18: 0 | CW18: 0 | CX18: 0 | CY18: 0 | CZ18: 0 | DA18: 34 | DB18: 20.62 | DC18: 34 | DD18: 0 | DE18: 0 | DF18: 1 | DG18: 0.61 | DH18: 2 | DI18: 1.21 | DJ18: 0.5 | DK18: 0 | DL18: 0 | DM18: 4 | DN18: 0 | DO18: 152 | DP18: 1 | DQ18: 0.61 | DR18: The next five years would pull them apart. | DS18: It started at peak trust â€” and ran out of it in seven years. | DT18: From that ridge, the next half-century is a single descending line. | DU18: [20]Gallup â€” Four in 10 Report Attending Church in Last Week [21]Congress.gov â€” Brief Examination of Union Membership Data [23]PBS American Experience â€” Kinsey in the News [24]ECU â€” Kinsey: A Controversial Seller [25]Rockefeller Arc | DV18: Part 1 Â· Verified Statistical Data (1960â€“1967) Family Structure Median age first marriage (Male, 1960)22.8 yrs Median age first marriage (Female, 1960)20.3 yrs Crude divorce rate (1955â€“63 â†’ 1967)2.1 â†’ 2.6 Divorces / 1,000 married w | DW18: 2.14 | DX18: 5 | DY18: 2 | DZ18: 5 | EA18: 0 | EB18: 14.14 | EC18: C (Developing) | ED18: B (Strong) | EE18: 1.52 | EF18: WEAK | EG18: 0.12 | EH18: 1.21 | EI18: 0.1 | EJ18: KNOWLEDGE-DOMINANT | EK18: 0.73 | EL18: peace | EM18: peace:3, goodness:2, hope:1, love:0, joy:0 | EN18: 1.31 | EO18: F_faith_coupling | EP18: 0 | EQ18: 1 | ER18: 100 | ES18: A — Publication Grade | ET18: 0 | EU18: 3.03 | EV18: 1.41 | EW18: 1.21 | EX18: 1.21 | EY18: 0 | EZ18: 0.61 | FA18: 1.01 | FB18: 4.04 | FC18: 0.61 | FD18: not run (use --openai flag) | FE18: 189 | FF18: Reader Mode Standard, Standard, David Lowe • Theophysics Institute, Avg, Household | FG18: HTMl\K-Production-Ready\03-moral-decline\DEPLOY-READY\03-evidence-chronology\MDA-017-unraveling-1960.html, Sexuality Men, Premarital, Media & Technology, Religious & Institutional Weekly | FH18: Enovid, democratic, American, Americans | FI18: ORG, CARDINAL, WORK_OF_ART, PERSON, PRODUCT, DATE, EVENT, PERCENT, ORDINAL, GPE, TIME, NORP, LAW, FAC | FJ18: --- source_html: "\\dlowenas\HPWorkstation\Desktop\Master HTMl\K-Production-Ready\03-moral-decline\DEPLOY-READY\03-evidence-chronology\MDA-017-unraveling-1960 | FK18: html" deploy_relative: "03-evidence-chronology\MDA-017-unraveling-1960 | FL18: html" title: "The Unraveling Begins | Moral Decline of America" --- The Unraveling Begins | Moral Decline of America ﻿ The Unraveling Begins | Moral Decline of America Home Home Previous | Next Seri | FM18: 0 | FN18: 0.6263 | FO18: 0.775 | FP18: 0.6887 | FQ18: 0.6964 | FR18: 0 | FS18: 0 | FT18: 0 | FU18: 0 | FV18: 0.1964 | FW18: 0 | FX18: 0.0275 | FY18: 0.2592 | FZ18: 0 | GA18: 56 | GB18: 1 | GC18: 1 | GD18: 49 | GE18: 0 | GF18: 12 | GG18: 0 | GH18: 0 | GI18: 0 | GJ18: 0 | GK18: 0 | GL18: 0 | GM18: 0 | GN18: 0 | GO18: 0 | GP18: 0 | GQ18: 0 | GR18: 0 | GS18: 0.0824 | GT18: 0 | GU18: 0 | GV18: 0 | GW18: 0 | GX18: 0 | GY18: 0 | GZ18: 0 | HA18: 0 | HB18: 0 | HC18: protective | HD18: 0 | HE18: 0 | HF18: 0 | HG18: 0 | HH18: 0 | HI18: protective | HJ18: 0 | HK18: 0 | HL18: 0 | HM18: 0 | HN18: 0 | HO18: protective | HP18: 0 | HQ18: 0 | HR18: 0 | HS18: 0 | HT18: 0 | HU18: protective | HV18: 0 | HW18: 0 | HX18: 0 | HY18: 0 | HZ18: 0 | IA18: threat | IB18: 0 | IC18: 0 | ID18: 0 | IE18: 0 | IF18: 0 | IG18: threat | IH18: 0 | II18: 0 | IJ18: 0 | IK18: 0 | IL18: 0 | IM18: threat | IN18: 0 | IO18: 0 | IP18: 0 | IQ18: 0 | IR18: 0 | IS18: threat | IT18: 0 | IU18: 0 | IV18: 0 | IW18: 0 | IX18: 0 | IY18: 0 | IZ18: 0 | JA18: 0 | JD18: mixed spiritual posture | JE18: coherent but cold; forceful and disciplined; precise but lifeless; technically strong, morally vacant; publication-ready but adversarially incomplete | JF18: [20]Gallup â€” Four in 10 Report Attending Church in Last Week [21]Congress.gov â€” Brief Examination of Union Membership Data [23]PBS American Experience â€” Kinsey in the News [24]ECU â€” Kinsey: A Controversial Seller [25]Rockefeller Archive â€” Funding a Sexual Revolution: The Kinsey Reports [26]Harvard DASH â€” America's Graduation from High School [27]InfoPlease â€” Median Age at First Marriage 15 + 15 = 100 David Lowe • Theophysics Institute Previous Series Home Next Theophysics Home MDA-017 of 54 Related Work Core article, supporting evidence, and broader context Ring 1 â€” This Article The core argument You are here. | JG18: The moral trajectory of 1960â€“1967 is defined by the transfer of moral authority from centralized institutions â€” Church, State, Nuclear Family â€” to the autonomous individual and emerging counter-cultural movements. | JH18: The unraveling did not break the rope. | JI18: This solidified the creation of the mass-educated, critically aware citizen. | JJ18: 0.4 | JK18: 0 | JL18: fallback: NRCLex not installed | JM18: 0 | JN18: 0 | JO18: 0 | JP18: 0 | JQ18: 0 | JR18: 0 | JS18: 0 | JT18: 0 | JU18: 0 | JV18: 0 | JX18: fallback: PreTrainedTokenizerFast._batch_encode_plus() got an unexpected keyword argument 'local_files_only' | JY18: 0 | JZ18: 0 | KA18: 1 | KB18: 0 | KC18: 0 | KD18: 1 | KE18: 0 | KF18: 0 | KG18: 1 | KH18: 0 | KI18: 0 | KJ18: 1 | KK18: 0 | KL18: 0 | KM18: 1 | KN18: 0 | KO18: 0 | KP18: 1 | KQ18: 0 | KR18: 0 | KS18: 1 | KT18: 0 | KU18: 0 | KV18: 1 | KW18: 0 | KX18: 0 | KY18: 1 | KZ18: 0 | LA18: 0 | LB18: 0 | LC18: 0 | LD18: 0 | LE18: 0 | LF18: 0 | LG18: 0 | LH18: 0 | LI18: 0 | LJ18: 0 | LK18: 0 | LN18: love | LO18: self_control | LP18: fallback: textdescriptives not installed | LQ18: 0.4162 | LR18: 16.1019 | LS18: 11.3858 | LT18: 1497 | LU18: 623 | LV18: 109.8505 | LW18: 0.8824 | LX18: 0.5121 | LY18: 0.5121 | LZ18: 0.5121 | MA18: 0 | MB18: 763 | MC18: 1 | MD18: fallback: lexical proposition estimate | ME18: HIGH (academic)
A19: P-3a2228a446d2 | B19: MDA-018-great-decoupling-1968.md | C19: BA-733478a8bf | D19: 20260530_220100 | E19: 2026.04.07-B | F19: C:\Users\lowes\Documents\Codex\2026-05-30\okay-let-find-the-open-ai\work\deploy_ready_extracted_md_20260530_220012\MDA-018-great-decoupling-1968.md | G19: 2026-05-30T22:02:17.032837 | H19: C:\Users\lowes\Documents\Codex\2026-05-30\okay-let-find-the-open-ai\outputs\deploy_ready_full_pipeline_20260530\paper_intelligence\snapshots\P-3a2228a446d2_snapshot.json | I19: L1:ok,L10:ok,L13:skipped,L2:ok,L3:ok,L4:skipped,L5:ok,L6:ok,L7:ok,L8:ok,L9:ok,PA:ok | J19: 2767 | K19: 1032 | L19: 0.373 | M19: 154 | N19: 3 | O19: 1 | P19: 18 | Q19: 51.3 | R19: 20.3 | S19: 7.5 | T19: 10.4 | U19: 2.9 | V19: 9.8 | W19: 11 | X19: 4.3 | Y19: 6 | Z19: 2 | AA19: 3 | AB19: CONCEPTUAL | AC19: FALSE | AD19: sentence-transformers not available | AE19: 0.415 | AF19: MODERATE | AG19: 0.3097 | AH19: 0.0325 | AI19: 0.6679 | AJ19: textstat not available | AK19: 5.2 | AL19: 10 | AM19: HIGH | AN19: 0 | AO19: 0 | AP19: 9 | AQ19: 3.25 | AR19: 9 | AS19: 1 | AT19: A — Evidence-Rich | AU19: 24.7 | AV19: 38 | AW19: MODERATE | AX19: 15 | AY19: 5.42 | AZ19: 0 | BA19: 14 | BB19: 0 | BC19: 1 | BD19: 0 | BE19: 14 | BF19: 0 | BG19: 14 | BH19: 0 | BI19: 0.53 | BJ19: FALSE | BK19: FALSE | BL19: 3 | BM19: 3 | BN19: 2 | BO19: 1 | BP19: 0 | BQ19: 1 | BR19: 0 | BS19: 2767 | BT19: 1032 | BU19: 0.373 | BV19: 3 | BW19: 1 | BX19: 922.3 | BZ19: Reader Mode(0.0049) | Academic Method(0.0083) | Great Decoupling(0.0092) | Master HTMl(0.0108) | Easy Plain-language(0.0121) | authority(0.0156) | traditional(0.0183) | Plain-language bridge(0.0189) | Current article(0.0192) | Moral(0.0228) | Home Reader(0.0234) | trust(0.0246) | CA19: was not | and the | great decoupling | was the | the great | post war | CB19: the great decoupling | mda great decoupling | great decoupling moral | decoupling moral decline | CC19: The Great Decoupling | Moral Decline of America | CD19: 0 | CE19: 0 | CF19: 0 | CG19: 0 | CH19: 1 | CI19: complexity | CJ19: 4 | CK19: 1.45 | CL19: 2/7 | CM19: 1 | CN19: 0 | CO19: TRUE | CP19: FALSE | CQ19: TRUE | CR19: FALSE | CS19: FALSE | CT19: FALSE | CU19: FALSE | CV19: 0 | CW19: 0 | CX19: 0 | CY19: 0 | CZ19: 0 | DA19: 9 | DB19: 3.25 | DC19: 9 | DD19: 1 | DE19: 0.36 | DF19: 0 | DG19: 0 | DH19: 10 | DI19: 3.61 | DJ19: 0 | DK19: 1 | DL19: 0 | DM19: 16 | DN19: 0 | DO19: 151 | DP19: 1 | DQ19: 0.36 | DR19: 15 + 15 = 100 David Lowe • Theophysics Institute Previous Series Home Next Theophysics Home MDA-018 of 54 Related Work Core article, supporting evidence, and broader context Ring 1 â€” This Article The core argument You are here. | DS19: The period culminated in the 1973 Roe v. | DT19: Trust would never return to its 1964 level. | DU19: 15 + 15 = 100 David Lowe • Theophysics Institute Previous Series Home Next Theophysics Home MDA-018 of 54 Related Work Core article, supporting evidence, and broader context Ring 1 â€” This Article The core argument You are here. | DV19: The Costs of Liberation The data reveals a counter-intuitive story. | DW19: 1.43 | DX19: 0 | DY19: 2 | DZ19: 5 | EA19: 1.5 | EB19: 9.93 | EC19: D (Light) | ED19: D (Light) | EE19: 1.39 | EF19: WEAK | EG19: 0.18 | EH19: 0.65 | EI19: 0.278 | EJ19: KNOWLEDGE-DOMINANT | EK19: 0.65 | EL19: peace | EM19: peace:7, goodness:1, gentleness:1, love:0, joy:0 | EN19: 1.1 | EO19: F_faith_coupling | EP19: 0 | EQ19: 0 | ER19: 23.9 | ES19: D — Developing | ET19: 0.84 | EU19: 1.32 | EV19: 0.96 | EW19: 1.08 | EX19: 1.2 | EY19: 0.12 | EZ19: 0.84 | FA19: 0.6 | FB19: 3.13 | FC19: 0.96 | FD19: not run (use --openai flag) | FE19: 260 | FF19: Reader Mode Standard, Standard, David Lowe • Theophysics Institute, Tet Offensive, Johnson | FG19: HTMl\K-Production-Ready\03-moral-decline\DEPLOY-READY\03-evidence-chronology\MDA-018-great-decoupling-1968.html, The Total Fertility Rate, Nixon Shock, Howard University, Chicago DNC | FH19: American, Americans, Christian, Roe v. Wade | FI19: ORG, CARDINAL, WORK_OF_ART, PERSON, PRODUCT, FAC, DATE, GPE, NORP, EVENT, PERCENT, LAW, LOC, ORDINAL, QUANTITY, MONEY | FJ19: --- source_html: "\\dlowenas\HPWorkstation\Desktop\Master HTMl\K-Production-Ready\03-moral-decline\DEPLOY-READY\03-evidence-chronology\MDA-018-great-decoupling-1968 | FK19: html" deploy_relative: "03-evidence-chronology\MDA-018-great-decoupling-1968 | FL19: html" title: "The Great Decoupling | Moral Decline of America" --- The Great Decoupling | Moral Decline of America ﻿ The Great Decoupling | Moral Decline of America Home Home Previous | Next Series | FM19: 0 | FN19: 0.5621 | FO19: 0.775 | FP19: 0.6515 | FQ19: 0.5613 | FR19: 0 | FS19: 0 | FT19: 0 | FU19: 0.0119 | FV19: 0.151 | FW19: 0.0241 | FX19: 0 | FY19: 0.2626 | FZ19: 0.0054 | GA19: 155 | GB19: 1 | GC19: 1 | GD19: 105 | GE19: 1 | GF19: 37 | GG19: 0 | GH19: 0 | GI19: 0 | GJ19: 0 | GK19: 0 | GL19: 0 | GM19: 0.0964 | GN19: 0 | GO19: 0 | GP19: 0.0482 | GQ19: 0 | GR19: 0 | GS19: 0 | GT19: 0 | GU19: 0 | GV19: 0.0482 | GW19: 0 | GX19: 0 | GY19: 0 | GZ19: 0 | HA19: 0 | HB19: 0 | HC19: protective | HD19: 0 | HE19: 0 | HF19: 0 | HG19: 0 | HH19: 0 | HI19: protective | HJ19: 0 | HK19: 0 | HL19: 0 | HM19: 0 | HN19: 0 | HO19: protective | HP19: 0 | HQ19: 0 | HR19: 0 | HS19: 0 | HT19: 0 | HU19: protective | HV19: 0 | HW19: 0 | HX19: 0 | HY19: 0 | HZ19: 0 | IA19: threat | IB19: 0 | IC19: 0 | ID19: 0 | IE19: 0 | IF19: 0 | IG19: threat | IH19: 0 | II19: 0 | IJ19: 0 | IK19: 0 | IL19: 0 | IM19: threat | IN19: 0 | IO19: 0 | IP19: 0 | IQ19: 0 | IR19: 0 | IS19: threat | IT19: 0 | IU19: 0 | IV19: 0 | IW19: 0 | IX19: 0 | IY19: 0 | IZ19: 0 | JA19: 0 | JD19: mixed spiritual posture | JE19: coherent but cold; forceful and disciplined; precise but lifeless; technically strong, morally vacant; narrow but rigorous | JF19: 15 + 15 = 100 David Lowe • Theophysics Institute Previous Series Home Next Theophysics Home MDA-018 of 54 Related Work Core article, supporting evidence, and broader context Ring 1 â€” This Article The core argument You are here. | JG19: While some pathologies worsened, others peaked in 1970 and then declined â€” not because of a return to traditional values, but because of new technocratic interventions. | JH19: It has, with few exceptions, never recovered. | JI19: The divorce rate accelerated. | JJ19: 0.4 | JK19: 0 | JL19: fallback: NRCLex not installed | JM19: 0 | JN19: 0 | JO19: 0 | JP19: 0 | JQ19: 0 | JR19: 0 | JS19: 0 | JT19: 0 | JU19: 0 | JV19: 0 | JX19: fallback: PreTrainedTokenizerFast._batch_encode_plus() got an unexpected keyword argument 'local_files_only' | JY19: 0 | JZ19: 0 | KA19: 1 | KB19: 0 | KC19: 0 | KD19: 1 | KE19: 0 | KF19: 0 | KG19: 1 | KH19: 0 | KI19: 0 | KJ19: 1 | KK19: 0 | KL19: 0 | KM19: 1 | KN19: 0 | KO19: 0 | KP19: 1 | KQ19: 0 | KR19: 0 | KS19: 1 | KT19: 0 | KU19: 0 | KV19: 1 | KW19: 0 | KX19: 0 | KY19: 1 | KZ19: 0 | LA19: 0 | LB19: 0 | LC19: 0 | LD19: 0 | LE19: 0 | LF19: 0 | LG19: 0 | LH19: 0 | LI19: 0 | LJ19: 0 | LK19: 0 | LN19: love | LO19: self_control | LP19: fallback: textdescriptives not installed | LQ19: 0.3655 | LR19: 18.6523 | LS19: 13.1892 | LT19: 2605 | LU19: 952 | LV19: 93.5128 | LW19: 0.8788 | LX19: 0.5042 | LY19: 0.5042 | LZ19: 0.5042 | MA19: 0 | MB19: 1307 | MC19: 1 | MD19: fallback: lexical proposition estimate | ME19: HIGH (academic)
A20: P-5349e862c92a | B20: MDA-019-current-state-2024.md | C20: BA-733478a8bf | D20: 20260530_220100 | E20: 2026.04.07-B | F20: C:\Users\lowes\Documents\Codex\2026-05-30\okay-let-find-the-open-ai\work\deploy_ready_extracted_md_20260530_220012\MDA-019-current-state-2024.md | G20: 2026-05-30T22:02:19.422413 | H20: C:\Users\lowes\Documents\Codex\2026-05-30\okay-let-find-the-open-ai\outputs\deploy_ready_full_pipeline_20260530\paper_intelligence\snapshots\P-5349e862c92a_snapshot.json | I20: L1:ok,L10:ok,L13:skipped,L2:ok,L3:ok,L4:skipped,L5:ok,L6:ok,L7:ok,L8:ok,L9:ok,PA:ok | J20: 2242 | K20: 1009 | L20: 0.45 | M20: 130 | N20: 3 | O20: 1 | P20: 17.2 | Q20: 43.3 | R20: 21.1 | S20: 7.6 | T20: 8.8 | U20: 3.2 | V20: 8.3 | W20: 5 | X20: 2.4 | Y20: 7 | Z20: 0 | AA20: 7 | AB20: CONCEPTUAL | AC20: FALSE | AD20: sentence-transformers not available | AE20: 0.455 | AF20: MODERATE | AG20: 0.2814 | AH20: 0.0259 | AI20: 0.7 | AJ20: textstat not available | AK20: 4.9 | AL20: 10 | AM20: HIGH | AN20: 0 | AO20: 0 | AP20: 18 | AQ20: 8.03 | AR20: 18 | AS20: 0 | AT20: A — Evidence-Rich | AU20: 18.5 | AV20: 24 | AW20: MODERATE | AX20: 8 | AY20: 3.57 | AZ20: 0 | BA20: 8 | BB20: 0 | BC20: 0 | BD20: 0 | BE20: 8 | BF20: 0 | BG20: 8 | BH20: 0 | BI20: 0.1 | BJ20: FALSE | BK20: FALSE | BL20: 3 | BM20: 3 | BN20: 2 | BO20: 1 | BP20: 0 | BQ20: 1 | BR20: 0 | BS20: 2242 | BT20: 1009 | BU20: 0.45 | BV20: 3 | BW20: 1 | BX20: 747.3 | BZ20: Amish(0.0025) | Amish population(0.0034) | Moral Decline(0.0042) | Reader Mode(0.0047) | Academic Method(0.0079) | Holmes County(0.0095) | Master HTMl(0.0097) | Easy Plain-language(0.0114) | population(0.0117) | American Amish(0.0121) | Moral(0.0132) | Amish live(0.0157) | CA20: the amish | and the | current state | for the | the population | the same | CB20: where coherence still | coherence still lives | the amish population | mda current state | CC20: Where Coherence Still Lives | Moral Decline of America | CD20: 0 | CE20: 0 | CF20: 0 | CG20: 0 | CH20: 0 | CJ20: 4 | CK20: 1.78 | CL20: 3/7 | CM20: 1 | CN20: 0 | CO20: FALSE | CP20: FALSE | CQ20: TRUE | CR20: TRUE | CS20: TRUE | CT20: FALSE | CU20: FALSE | CV20: 0 | CW20: 0 | CX20: 0 | CY20: 1 | CZ20: 0.45 | DA20: 18 | DB20: 8.02 | DC20: 18 | DD20: 1 | DE20: 0.45 | DF20: 8 | DG20: 3.57 | DH20: 5 | DI20: 2.23 | DJ20: 1.6 | DK20: 0 | DL20: 1 | DM20: 7 | DN20: 0 | DO20: 181 | DP20: 9 | DQ20: 4.01 | DR20: The Doubling Function A central concept in Amish demography is doubling time â€” the years required for the population to grow by 100%. | DS20: But it also points to a real demographic: the “Lunch Pail” Amish, men with no land and no business who must work hourly wages in factories. | DT20: 15 + 15 = 100 David Lowe • Theophysics Institute Previous Series Home Next Theophysics Home MDA-019 of 54 Related Work Core article, supporting evidence, and broader context Ring 1 â€” This Article The core argument You are here. | DU20: 15 + 15 = 100 David Lowe • Theophysics Institute Previous Series Home Next Theophysics Home MDA-019 of 54 Related Work Core article, supporting evidence, and broader context Ring 1 â€” This Article The core argument You are here. | DV20: The result is a population pyramid with an exceptionally broad base. | DW20: 2.14 | DX20: 0 | DY20: 2.17 | DZ20: 5 | EA20: 1.5 | EB20: 10.81 | EC20: D (Light) | ED20: F (Needs Citations) | EE20: 2.01 | EF20: WEAK | EG20: 0.09 | EH20: 1.16 | EI20: 0.077 | EJ20: KNOWLEDGE-DOMINANT | EK20: 0.98 | EL20: peace | EM20: peace:3, gentleness:2, hope:2, love:1, goodness:1 | EN20: 0.94 | EO20: E_entropy_engagement | EP20: 0 | EQ20: 0 | ER20: 31 | ES20: D — Developing | ET20: 0.74 | EU20: 0.89 | EV20: 2.08 | EW20: 1.19 | EX20: 1.19 | EY20: 0.15 | EZ20: 1.19 | FA20: 0.3 | FB20: 0.3 | FC20: 1.34 | FD20: not run (use --openai flag) | FE20: 244 | FF20: Reader Mode Standard, Standard, David Lowe • Theophysics Institute, Amish, Ordnung | FG20: HTMl\K-Production-Ready\03-moral-decline\DEPLOY-READY\03-evidence-chronology\MDA-019, Gallup, CDC, The U.S. Census Bureau, the Young Center for Anabaptist | FH20: American, North American, Amish, New Order Amish | FI20: ORG, CARDINAL, PERSON, WORK_OF_ART, PRODUCT, NORP, DATE, PERCENT, MONEY, GPE, ORDINAL, QUANTITY, LOC, LANGUAGE, TIME | FJ20: --- source_html: "\\dlowenas\HPWorkstation\Desktop\Master HTMl\K-Production-Ready\03-moral-decline\DEPLOY-READY\03-evidence-chronology\MDA-019-current-state-2024 | FK20: html" deploy_relative: "03-evidence-chronology\MDA-019-current-state-2024 | FL20: html" title: "Where Coherence Still Lives | Moral Decline of America" --- Where Coherence Still Lives | Moral Decline of America ﻿ Where Coherence Still Lives | Moral Decline of America Home Home Pr | FM20: 0 | FN20: 0.6022 | FO20: 0.775 | FP20: 0.6748 | FQ20: 0.6718 | FR20: 0 | FS20: 0.0305 | FT20: 0 | FU20: 0.0029 | FV20: 0.2122 | FW20: 0.0147 | FX20: 0 | FY20: 0.2565 | FZ20: 0 | GA20: 131 | GB20: 1 | GC20: 1 | GD20: 93 | GE20: 2 | GF20: 23 | GG20: 0 | GH20: 1 | GI20: 0 | GJ20: 0 | GK20: 0 | GL20: 0 | GM20: 0.0588 | GN20: 0 | GO20: 0 | GP20: 0 | GQ20: 0 | GR20: 0 | GS20: 0 | GT20: 0 | GU20: 0 | GV20: 0 | GW20: 0 | GX20: 0 | GY20: 0 | GZ20: 0 | HA20: 0 | HB20: 0 | HC20: protective | HD20: 0 | HE20: 0 | HF20: 0 | HG20: 0 | HH20: 0 | HI20: protective | HJ20: 0 | HK20: 0 | HL20: 0 | HM20: 0 | HN20: 0 | HO20: protective | HP20: 0 | HQ20: 0 | HR20: 0 | HS20: 0 | HT20: 0 | HU20: protective | HV20: 0 | HW20: 0 | HX20: 0 | HY20: 0 | HZ20: 0 | IA20: threat | IB20: 0 | IC20: 0 | ID20: 0 | IE20: 0 | IF20: 0 | IG20: threat | IH20: 0 | II20: 0 | IJ20: 0 | IK20: 0 | IL20: 0 | IM20: threat | IN20: 0 | IO20: 0 | IP20: 0 | IQ20: 0 | IR20: 0 | IS20: threat | IT20: 0 | IU20: 0 | IV20: 0 | IW20: 0 | IX20: 0 | IY20: 0 | IZ20: 0 | JA20: 0 | JD20: mixed spiritual posture | JE20: coherent but cold; forceful and disciplined; precise but lifeless; technically strong, morally vacant; publication-ready but adversarially incomplete | JF20: Differential fertility means the Amish population is not simply growing; it is becoming statistically more conservative over time, because the strictest subgroups reproduce fastest. | JG20: Because in the same country, on the same calendar, in the same year, there is a population doing the inverse: doubling every twenty years, retaining 85 to 97 percent of its youth, and accumulating capital fast enough that its primary bank crossed $1.5 billion in assets in 2024. | JH20: Without high retention, no fertility rate could keep up. | JI20: Rumspringa â€” the adolescent period of relative freedom â€” appears to function as inoculation: youth experience the world enough to make an informed, usually affirmative, return. | JJ20: 0.6 | JK20: 0 | JL20: fallback: NRCLex not installed | JM20: 0 | JN20: 0 | JO20: 0 | JP20: 0 | JQ20: 0 | JR20: 0 | JS20: 0 | JT20: 0 | JU20: 0 | JV20: 0 | JX20: fallback: PreTrainedTokenizerFast._batch_encode_plus() got an unexpected keyword argument 'local_files_only' | JY20: 0 | JZ20: 0 | KA20: 1 | KB20: 0 | KC20: 0 | KD20: 1 | KE20: 0 | KF20: 0 | KG20: 1 | KH20: 0 | KI20: 0 | KJ20: 1 | KK20: 0 | KL20: 0 | KM20: 1 | KN20: 0 | KO20: 0 | KP20: 1 | KQ20: 0 | KR20: 0 | KS20: 1 | KT20: 0 | KU20: 0 | KV20: 1 | KW20: 0 | KX20: 0 | KY20: 1 | KZ20: 0 | LA20: 0 | LB20: 0 | LC20: 0 | LD20: 0 | LE20: 0 | LF20: 0 | LG20: 0 | LH20: 0 | LI20: 0 | LJ20: 0 | LK20: 0 | LN20: love | LO20: self_control | LP20: fallback: textdescriptives not installed | LQ20: 0.4375 | LR20: 20.182 | LS20: 14.2708 | LT20: 2128 | LU20: 931 | LV20: 109.2 | LW20: 0.8933 | LX20: 0.531 | LY20: 0.531 | LZ20: 0.531 | MA20: 0 | MB20: 1130 | MC20: 1 | MD20: fallback: lexical proposition estimate | ME20: HIGH (academic)
